{"pagelen": 50, "values": [{"comment": {"links": {"self": {"href": "data/repositories/osrf/gazebo/pullrequests/1974/comments/12038916.json"}, "html": {"href": "#!/osrf/gazebo/pull-requests/1974/_/diff#comment-12038916"}}, "deleted": false, "pullrequest": {"type": "pullrequest", "id": 1974, "links": {"self": {"href": "data/repositories/osrf/gazebo/pullrequests/1974.json"}, "html": {"href": "#!/osrf/gazebo/pull-requests/1974"}}, "title": "Elastic_modulus"}, "content": {"raw": "if this is using the new elements, then we need to require sdformat 3.7 when we `find_package`. I'll create a new pull request", "markup": "markdown", "html": "<p>if this is using the new elements, then we need to require sdformat 3.7 when we <code>find_package</code>. I'll create a new pull request</p>", "type": "rendered"}, "created_on": "2015-11-21T00:37:55.129962+00:00", "user": {"display_name": "Steve Peters", "uuid": "{2ccfed09-18b8-4921-8d58-15ef01092802}", "links": {"self": {"href": "https://api.bitbucket.org/2.0/users/%7B2ccfed09-18b8-4921-8d58-15ef01092802%7D"}, "html": {"href": "https://bitbucket.org/%7B2ccfed09-18b8-4921-8d58-15ef01092802%7D/"}, "avatar": {"href": "data/secure.gravatar.com/avatar/1fb4816dad9e68337d3096f750951f6cd=httpsavatar-management--avatars.us-west-2.prod.public.atl-paas.netinitialsSP-1.png"}}, "nickname": "Steven Peters", "type": "user", "account_id": "557058:5de38267-b118-494c-aa76-4fab35448816"}, "inline": {}, "updated_on": "2015-11-21T00:37:55.132084+00:00", "type": "pullrequest_comment", "id": 12038916}, "pull_request": {"type": "pullrequest", "id": 1974, "links": {"self": {"href": "data/repositories/osrf/gazebo/pullrequests/1974.json"}, "html": {"href": "#!/osrf/gazebo/pull-requests/1974"}}, "title": "Elastic_modulus"}}, {"comment": {"links": {"self": {"href": "data/repositories/osrf/gazebo/pullrequests/1974/comments/11999847.json"}, "html": {"href": "#!/osrf/gazebo/pull-requests/1974/_/diff#comment-11999847"}}, "parent": {"id": 11999575, "links": {"self": {"href": "data/repositories/osrf/gazebo/pullrequests/1974/comments/11999575.json"}, "html": {"href": "#!/osrf/gazebo/pull-requests/1974/_/diff#comment-11999575"}}}, "deleted": false, "pullrequest": {"type": "pullrequest", "id": 1974, "links": {"self": {"href": "data/repositories/osrf/gazebo/pullrequests/1974.json"}, "html": {"href": "#!/osrf/gazebo/pull-requests/1974"}}, "title": "Elastic_modulus"}, "content": {"raw": "I'll add it to pull request #2001 so it's not too off topic", "markup": "markdown", "html": "<p>I'll add it to <a href=\"#!/osrf/gazebo/pull-requests/2001/fix-enabling-child-config-widgets\" rel=\"nofollow\" class=\"ap-connect-link\">pull request #2001</a> so it's not too off topic</p>", "type": "rendered"}, "created_on": "2015-11-20T01:21:55.399043+00:00", "user": {"display_name": "Louise Poubel", "uuid": "{5cfa2075-477b-4ded-bdb9-8d2479544ec4}", "links": {"self": {"href": "https://api.bitbucket.org/2.0/users/%7B5cfa2075-477b-4ded-bdb9-8d2479544ec4%7D"}, "html": {"href": "https://bitbucket.org/%7B5cfa2075-477b-4ded-bdb9-8d2479544ec4%7D/"}, "avatar": {"href": "https://avatar-management--avatars.us-west-2.prod.public.atl-paas.net/557058:6ff86fcb-b7ab-44a5-b8a6-f6d9cae8b6e8/7d903d90-c5ea-4182-b7ef-0d467e9e1c74/128"}}, "nickname": "chapulina", "type": "user", "account_id": "557058:6ff86fcb-b7ab-44a5-b8a6-f6d9cae8b6e8"}, "updated_on": "2015-11-20T01:21:55.401670+00:00", "type": "pullrequest_comment", "id": 11999847}, "pull_request": {"type": "pullrequest", "id": 1974, "links": {"self": {"href": "data/repositories/osrf/gazebo/pullrequests/1974.json"}, "html": {"href": "#!/osrf/gazebo/pull-requests/1974"}}, "title": "Elastic_modulus"}}, {"comment": {"links": {"self": {"href": "data/repositories/osrf/gazebo/pullrequests/1974/comments/11999575.json"}, "html": {"href": "#!/osrf/gazebo/pull-requests/1974/_/diff#comment-11999575"}}, "parent": {"id": 11998702, "links": {"self": {"href": "data/repositories/osrf/gazebo/pullrequests/1974/comments/11998702.json"}, "html": {"href": "#!/osrf/gazebo/pull-requests/1974/_/diff#comment-11998702"}}}, "deleted": false, "pullrequest": {"type": "pullrequest", "id": 1974, "links": {"self": {"href": "data/repositories/osrf/gazebo/pullrequests/1974.json"}, "html": {"href": "#!/osrf/gazebo/pull-requests/1974"}}, "title": "Elastic_modulus"}, "content": {"raw": "that makes sense. Maybe we can add it to an existing pull request to default", "markup": "markdown", "html": "<p>that makes sense. Maybe we can add it to an existing pull request to default</p>", "type": "rendered"}, "created_on": "2015-11-20T01:09:21.878393+00:00", "user": {"display_name": "Steve Peters", "uuid": "{2ccfed09-18b8-4921-8d58-15ef01092802}", "links": {"self": {"href": "https://api.bitbucket.org/2.0/users/%7B2ccfed09-18b8-4921-8d58-15ef01092802%7D"}, "html": {"href": "https://bitbucket.org/%7B2ccfed09-18b8-4921-8d58-15ef01092802%7D/"}, "avatar": {"href": "data/secure.gravatar.com/avatar/1fb4816dad9e68337d3096f750951f6cd=httpsavatar-management--avatars.us-west-2.prod.public.atl-paas.netinitialsSP-1.png"}}, "nickname": "Steven Peters", "type": "user", "account_id": "557058:5de38267-b118-494c-aa76-4fab35448816"}, "updated_on": "2015-11-20T01:09:21.880443+00:00", "type": "pullrequest_comment", "id": 11999575}, "pull_request": {"type": "pullrequest", "id": 1974, "links": {"self": {"href": "data/repositories/osrf/gazebo/pullrequests/1974.json"}, "html": {"href": "#!/osrf/gazebo/pull-requests/1974"}}, "title": "Elastic_modulus"}}, {"comment": {"links": {"self": {"href": "data/repositories/osrf/gazebo/pullrequests/1974/comments/11998702.json"}, "html": {"href": "#!/osrf/gazebo/pull-requests/1974/_/diff#comment-11998702"}}, "parent": {"id": 11998660, "links": {"self": {"href": "data/repositories/osrf/gazebo/pullrequests/1974/comments/11998660.json"}, "html": {"href": "#!/osrf/gazebo/pull-requests/1974/_/diff#comment-11998660"}}}, "deleted": false, "pullrequest": {"type": "pullrequest", "id": 1974, "links": {"self": {"href": "data/repositories/osrf/gazebo/pullrequests/1974.json"}, "html": {"href": "#!/osrf/gazebo/pull-requests/1974"}}, "title": "Elastic_modulus"}, "content": {"raw": "Oh the fields added to the message generated more spin boxes. It's just a matter of changing the value on the test.", "markup": "markdown", "html": "<p>Oh the fields added to the message generated more spin boxes. It's just a matter of changing the value on the test.</p>", "type": "rendered"}, "created_on": "2015-11-20T00:28:32.596475+00:00", "user": {"display_name": "Louise Poubel", "uuid": "{5cfa2075-477b-4ded-bdb9-8d2479544ec4}", "links": {"self": {"href": "https://api.bitbucket.org/2.0/users/%7B5cfa2075-477b-4ded-bdb9-8d2479544ec4%7D"}, "html": {"href": "https://bitbucket.org/%7B5cfa2075-477b-4ded-bdb9-8d2479544ec4%7D/"}, "avatar": {"href": "https://avatar-management--avatars.us-west-2.prod.public.atl-paas.net/557058:6ff86fcb-b7ab-44a5-b8a6-f6d9cae8b6e8/7d903d90-c5ea-4182-b7ef-0d467e9e1c74/128"}}, "nickname": "chapulina", "type": "user", "account_id": "557058:6ff86fcb-b7ab-44a5-b8a6-f6d9cae8b6e8"}, "updated_on": "2015-11-20T00:28:32.598549+00:00", "type": "pullrequest_comment", "id": 11998702}, "pull_request": {"type": "pullrequest", "id": 1974, "links": {"self": {"href": "data/repositories/osrf/gazebo/pullrequests/1974.json"}, "html": {"href": "#!/osrf/gazebo/pull-requests/1974"}}, "title": "Elastic_modulus"}}, {"comment": {"links": {"self": {"href": "data/repositories/osrf/gazebo/pullrequests/1974/comments/11998660.json"}, "html": {"href": "#!/osrf/gazebo/pull-requests/1974/_/diff#comment-11998660"}}, "deleted": false, "pullrequest": {"type": "pullrequest", "id": 1974, "links": {"self": {"href": "data/repositories/osrf/gazebo/pullrequests/1974.json"}, "html": {"href": "#!/osrf/gazebo/pull-requests/1974"}}, "title": "Elastic_modulus"}, "content": {"raw": "I think this caused a [test failure in CollisionConfig_TEST/AppliedSignal](http://build.osrfoundation.org/job/gazebo-default-devel-trusty-amd64-gpu-nvidia/244/testReport/junit/%28root%29/CollisionConfig_TEST/AppliedSignal/). Any thoughts @chapulina ?", "markup": "markdown", "html": "<p>I think this caused a <a data-is-external-link=\"true\" href=\"http://build.osrfoundation.org/job/gazebo-default-devel-trusty-amd64-gpu-nvidia/244/testReport/junit/%28root%29/CollisionConfig_TEST/AppliedSignal/\" rel=\"nofollow\">test failure in CollisionConfig_TEST/AppliedSignal</a>. Any thoughts @chapulina ?</p>", "type": "rendered"}, "created_on": "2015-11-20T00:26:45.516585+00:00", "user": {"display_name": "Steve Peters", "uuid": "{2ccfed09-18b8-4921-8d58-15ef01092802}", "links": {"self": {"href": "https://api.bitbucket.org/2.0/users/%7B2ccfed09-18b8-4921-8d58-15ef01092802%7D"}, "html": {"href": "https://bitbucket.org/%7B2ccfed09-18b8-4921-8d58-15ef01092802%7D/"}, "avatar": {"href": "data/secure.gravatar.com/avatar/1fb4816dad9e68337d3096f750951f6cd=httpsavatar-management--avatars.us-west-2.prod.public.atl-paas.netinitialsSP-1.png"}}, "nickname": "Steven Peters", "type": "user", "account_id": "557058:5de38267-b118-494c-aa76-4fab35448816"}, "updated_on": "2015-11-20T00:26:45.522569+00:00", "type": "pullrequest_comment", "id": 11998660}, "pull_request": {"type": "pullrequest", "id": 1974, "links": {"self": {"href": "data/repositories/osrf/gazebo/pullrequests/1974.json"}, "html": {"href": "#!/osrf/gazebo/pull-requests/1974"}}, "title": "Elastic_modulus"}}, {"update": {"description": "* implement Poisson's Ratio and Elastic Modulus for ODE\r\n* add conditional specifying when to use Elastic Modulus (dContactEM).\r\n* setting up elastic modulus test\r\n", "title": "Elastic_modulus", "destination": {"commit": {"hash": "c62677a754d0", "type": "commit", "links": {"self": {"href": "data/repositories/osrf/gazebo/commit/c62677a754d0.json"}, "html": {"href": "#!/osrf/gazebo/commits/c62677a754d0"}}}, "repository": {"links": {"self": {"href": "data/repositories/osrf/gazebo.json"}, "html": {"href": "#!/osrf/gazebo"}, "avatar": {"href": "data/bytebucket.org/ravatar/{51a0cd5d-8697-4eb1-8b08-e919ee881e1c}ts=1694483"}}, "type": "repository", "name": "gazebo", "full_name": "osrf/gazebo", "uuid": "{51a0cd5d-8697-4eb1-8b08-e919ee881e1c}"}, "branch": {"name": "default"}}, "reason": "", "source": {"commit": {"hash": "f73ee012649e", "type": "commit", "links": {"self": {"href": "data/repositories/osrf/gazebo/commit/f73ee012649e.json"}, "html": {"href": "#!/osrf/gazebo/commits/f73ee012649e"}}}, "repository": {"links": {"self": {"href": "data/repositories/osrf/gazebo.json"}, "html": {"href": "#!/osrf/gazebo"}, "avatar": {"href": "data/bytebucket.org/ravatar/{51a0cd5d-8697-4eb1-8b08-e919ee881e1c}ts=1694483"}}, "type": "repository", "name": "gazebo", "full_name": "osrf/gazebo", "uuid": "{51a0cd5d-8697-4eb1-8b08-e919ee881e1c}"}, "branch": {"name": "elastic_modulus"}}, "state": "MERGED", "author": {"display_name": "John Hsu", "uuid": "{0a186eae-abf0-4514-a951-23db5eccc286}", "links": {"self": {"href": "https://api.bitbucket.org/2.0/users/%7B0a186eae-abf0-4514-a951-23db5eccc286%7D"}, "html": {"href": "https://bitbucket.org/%7B0a186eae-abf0-4514-a951-23db5eccc286%7D/"}, "avatar": {"href": "https://avatar-management--avatars.us-west-2.prod.public.atl-paas.net/557058:f3968cd3-4910-4384-8349-482a6c7889ec/5445ce6e-6273-47f0-84eb-621c86ca11cb/128"}}, "nickname": "hsu", "type": "user", "account_id": "557058:f3968cd3-4910-4384-8349-482a6c7889ec"}, "date": "2015-11-19T22:36:41.816188+00:00"}, "pull_request": {"type": "pullrequest", "id": 1974, "links": {"self": {"href": "data/repositories/osrf/gazebo/pullrequests/1974.json"}, "html": {"href": "#!/osrf/gazebo/pull-requests/1974"}}, "title": "Elastic_modulus"}}, {"approval": {"date": "2015-11-19T22:31:59.111364+00:00", "pullrequest": {"type": "pullrequest", "id": 1974, "links": {"self": {"href": "data/repositories/osrf/gazebo/pullrequests/1974.json"}, "html": {"href": "#!/osrf/gazebo/pull-requests/1974"}}, "title": "Elastic_modulus"}, "user": {"display_name": "Nate Koenig", "uuid": "{c862cdd9-fcc8-4419-9fc7-e20db14b8fcb}", "links": {"self": {"href": "https://api.bitbucket.org/2.0/users/%7Bc862cdd9-fcc8-4419-9fc7-e20db14b8fcb%7D"}, "html": {"href": "https://bitbucket.org/%7Bc862cdd9-fcc8-4419-9fc7-e20db14b8fcb%7D/"}, "avatar": {"href": "https://avatar-management--avatars.us-west-2.prod.public.atl-paas.net/557058:095b1e12-74ed-4e20-b44f-2f0745b616e0/ca24bb11-4787-4b14-a20d-d91835e9bde2/128"}}, "nickname": "Nathan Koenig", "type": "user", "account_id": "557058:095b1e12-74ed-4e20-b44f-2f0745b616e0"}}, "pull_request": {"type": "pullrequest", "id": 1974, "links": {"self": {"href": "data/repositories/osrf/gazebo/pullrequests/1974.json"}, "html": {"href": "#!/osrf/gazebo/pull-requests/1974"}}, "title": "Elastic_modulus"}}, {"update": {"description": "* implement Poisson's Ratio and Elastic Modulus for ODE\r\n* add conditional specifying when to use Elastic Modulus (dContactEM).\r\n* setting up elastic modulus test\r\n", "title": "Elastic_modulus", "destination": {"commit": {"hash": "c62677a754d0", "type": "commit", "links": {"self": {"href": "data/repositories/osrf/gazebo/commit/c62677a754d0.json"}, "html": {"href": "#!/osrf/gazebo/commits/c62677a754d0"}}}, "repository": {"links": {"self": {"href": "data/repositories/osrf/gazebo.json"}, "html": {"href": "#!/osrf/gazebo"}, "avatar": {"href": "data/bytebucket.org/ravatar/{51a0cd5d-8697-4eb1-8b08-e919ee881e1c}ts=1694483"}}, "type": "repository", "name": "gazebo", "full_name": "osrf/gazebo", "uuid": "{51a0cd5d-8697-4eb1-8b08-e919ee881e1c}"}, "branch": {"name": "default"}}, "reason": "", "source": {"commit": {"hash": "f73ee012649e", "type": "commit", "links": {"self": {"href": "data/repositories/osrf/gazebo/commit/f73ee012649e.json"}, "html": {"href": "#!/osrf/gazebo/commits/f73ee012649e"}}}, "repository": {"links": {"self": {"href": "data/repositories/osrf/gazebo.json"}, "html": {"href": "#!/osrf/gazebo"}, "avatar": {"href": "data/bytebucket.org/ravatar/{51a0cd5d-8697-4eb1-8b08-e919ee881e1c}ts=1694483"}}, "type": "repository", "name": "gazebo", "full_name": "osrf/gazebo", "uuid": "{51a0cd5d-8697-4eb1-8b08-e919ee881e1c}"}, "branch": {"name": "elastic_modulus"}}, "state": "OPEN", "author": {"display_name": "Nate Koenig", "uuid": "{c862cdd9-fcc8-4419-9fc7-e20db14b8fcb}", "links": {"self": {"href": "https://api.bitbucket.org/2.0/users/%7Bc862cdd9-fcc8-4419-9fc7-e20db14b8fcb%7D"}, "html": {"href": "https://bitbucket.org/%7Bc862cdd9-fcc8-4419-9fc7-e20db14b8fcb%7D/"}, "avatar": {"href": "https://avatar-management--avatars.us-west-2.prod.public.atl-paas.net/557058:095b1e12-74ed-4e20-b44f-2f0745b616e0/ca24bb11-4787-4b14-a20d-d91835e9bde2/128"}}, "nickname": "Nathan Koenig", "type": "user", "account_id": "557058:095b1e12-74ed-4e20-b44f-2f0745b616e0"}, "date": "2015-11-19T22:28:44.544469+00:00"}, "pull_request": {"type": "pullrequest", "id": 1974, "links": {"self": {"href": "data/repositories/osrf/gazebo/pullrequests/1974.json"}, "html": {"href": "#!/osrf/gazebo/pull-requests/1974"}}, "title": "Elastic_modulus"}}, {"update": {"description": "* implement Poisson's Ratio and Elastic Modulus for ODE\r\n* add conditional specifying when to use Elastic Modulus (dContactEM).\r\n* setting up elastic modulus test\r\n", "title": "Elastic_modulus", "destination": {"commit": {"hash": "c62677a754d0", "type": "commit", "links": {"self": {"href": "data/repositories/osrf/gazebo/commit/c62677a754d0.json"}, "html": {"href": "#!/osrf/gazebo/commits/c62677a754d0"}}}, "repository": {"links": {"self": {"href": "data/repositories/osrf/gazebo.json"}, "html": {"href": "#!/osrf/gazebo"}, "avatar": {"href": "data/bytebucket.org/ravatar/{51a0cd5d-8697-4eb1-8b08-e919ee881e1c}ts=1694483"}}, "type": "repository", "name": "gazebo", "full_name": "osrf/gazebo", "uuid": "{51a0cd5d-8697-4eb1-8b08-e919ee881e1c}"}, "branch": {"name": "default"}}, "reason": "", "source": {"commit": {"hash": "f73ee012649e", "type": "commit", "links": {"self": {"href": "data/repositories/osrf/gazebo/commit/f73ee012649e.json"}, "html": {"href": "#!/osrf/gazebo/commits/f73ee012649e"}}}, "repository": {"links": {"self": {"href": "data/repositories/osrf/gazebo.json"}, "html": {"href": "#!/osrf/gazebo"}, "avatar": {"href": "data/bytebucket.org/ravatar/{51a0cd5d-8697-4eb1-8b08-e919ee881e1c}ts=1694483"}}, "type": "repository", "name": "gazebo", "full_name": "osrf/gazebo", "uuid": "{51a0cd5d-8697-4eb1-8b08-e919ee881e1c}"}, "branch": {"name": "elastic_modulus"}}, "state": "OPEN", "author": {"display_name": "Nate Koenig", "uuid": "{c862cdd9-fcc8-4419-9fc7-e20db14b8fcb}", "links": {"self": {"href": "https://api.bitbucket.org/2.0/users/%7Bc862cdd9-fcc8-4419-9fc7-e20db14b8fcb%7D"}, "html": {"href": "https://bitbucket.org/%7Bc862cdd9-fcc8-4419-9fc7-e20db14b8fcb%7D/"}, "avatar": {"href": "https://avatar-management--avatars.us-west-2.prod.public.atl-paas.net/557058:095b1e12-74ed-4e20-b44f-2f0745b616e0/ca24bb11-4787-4b14-a20d-d91835e9bde2/128"}}, "nickname": "Nathan Koenig", "type": "user", "account_id": "557058:095b1e12-74ed-4e20-b44f-2f0745b616e0"}, "date": "2015-11-19T22:28:43.055993+00:00"}, "pull_request": {"type": "pullrequest", "id": 1974, "links": {"self": {"href": "data/repositories/osrf/gazebo/pullrequests/1974.json"}, "html": {"href": "#!/osrf/gazebo/pull-requests/1974"}}, "title": "Elastic_modulus"}}, {"approval": {"date": "2015-11-17T22:01:37.492413+00:00", "pullrequest": {"type": "pullrequest", "id": 1974, "links": {"self": {"href": "data/repositories/osrf/gazebo/pullrequests/1974.json"}, "html": {"href": "#!/osrf/gazebo/pull-requests/1974"}}, "title": "Elastic_modulus"}, "user": {"display_name": "Carlos Ag\u00fcero", "uuid": "{da8a8e89-4bb0-421b-bd0e-dbbed3d4ed6a}", "links": {"self": {"href": "https://api.bitbucket.org/2.0/users/%7Bda8a8e89-4bb0-421b-bd0e-dbbed3d4ed6a%7D"}, "html": {"href": "https://bitbucket.org/%7Bda8a8e89-4bb0-421b-bd0e-dbbed3d4ed6a%7D/"}, "avatar": {"href": "data/secure.gravatar.com/avatar/692bf15758111acaddae4da15a47f9e5d=httpsavatar-management--avatars.us-west-2.prod.public.atl-paas.netinitialsCA-0.png"}}, "nickname": "caguero", "type": "user", "account_id": "557058:4ded1ddf-947e-4154-bbd1-3dba24f1bdbd"}}, "pull_request": {"type": "pullrequest", "id": 1974, "links": {"self": {"href": "data/repositories/osrf/gazebo/pullrequests/1974.json"}, "html": {"href": "#!/osrf/gazebo/pull-requests/1974"}}, "title": "Elastic_modulus"}}, {"comment": {"links": {"self": {"href": "data/repositories/osrf/gazebo/pullrequests/1974/comments/11897276.json"}, "html": {"href": "#!/osrf/gazebo/pull-requests/1974/_/diff#comment-11897276"}}, "parent": {"id": 11894010, "links": {"self": {"href": "data/repositories/osrf/gazebo/pullrequests/1974/comments/11894010.json"}, "html": {"href": "#!/osrf/gazebo/pull-requests/1974/_/diff#comment-11894010"}}}, "deleted": false, "pullrequest": {"type": "pullrequest", "id": 1974, "links": {"self": {"href": "data/repositories/osrf/gazebo/pullrequests/1974.json"}, "html": {"href": "#!/osrf/gazebo/pull-requests/1974"}}, "title": "Elastic_modulus"}, "content": {"raw": "Thanks for the clarification", "markup": "markdown", "html": "<p>Thanks for the clarification</p>", "type": "rendered"}, "created_on": "2015-11-17T21:22:47.639703+00:00", "user": {"display_name": "Carlos Ag\u00fcero", "uuid": "{da8a8e89-4bb0-421b-bd0e-dbbed3d4ed6a}", "links": {"self": {"href": "https://api.bitbucket.org/2.0/users/%7Bda8a8e89-4bb0-421b-bd0e-dbbed3d4ed6a%7D"}, "html": {"href": "https://bitbucket.org/%7Bda8a8e89-4bb0-421b-bd0e-dbbed3d4ed6a%7D/"}, "avatar": {"href": "data/secure.gravatar.com/avatar/692bf15758111acaddae4da15a47f9e5d=httpsavatar-management--avatars.us-west-2.prod.public.atl-paas.netinitialsCA-0.png"}}, "nickname": "caguero", "type": "user", "account_id": "557058:4ded1ddf-947e-4154-bbd1-3dba24f1bdbd"}, "inline": {}, "updated_on": "2015-11-17T21:22:47.645194+00:00", "type": "pullrequest_comment", "id": 11897276}, "pull_request": {"type": "pullrequest", "id": 1974, "links": {"self": {"href": "data/repositories/osrf/gazebo/pullrequests/1974.json"}, "html": {"href": "#!/osrf/gazebo/pull-requests/1974"}}, "title": "Elastic_modulus"}}, {"comment": {"links": {"self": {"href": "data/repositories/osrf/gazebo/pullrequests/1974/comments/11897261.json"}, "html": {"href": "#!/osrf/gazebo/pull-requests/1974/_/diff#comment-11897261"}}, "parent": {"id": 11897221, "links": {"self": {"href": "data/repositories/osrf/gazebo/pullrequests/1974/comments/11897221.json"}, "html": {"href": "#!/osrf/gazebo/pull-requests/1974/_/diff#comment-11897221"}}}, "deleted": false, "pullrequest": {"type": "pullrequest", "id": 1974, "links": {"self": {"href": "data/repositories/osrf/gazebo/pullrequests/1974.json"}, "html": {"href": "#!/osrf/gazebo/pull-requests/1974"}}, "title": "Elastic_modulus"}, "content": {"raw": "Fixed in c2b9a44", "markup": "markdown", "html": "<p>Fixed in <a href=\"#!/osrf/gazebo/commits/c2b9a44\" rel=\"nofollow\" class=\"ap-connect-link\">c2b9a44</a></p>", "type": "rendered"}, "created_on": "2015-11-17T21:22:31.715631+00:00", "user": {"display_name": "Carlos Ag\u00fcero", "uuid": "{da8a8e89-4bb0-421b-bd0e-dbbed3d4ed6a}", "links": {"self": {"href": "https://api.bitbucket.org/2.0/users/%7Bda8a8e89-4bb0-421b-bd0e-dbbed3d4ed6a%7D"}, "html": {"href": "https://bitbucket.org/%7Bda8a8e89-4bb0-421b-bd0e-dbbed3d4ed6a%7D/"}, "avatar": {"href": "data/secure.gravatar.com/avatar/692bf15758111acaddae4da15a47f9e5d=httpsavatar-management--avatars.us-west-2.prod.public.atl-paas.netinitialsCA-0.png"}}, "nickname": "caguero", "type": "user", "account_id": "557058:4ded1ddf-947e-4154-bbd1-3dba24f1bdbd"}, "inline": {}, "updated_on": "2015-11-17T21:22:31.717582+00:00", "type": "pullrequest_comment", "id": 11897261}, "pull_request": {"type": "pullrequest", "id": 1974, "links": {"self": {"href": "data/repositories/osrf/gazebo/pullrequests/1974.json"}, "html": {"href": "#!/osrf/gazebo/pull-requests/1974"}}, "title": "Elastic_modulus"}}, {"update": {"description": "* implement Poisson's Ratio and Elastic Modulus for ODE\r\n* add conditional specifying when to use Elastic Modulus (dContactEM).\r\n* setting up elastic modulus test\r\n", "title": "Elastic_modulus", "destination": {"commit": {"hash": "c62677a754d0", "type": "commit", "links": {"self": {"href": "data/repositories/osrf/gazebo/commit/c62677a754d0.json"}, "html": {"href": "#!/osrf/gazebo/commits/c62677a754d0"}}}, "repository": {"links": {"self": {"href": "data/repositories/osrf/gazebo.json"}, "html": {"href": "#!/osrf/gazebo"}, "avatar": {"href": "data/bytebucket.org/ravatar/{51a0cd5d-8697-4eb1-8b08-e919ee881e1c}ts=1694483"}}, "type": "repository", "name": "gazebo", "full_name": "osrf/gazebo", "uuid": "{51a0cd5d-8697-4eb1-8b08-e919ee881e1c}"}, "branch": {"name": "default"}}, "reason": "", "source": {"commit": {"hash": "c2b9a44a0ef1", "type": "commit", "links": {"self": {"href": "data/repositories/osrf/gazebo/commit/c2b9a44a0ef1.json"}, "html": {"href": "#!/osrf/gazebo/commits/c2b9a44a0ef1"}}}, "repository": {"links": {"self": {"href": "data/repositories/osrf/gazebo.json"}, "html": {"href": "#!/osrf/gazebo"}, "avatar": {"href": "data/bytebucket.org/ravatar/{51a0cd5d-8697-4eb1-8b08-e919ee881e1c}ts=1694483"}}, "type": "repository", "name": "gazebo", "full_name": "osrf/gazebo", "uuid": "{51a0cd5d-8697-4eb1-8b08-e919ee881e1c}"}, "branch": {"name": "elastic_modulus"}}, "state": "OPEN", "author": {"display_name": "Carlos Ag\u00fcero", "uuid": "{da8a8e89-4bb0-421b-bd0e-dbbed3d4ed6a}", "links": {"self": {"href": "https://api.bitbucket.org/2.0/users/%7Bda8a8e89-4bb0-421b-bd0e-dbbed3d4ed6a%7D"}, "html": {"href": "https://bitbucket.org/%7Bda8a8e89-4bb0-421b-bd0e-dbbed3d4ed6a%7D/"}, "avatar": {"href": "data/secure.gravatar.com/avatar/692bf15758111acaddae4da15a47f9e5d=httpsavatar-management--avatars.us-west-2.prod.public.atl-paas.netinitialsCA-0.png"}}, "nickname": "caguero", "type": "user", "account_id": "557058:4ded1ddf-947e-4154-bbd1-3dba24f1bdbd"}, "date": "2015-11-17T21:21:50.158874+00:00"}, "pull_request": {"type": "pullrequest", "id": 1974, "links": {"self": {"href": "data/repositories/osrf/gazebo/pullrequests/1974.json"}, "html": {"href": "#!/osrf/gazebo/pull-requests/1974"}}, "title": "Elastic_modulus"}}, {"comment": {"links": {"self": {"href": "data/repositories/osrf/gazebo/pullrequests/1974/comments/11897221.json"}, "html": {"href": "#!/osrf/gazebo/pull-requests/1974/_/diff#comment-11897221"}}, "deleted": false, "pullrequest": {"type": "pullrequest", "id": 1974, "links": {"self": {"href": "data/repositories/osrf/gazebo/pullrequests/1974.json"}, "html": {"href": "#!/osrf/gazebo/pull-requests/1974"}}, "title": "Elastic_modulus"}, "content": {"raw": "Repeated #include", "markup": "markdown", "html": "<p>Repeated #include</p>", "type": "rendered"}, "created_on": "2015-11-17T21:21:23.888728+00:00", "user": {"display_name": "Carlos Ag\u00fcero", "uuid": "{da8a8e89-4bb0-421b-bd0e-dbbed3d4ed6a}", "links": {"self": {"href": "https://api.bitbucket.org/2.0/users/%7Bda8a8e89-4bb0-421b-bd0e-dbbed3d4ed6a%7D"}, "html": {"href": "https://bitbucket.org/%7Bda8a8e89-4bb0-421b-bd0e-dbbed3d4ed6a%7D/"}, "avatar": {"href": "data/secure.gravatar.com/avatar/692bf15758111acaddae4da15a47f9e5d=httpsavatar-management--avatars.us-west-2.prod.public.atl-paas.netinitialsCA-0.png"}}, "nickname": "caguero", "type": "user", "account_id": "557058:4ded1ddf-947e-4154-bbd1-3dba24f1bdbd"}, "inline": {}, "updated_on": "2015-11-17T21:21:23.891406+00:00", "type": "pullrequest_comment", "id": 11897221}, "pull_request": {"type": "pullrequest", "id": 1974, "links": {"self": {"href": "data/repositories/osrf/gazebo/pullrequests/1974.json"}, "html": {"href": "#!/osrf/gazebo/pull-requests/1974"}}, "title": "Elastic_modulus"}}, {"comment": {"links": {"self": {"href": "data/repositories/osrf/gazebo/pullrequests/1974/comments/11894010.json"}, "html": {"href": "#!/osrf/gazebo/pull-requests/1974/_/diff#comment-11894010"}}, "parent": {"id": 11890624, "links": {"self": {"href": "data/repositories/osrf/gazebo/pullrequests/1974/comments/11890624.json"}, "html": {"href": "#!/osrf/gazebo/pull-requests/1974/_/diff#comment-11890624"}}}, "deleted": false, "pullrequest": {"type": "pullrequest", "id": 1974, "links": {"self": {"href": "data/repositories/osrf/gazebo/pullrequests/1974.json"}, "html": {"href": "#!/osrf/gazebo/pull-requests/1974"}}, "title": "Elastic_modulus"}, "content": {"raw": "yeah sorry, it's not obvious but `kph` is `kp * h` where we kind of loosely use `h` and `dt` synonymously.\n\nOh and `info->fps` is `1/h`, `khertz_sqrtx` is `kp` in this use case.", "markup": "markdown", "html": "<p>yeah sorry, it's not obvious but <code>kph</code> is <code>kp * h</code> where we kind of loosely use <code>h</code> and <code>dt</code> synonymously.</p>\n<p>Oh and <code>info-&gt;fps</code> is <code>1/h</code>, <code>khertz_sqrtx</code> is <code>kp</code> in this use case.</p>", "type": "rendered"}, "created_on": "2015-11-17T19:57:23.030090+00:00", "user": {"display_name": "John Hsu", "uuid": "{0a186eae-abf0-4514-a951-23db5eccc286}", "links": {"self": {"href": "https://api.bitbucket.org/2.0/users/%7B0a186eae-abf0-4514-a951-23db5eccc286%7D"}, "html": {"href": "https://bitbucket.org/%7B0a186eae-abf0-4514-a951-23db5eccc286%7D/"}, "avatar": {"href": "https://avatar-management--avatars.us-west-2.prod.public.atl-paas.net/557058:f3968cd3-4910-4384-8349-482a6c7889ec/5445ce6e-6273-47f0-84eb-621c86ca11cb/128"}}, "nickname": "hsu", "type": "user", "account_id": "557058:f3968cd3-4910-4384-8349-482a6c7889ec"}, "inline": {}, "updated_on": "2015-11-17T19:58:26.074981+00:00", "type": "pullrequest_comment", "id": 11894010}, "pull_request": {"type": "pullrequest", "id": 1974, "links": {"self": {"href": "data/repositories/osrf/gazebo/pullrequests/1974.json"}, "html": {"href": "#!/osrf/gazebo/pull-requests/1974"}}, "title": "Elastic_modulus"}}, {"update": {"description": "* implement Poisson's Ratio and Elastic Modulus for ODE\r\n* add conditional specifying when to use Elastic Modulus (dContactEM).\r\n* setting up elastic modulus test\r\n", "title": "Elastic_modulus", "destination": {"commit": {"hash": "c62677a754d0", "type": "commit", "links": {"self": {"href": "data/repositories/osrf/gazebo/commit/c62677a754d0.json"}, "html": {"href": "#!/osrf/gazebo/commits/c62677a754d0"}}}, "repository": {"links": {"self": {"href": "data/repositories/osrf/gazebo.json"}, "html": {"href": "#!/osrf/gazebo"}, "avatar": {"href": "data/bytebucket.org/ravatar/{51a0cd5d-8697-4eb1-8b08-e919ee881e1c}ts=1694483"}}, "type": "repository", "name": "gazebo", "full_name": "osrf/gazebo", "uuid": "{51a0cd5d-8697-4eb1-8b08-e919ee881e1c}"}, "branch": {"name": "default"}}, "reason": "", "source": {"commit": {"hash": "88d70969f67e", "type": "commit", "links": {"self": {"href": "data/repositories/osrf/gazebo/commit/88d70969f67e.json"}, "html": {"href": "#!/osrf/gazebo/commits/88d70969f67e"}}}, "repository": {"links": {"self": {"href": "data/repositories/osrf/gazebo.json"}, "html": {"href": "#!/osrf/gazebo"}, "avatar": {"href": "data/bytebucket.org/ravatar/{51a0cd5d-8697-4eb1-8b08-e919ee881e1c}ts=1694483"}}, "type": "repository", "name": "gazebo", "full_name": "osrf/gazebo", "uuid": "{51a0cd5d-8697-4eb1-8b08-e919ee881e1c}"}, "branch": {"name": "elastic_modulus"}}, "state": "OPEN", "author": {"display_name": "Carlos Ag\u00fcero", "uuid": "{da8a8e89-4bb0-421b-bd0e-dbbed3d4ed6a}", "links": {"self": {"href": "https://api.bitbucket.org/2.0/users/%7Bda8a8e89-4bb0-421b-bd0e-dbbed3d4ed6a%7D"}, "html": {"href": "https://bitbucket.org/%7Bda8a8e89-4bb0-421b-bd0e-dbbed3d4ed6a%7D/"}, "avatar": {"href": "data/secure.gravatar.com/avatar/692bf15758111acaddae4da15a47f9e5d=httpsavatar-management--avatars.us-west-2.prod.public.atl-paas.netinitialsCA-0.png"}}, "nickname": "caguero", "type": "user", "account_id": "557058:4ded1ddf-947e-4154-bbd1-3dba24f1bdbd"}, "date": "2015-11-17T18:26:08.141610+00:00"}, "pull_request": {"type": "pullrequest", "id": 1974, "links": {"self": {"href": "data/repositories/osrf/gazebo/pullrequests/1974.json"}, "html": {"href": "#!/osrf/gazebo/pull-requests/1974"}}, "title": "Elastic_modulus"}}, {"comment": {"links": {"self": {"href": "data/repositories/osrf/gazebo/pullrequests/1974/comments/11890624.json"}, "html": {"href": "#!/osrf/gazebo/pull-requests/1974/_/diff#comment-11890624"}}, "deleted": false, "pullrequest": {"type": "pullrequest", "id": 1974, "links": {"self": {"href": "data/repositories/osrf/gazebo/pullrequests/1974.json"}, "html": {"href": "#!/osrf/gazebo/pull-requests/1974"}}, "title": "Elastic_modulus"}, "content": {"raw": "According to the comment in line 201, there is a `dt` factor in the equation. Are we using it here? Maybe is already in `kph` but it's not evident to me. Not a big deal, but it would be nice to make the name of the variables to match the variables used in the comments. It's easier to follow. For example, the comment in line 201 uses `kp` but here we use `kph`. ", "markup": "markdown", "html": "<p>According to the comment in line 201, there is a <code>dt</code> factor in the equation. Are we using it here? Maybe is already in <code>kph</code> but it's not evident to me. Not a big deal, but it would be nice to make the name of the variables to match the variables used in the comments. It's easier to follow. For example, the comment in line 201 uses <code>kp</code> but here we use <code>kph</code>. </p>", "type": "rendered"}, "created_on": "2015-11-17T18:24:03.291310+00:00", "user": {"display_name": "Carlos Ag\u00fcero", "uuid": "{da8a8e89-4bb0-421b-bd0e-dbbed3d4ed6a}", "links": {"self": {"href": "https://api.bitbucket.org/2.0/users/%7Bda8a8e89-4bb0-421b-bd0e-dbbed3d4ed6a%7D"}, "html": {"href": "https://bitbucket.org/%7Bda8a8e89-4bb0-421b-bd0e-dbbed3d4ed6a%7D/"}, "avatar": {"href": "data/secure.gravatar.com/avatar/692bf15758111acaddae4da15a47f9e5d=httpsavatar-management--avatars.us-west-2.prod.public.atl-paas.netinitialsCA-0.png"}}, "nickname": "caguero", "type": "user", "account_id": "557058:4ded1ddf-947e-4154-bbd1-3dba24f1bdbd"}, "inline": {}, "updated_on": "2015-11-17T18:24:03.294249+00:00", "type": "pullrequest_comment", "id": 11890624}, "pull_request": {"type": "pullrequest", "id": 1974, "links": {"self": {"href": "data/repositories/osrf/gazebo/pullrequests/1974.json"}, "html": {"href": "#!/osrf/gazebo/pull-requests/1974"}}, "title": "Elastic_modulus"}}, {"comment": {"links": {"self": {"href": "data/repositories/osrf/gazebo/pullrequests/1974/comments/11869989.json"}, "html": {"href": "#!/osrf/gazebo/pull-requests/1974/_/diff#comment-11869989"}}, "parent": {"id": 11851142, "links": {"self": {"href": "data/repositories/osrf/gazebo/pullrequests/1974/comments/11851142.json"}, "html": {"href": "#!/osrf/gazebo/pull-requests/1974/_/diff#comment-11851142"}}}, "deleted": false, "pullrequest": {"type": "pullrequest", "id": 1974, "links": {"self": {"href": "data/repositories/osrf/gazebo/pullrequests/1974.json"}, "html": {"href": "#!/osrf/gazebo/pull-requests/1974"}}, "title": "Elastic_modulus"}, "content": {"raw": "some updates in 4d9d335", "markup": "markdown", "html": "<p>some updates in <a href=\"#!/osrf/gazebo/commits/4d9d335\" rel=\"nofollow\" class=\"ap-connect-link\">4d9d335</a></p>", "type": "rendered"}, "created_on": "2015-11-17T11:00:07.890856+00:00", "user": {"display_name": "John Hsu", "uuid": "{0a186eae-abf0-4514-a951-23db5eccc286}", "links": {"self": {"href": "https://api.bitbucket.org/2.0/users/%7B0a186eae-abf0-4514-a951-23db5eccc286%7D"}, "html": {"href": "https://bitbucket.org/%7B0a186eae-abf0-4514-a951-23db5eccc286%7D/"}, "avatar": {"href": "https://avatar-management--avatars.us-west-2.prod.public.atl-paas.net/557058:f3968cd3-4910-4384-8349-482a6c7889ec/5445ce6e-6273-47f0-84eb-621c86ca11cb/128"}}, "nickname": "hsu", "type": "user", "account_id": "557058:f3968cd3-4910-4384-8349-482a6c7889ec"}, "inline": {}, "updated_on": "2015-11-17T11:00:07.893271+00:00", "type": "pullrequest_comment", "id": 11869989}, "pull_request": {"type": "pullrequest", "id": 1974, "links": {"self": {"href": "data/repositories/osrf/gazebo/pullrequests/1974.json"}, "html": {"href": "#!/osrf/gazebo/pull-requests/1974"}}, "title": "Elastic_modulus"}}, {"update": {"description": "* implement Poisson's Ratio and Elastic Modulus for ODE\r\n* add conditional specifying when to use Elastic Modulus (dContactEM).\r\n* setting up elastic modulus test\r\n", "title": "Elastic_modulus", "destination": {"commit": {"hash": "23eb27c0e89f", "type": "commit", "links": {"self": {"href": "data/repositories/osrf/gazebo/commit/23eb27c0e89f.json"}, "html": {"href": "#!/osrf/gazebo/commits/23eb27c0e89f"}}}, "repository": {"links": {"self": {"href": "data/repositories/osrf/gazebo.json"}, "html": {"href": "#!/osrf/gazebo"}, "avatar": {"href": "data/bytebucket.org/ravatar/{51a0cd5d-8697-4eb1-8b08-e919ee881e1c}ts=1694483"}}, "type": "repository", "name": "gazebo", "full_name": "osrf/gazebo", "uuid": "{51a0cd5d-8697-4eb1-8b08-e919ee881e1c}"}, "branch": {"name": "default"}}, "reason": "", "source": {"commit": {"hash": "4d9d335d87f8", "type": "commit", "links": {"self": {"href": "data/repositories/osrf/gazebo/commit/4d9d335d87f8.json"}, "html": {"href": "#!/osrf/gazebo/commits/4d9d335d87f8"}}}, "repository": {"links": {"self": {"href": "data/repositories/osrf/gazebo.json"}, "html": {"href": "#!/osrf/gazebo"}, "avatar": {"href": "data/bytebucket.org/ravatar/{51a0cd5d-8697-4eb1-8b08-e919ee881e1c}ts=1694483"}}, "type": "repository", "name": "gazebo", "full_name": "osrf/gazebo", "uuid": "{51a0cd5d-8697-4eb1-8b08-e919ee881e1c}"}, "branch": {"name": "elastic_modulus"}}, "state": "OPEN", "author": {"display_name": "John Hsu", "uuid": "{0a186eae-abf0-4514-a951-23db5eccc286}", "links": {"self": {"href": "https://api.bitbucket.org/2.0/users/%7B0a186eae-abf0-4514-a951-23db5eccc286%7D"}, "html": {"href": "https://bitbucket.org/%7B0a186eae-abf0-4514-a951-23db5eccc286%7D/"}, "avatar": {"href": "https://avatar-management--avatars.us-west-2.prod.public.atl-paas.net/557058:f3968cd3-4910-4384-8349-482a6c7889ec/5445ce6e-6273-47f0-84eb-621c86ca11cb/128"}}, "nickname": "hsu", "type": "user", "account_id": "557058:f3968cd3-4910-4384-8349-482a6c7889ec"}, "date": "2015-11-17T10:59:50.870630+00:00"}, "pull_request": {"type": "pullrequest", "id": 1974, "links": {"self": {"href": "data/repositories/osrf/gazebo/pullrequests/1974.json"}, "html": {"href": "#!/osrf/gazebo/pull-requests/1974"}}, "title": "Elastic_modulus"}}, {"comment": {"links": {"self": {"href": "data/repositories/osrf/gazebo/pullrequests/1974/comments/11851142.json"}, "html": {"href": "#!/osrf/gazebo/pull-requests/1974/_/diff#comment-11851142"}}, "deleted": false, "pullrequest": {"type": "pullrequest", "id": 1974, "links": {"self": {"href": "data/repositories/osrf/gazebo/pullrequests/1974.json"}, "html": {"href": "#!/osrf/gazebo/pull-requests/1974"}}, "title": "Elastic_modulus"}, "content": {"raw": "Just checking: Should this line match the formula on line 200?", "markup": "markdown", "html": "<p>Just checking: Should this line match the formula on line 200?</p>", "type": "rendered"}, "created_on": "2015-11-16T21:38:44.795275+00:00", "user": {"display_name": "Carlos Ag\u00fcero", "uuid": "{da8a8e89-4bb0-421b-bd0e-dbbed3d4ed6a}", "links": {"self": {"href": "https://api.bitbucket.org/2.0/users/%7Bda8a8e89-4bb0-421b-bd0e-dbbed3d4ed6a%7D"}, "html": {"href": "https://bitbucket.org/%7Bda8a8e89-4bb0-421b-bd0e-dbbed3d4ed6a%7D/"}, "avatar": {"href": "data/secure.gravatar.com/avatar/692bf15758111acaddae4da15a47f9e5d=httpsavatar-management--avatars.us-west-2.prod.public.atl-paas.netinitialsCA-0.png"}}, "nickname": "caguero", "type": "user", "account_id": "557058:4ded1ddf-947e-4154-bbd1-3dba24f1bdbd"}, "inline": {}, "updated_on": "2015-11-16T21:38:44.800099+00:00", "type": "pullrequest_comment", "id": 11851142}, "pull_request": {"type": "pullrequest", "id": 1974, "links": {"self": {"href": "data/repositories/osrf/gazebo/pullrequests/1974.json"}, "html": {"href": "#!/osrf/gazebo/pull-requests/1974"}}, "title": "Elastic_modulus"}}, {"comment": {"links": {"self": {"href": "data/repositories/osrf/gazebo/pullrequests/1974/comments/11816371.json"}, "html": {"href": "#!/osrf/gazebo/pull-requests/1974/_/diff#comment-11816371"}}, "parent": {"id": 11802418, "links": {"self": {"href": "data/repositories/osrf/gazebo/pullrequests/1974/comments/11802418.json"}, "html": {"href": "#!/osrf/gazebo/pull-requests/1974/_/diff#comment-11802418"}}}, "deleted": false, "pullrequest": {"type": "pullrequest", "id": 1974, "links": {"self": {"href": "data/repositories/osrf/gazebo/pullrequests/1974.json"}, "html": {"href": "#!/osrf/gazebo/pull-requests/1974"}}, "title": "Elastic_modulus"}, "content": {"raw": "184cd95", "markup": "markdown", "html": "<p><a href=\"#!/osrf/gazebo/commits/184cd95\" rel=\"nofollow\" class=\"ap-connect-link\">184cd95</a></p>", "type": "rendered"}, "created_on": "2015-11-16T05:42:18.028342+00:00", "user": {"display_name": "John Hsu", "uuid": "{0a186eae-abf0-4514-a951-23db5eccc286}", "links": {"self": {"href": "https://api.bitbucket.org/2.0/users/%7B0a186eae-abf0-4514-a951-23db5eccc286%7D"}, "html": {"href": "https://bitbucket.org/%7B0a186eae-abf0-4514-a951-23db5eccc286%7D/"}, "avatar": {"href": "https://avatar-management--avatars.us-west-2.prod.public.atl-paas.net/557058:f3968cd3-4910-4384-8349-482a6c7889ec/5445ce6e-6273-47f0-84eb-621c86ca11cb/128"}}, "nickname": "hsu", "type": "user", "account_id": "557058:f3968cd3-4910-4384-8349-482a6c7889ec"}, "inline": {}, "updated_on": "2015-11-16T05:42:18.030651+00:00", "type": "pullrequest_comment", "id": 11816371}, "pull_request": {"type": "pullrequest", "id": 1974, "links": {"self": {"href": "data/repositories/osrf/gazebo/pullrequests/1974.json"}, "html": {"href": "#!/osrf/gazebo/pull-requests/1974"}}, "title": "Elastic_modulus"}}, {"update": {"description": "* implement Poisson's Ratio and Elastic Modulus for ODE\r\n* add conditional specifying when to use Elastic Modulus (dContactEM).\r\n* setting up elastic modulus test\r\n", "title": "Elastic_modulus", "destination": {"commit": {"hash": "674cbf794b96", "type": "commit", "links": {"self": {"href": "data/repositories/osrf/gazebo/commit/674cbf794b96.json"}, "html": {"href": "#!/osrf/gazebo/commits/674cbf794b96"}}}, "repository": {"links": {"self": {"href": "data/repositories/osrf/gazebo.json"}, "html": {"href": "#!/osrf/gazebo"}, "avatar": {"href": "data/bytebucket.org/ravatar/{51a0cd5d-8697-4eb1-8b08-e919ee881e1c}ts=1694483"}}, "type": "repository", "name": "gazebo", "full_name": "osrf/gazebo", "uuid": "{51a0cd5d-8697-4eb1-8b08-e919ee881e1c}"}, "branch": {"name": "default"}}, "reason": "", "source": {"commit": {"hash": "184cd95cd40d", "type": "commit", "links": {"self": {"href": "data/repositories/osrf/gazebo/commit/184cd95cd40d.json"}, "html": {"href": "#!/osrf/gazebo/commits/184cd95cd40d"}}}, "repository": {"links": {"self": {"href": "data/repositories/osrf/gazebo.json"}, "html": {"href": "#!/osrf/gazebo"}, "avatar": {"href": "data/bytebucket.org/ravatar/{51a0cd5d-8697-4eb1-8b08-e919ee881e1c}ts=1694483"}}, "type": "repository", "name": "gazebo", "full_name": "osrf/gazebo", "uuid": "{51a0cd5d-8697-4eb1-8b08-e919ee881e1c}"}, "branch": {"name": "elastic_modulus"}}, "state": "OPEN", "author": {"display_name": "John Hsu", "uuid": "{0a186eae-abf0-4514-a951-23db5eccc286}", "links": {"self": {"href": "https://api.bitbucket.org/2.0/users/%7B0a186eae-abf0-4514-a951-23db5eccc286%7D"}, "html": {"href": "https://bitbucket.org/%7B0a186eae-abf0-4514-a951-23db5eccc286%7D/"}, "avatar": {"href": "https://avatar-management--avatars.us-west-2.prod.public.atl-paas.net/557058:f3968cd3-4910-4384-8349-482a6c7889ec/5445ce6e-6273-47f0-84eb-621c86ca11cb/128"}}, "nickname": "hsu", "type": "user", "account_id": "557058:f3968cd3-4910-4384-8349-482a6c7889ec"}, "date": "2015-11-16T05:42:06.403132+00:00"}, "pull_request": {"type": "pullrequest", "id": 1974, "links": {"self": {"href": "data/repositories/osrf/gazebo/pullrequests/1974.json"}, "html": {"href": "#!/osrf/gazebo/pull-requests/1974"}}, "title": "Elastic_modulus"}}, {"comment": {"links": {"self": {"href": "data/repositories/osrf/gazebo/pullrequests/1974/comments/11802418.json"}, "html": {"href": "#!/osrf/gazebo/pull-requests/1974/_/diff#comment-11802418"}}, "parent": {"id": 11672066, "links": {"self": {"href": "data/repositories/osrf/gazebo/pullrequests/1974/comments/11672066.json"}, "html": {"href": "#!/osrf/gazebo/pull-requests/1974/_/diff#comment-11672066"}}}, "deleted": false, "pullrequest": {"type": "pullrequest", "id": 1974, "links": {"self": {"href": "data/repositories/osrf/gazebo/pullrequests/1974.json"}, "html": {"href": "#!/osrf/gazebo/pull-requests/1974"}}, "title": "Elastic_modulus"}, "content": {"raw": "good point, maybe not non-zero,, but `patch_radius * depth` should be greater than 0", "markup": "markdown", "html": "<p>good point, maybe not non-zero,, but <code>patch_radius * depth</code> should be greater than 0</p>", "type": "rendered"}, "created_on": "2015-11-14T06:26:08.368623+00:00", "user": {"display_name": "John Hsu", "uuid": "{0a186eae-abf0-4514-a951-23db5eccc286}", "links": {"self": {"href": "https://api.bitbucket.org/2.0/users/%7B0a186eae-abf0-4514-a951-23db5eccc286%7D"}, "html": {"href": "https://bitbucket.org/%7B0a186eae-abf0-4514-a951-23db5eccc286%7D/"}, "avatar": {"href": "https://avatar-management--avatars.us-west-2.prod.public.atl-paas.net/557058:f3968cd3-4910-4384-8349-482a6c7889ec/5445ce6e-6273-47f0-84eb-621c86ca11cb/128"}}, "nickname": "hsu", "type": "user", "account_id": "557058:f3968cd3-4910-4384-8349-482a6c7889ec"}, "inline": {}, "updated_on": "2015-11-14T06:26:08.371547+00:00", "type": "pullrequest_comment", "id": 11802418}, "pull_request": {"type": "pullrequest", "id": 1974, "links": {"self": {"href": "data/repositories/osrf/gazebo/pullrequests/1974.json"}, "html": {"href": "#!/osrf/gazebo/pull-requests/1974"}}, "title": "Elastic_modulus"}}, {"update": {"description": "* implement Poisson's Ratio and Elastic Modulus for ODE\r\n* add conditional specifying when to use Elastic Modulus (dContactEM).\r\n* setting up elastic modulus test\r\n", "title": "Elastic_modulus", "destination": {"commit": {"hash": "674cbf794b96", "type": "commit", "links": {"self": {"href": "data/repositories/osrf/gazebo/commit/674cbf794b96.json"}, "html": {"href": "#!/osrf/gazebo/commits/674cbf794b96"}}}, "repository": {"links": {"self": {"href": "data/repositories/osrf/gazebo.json"}, "html": {"href": "#!/osrf/gazebo"}, "avatar": {"href": "data/bytebucket.org/ravatar/{51a0cd5d-8697-4eb1-8b08-e919ee881e1c}ts=1694483"}}, "type": "repository", "name": "gazebo", "full_name": "osrf/gazebo", "uuid": "{51a0cd5d-8697-4eb1-8b08-e919ee881e1c}"}, "branch": {"name": "default"}}, "reason": "", "source": {"commit": {"hash": "5c1ee5ef03fe", "type": "commit", "links": {"self": {"href": "data/repositories/osrf/gazebo/commit/5c1ee5ef03fe.json"}, "html": {"href": "#!/osrf/gazebo/commits/5c1ee5ef03fe"}}}, "repository": {"links": {"self": {"href": "data/repositories/osrf/gazebo.json"}, "html": {"href": "#!/osrf/gazebo"}, "avatar": {"href": "data/bytebucket.org/ravatar/{51a0cd5d-8697-4eb1-8b08-e919ee881e1c}ts=1694483"}}, "type": "repository", "name": "gazebo", "full_name": "osrf/gazebo", "uuid": "{51a0cd5d-8697-4eb1-8b08-e919ee881e1c}"}, "branch": {"name": "elastic_modulus"}}, "state": "OPEN", "author": {"display_name": "John Hsu", "uuid": "{0a186eae-abf0-4514-a951-23db5eccc286}", "links": {"self": {"href": "https://api.bitbucket.org/2.0/users/%7B0a186eae-abf0-4514-a951-23db5eccc286%7D"}, "html": {"href": "https://bitbucket.org/%7B0a186eae-abf0-4514-a951-23db5eccc286%7D/"}, "avatar": {"href": "https://avatar-management--avatars.us-west-2.prod.public.atl-paas.net/557058:f3968cd3-4910-4384-8349-482a6c7889ec/5445ce6e-6273-47f0-84eb-621c86ca11cb/128"}}, "nickname": "hsu", "type": "user", "account_id": "557058:f3968cd3-4910-4384-8349-482a6c7889ec"}, "date": "2015-11-13T22:24:05.663137+00:00"}, "pull_request": {"type": "pullrequest", "id": 1974, "links": {"self": {"href": "data/repositories/osrf/gazebo/pullrequests/1974.json"}, "html": {"href": "#!/osrf/gazebo/pull-requests/1974"}}, "title": "Elastic_modulus"}}, {"comment": {"links": {"self": {"href": "data/repositories/osrf/gazebo/pullrequests/1974/comments/11672066.json"}, "html": {"href": "#!/osrf/gazebo/pull-requests/1974/_/diff#comment-11672066"}}, "deleted": false, "pullrequest": {"type": "pullrequest", "id": 1974, "links": {"self": {"href": "data/repositories/osrf/gazebo/pullrequests/1974.json"}, "html": {"href": "#!/osrf/gazebo/pull-requests/1974"}}, "title": "Elastic_modulus"}, "content": {"raw": "Are we checking that `e_star`, `patch_radius` or `depth` are non-zero somewhere?", "markup": "markdown", "html": "<p>Are we checking that <code>e_star</code>, <code>patch_radius</code> or <code>depth</code> are non-zero somewhere?</p>", "type": "rendered"}, "created_on": "2015-11-10T22:06:15.870736+00:00", "user": {"display_name": "Carlos Ag\u00fcero", "uuid": "{da8a8e89-4bb0-421b-bd0e-dbbed3d4ed6a}", "links": {"self": {"href": "https://api.bitbucket.org/2.0/users/%7Bda8a8e89-4bb0-421b-bd0e-dbbed3d4ed6a%7D"}, "html": {"href": "https://bitbucket.org/%7Bda8a8e89-4bb0-421b-bd0e-dbbed3d4ed6a%7D/"}, "avatar": {"href": "data/secure.gravatar.com/avatar/692bf15758111acaddae4da15a47f9e5d=httpsavatar-management--avatars.us-west-2.prod.public.atl-paas.netinitialsCA-0.png"}}, "nickname": "caguero", "type": "user", "account_id": "557058:4ded1ddf-947e-4154-bbd1-3dba24f1bdbd"}, "inline": {}, "updated_on": "2015-11-10T22:06:15.875556+00:00", "type": "pullrequest_comment", "id": 11672066}, "pull_request": {"type": "pullrequest", "id": 1974, "links": {"self": {"href": "data/repositories/osrf/gazebo/pullrequests/1974.json"}, "html": {"href": "#!/osrf/gazebo/pull-requests/1974"}}, "title": "Elastic_modulus"}}, {"comment": {"links": {"self": {"href": "data/repositories/osrf/gazebo/pullrequests/1974/comments/11493151.json"}, "html": {"href": "#!/osrf/gazebo/pull-requests/1974/_/diff#comment-11493151"}}, "parent": {"id": 11490737, "links": {"self": {"href": "data/repositories/osrf/gazebo/pullrequests/1974/comments/11490737.json"}, "html": {"href": "#!/osrf/gazebo/pull-requests/1974/_/diff#comment-11490737"}}}, "deleted": false, "pullrequest": {"type": "pullrequest", "id": 1974, "links": {"self": {"href": "data/repositories/osrf/gazebo/pullrequests/1974.json"}, "html": {"href": "#!/osrf/gazebo/pull-requests/1974"}}, "title": "Elastic_modulus"}, "content": {"raw": "[restarted test](http://build.osrfoundation.org/job/gazebo-any-devel-trusty-amd64-gpu-nvidia/613/) since adding linearization (087716c and 391716e)\n", "markup": "markdown", "html": "<p><a data-is-external-link=\"true\" href=\"http://build.osrfoundation.org/job/gazebo-any-devel-trusty-amd64-gpu-nvidia/613/\" rel=\"nofollow\">restarted test</a> since adding linearization (<a href=\"#!/osrf/gazebo/commits/087716c\" rel=\"nofollow\" class=\"ap-connect-link\">087716c</a> and <a href=\"#!/osrf/gazebo/commits/391716e\" rel=\"nofollow\" class=\"ap-connect-link\">391716e</a>)</p>", "type": "rendered"}, "created_on": "2015-11-05T06:42:23.034658+00:00", "user": {"display_name": "John Hsu", "uuid": "{0a186eae-abf0-4514-a951-23db5eccc286}", "links": {"self": {"href": "https://api.bitbucket.org/2.0/users/%7B0a186eae-abf0-4514-a951-23db5eccc286%7D"}, "html": {"href": "https://bitbucket.org/%7B0a186eae-abf0-4514-a951-23db5eccc286%7D/"}, "avatar": {"href": "https://avatar-management--avatars.us-west-2.prod.public.atl-paas.net/557058:f3968cd3-4910-4384-8349-482a6c7889ec/5445ce6e-6273-47f0-84eb-621c86ca11cb/128"}}, "nickname": "hsu", "type": "user", "account_id": "557058:f3968cd3-4910-4384-8349-482a6c7889ec"}, "updated_on": "2015-11-05T06:42:23.043492+00:00", "type": "pullrequest_comment", "id": 11493151}, "pull_request": {"type": "pullrequest", "id": 1974, "links": {"self": {"href": "data/repositories/osrf/gazebo/pullrequests/1974.json"}, "html": {"href": "#!/osrf/gazebo/pull-requests/1974"}}, "title": "Elastic_modulus"}}, {"comment": {"links": {"self": {"href": "data/repositories/osrf/gazebo/pullrequests/1974/comments/11493141.json"}, "html": {"href": "#!/osrf/gazebo/pull-requests/1974/_/diff#comment-11493141"}}, "parent": {"id": 11483677, "links": {"self": {"href": "data/repositories/osrf/gazebo/pullrequests/1974/comments/11483677.json"}, "html": {"href": "#!/osrf/gazebo/pull-requests/1974/_/diff#comment-11483677"}}}, "deleted": false, "pullrequest": {"type": "pullrequest", "id": 1974, "links": {"self": {"href": "data/repositories/osrf/gazebo/pullrequests/1974.json"}, "html": {"href": "#!/osrf/gazebo/pull-requests/1974"}}, "title": "Elastic_modulus"}, "content": {"raw": "68289fd", "markup": "markdown", "html": "<p><a href=\"#!/osrf/gazebo/commits/68289fd\" rel=\"nofollow\" class=\"ap-connect-link\">68289fd</a></p>", "type": "rendered"}, "created_on": "2015-11-05T06:40:46.591480+00:00", "user": {"display_name": "John Hsu", "uuid": "{0a186eae-abf0-4514-a951-23db5eccc286}", "links": {"self": {"href": "https://api.bitbucket.org/2.0/users/%7B0a186eae-abf0-4514-a951-23db5eccc286%7D"}, "html": {"href": "https://bitbucket.org/%7B0a186eae-abf0-4514-a951-23db5eccc286%7D/"}, "avatar": {"href": "https://avatar-management--avatars.us-west-2.prod.public.atl-paas.net/557058:f3968cd3-4910-4384-8349-482a6c7889ec/5445ce6e-6273-47f0-84eb-621c86ca11cb/128"}}, "nickname": "hsu", "type": "user", "account_id": "557058:f3968cd3-4910-4384-8349-482a6c7889ec"}, "inline": {}, "updated_on": "2015-11-05T06:40:46.593672+00:00", "type": "pullrequest_comment", "id": 11493141}, "pull_request": {"type": "pullrequest", "id": 1974, "links": {"self": {"href": "data/repositories/osrf/gazebo/pullrequests/1974.json"}, "html": {"href": "#!/osrf/gazebo/pull-requests/1974"}}, "title": "Elastic_modulus"}}, {"comment": {"links": {"self": {"href": "data/repositories/osrf/gazebo/pullrequests/1974/comments/11493137.json"}, "html": {"href": "#!/osrf/gazebo/pull-requests/1974/_/diff#comment-11493137"}}, "parent": {"id": 11483430, "links": {"self": {"href": "data/repositories/osrf/gazebo/pullrequests/1974/comments/11483430.json"}, "html": {"href": "#!/osrf/gazebo/pull-requests/1974/_/diff#comment-11483430"}}}, "deleted": false, "pullrequest": {"type": "pullrequest", "id": 1974, "links": {"self": {"href": "data/repositories/osrf/gazebo/pullrequests/1974.json"}, "html": {"href": "#!/osrf/gazebo/pull-requests/1974"}}, "title": "Elastic_modulus"}, "content": {"raw": "bccec5c", "markup": "markdown", "html": "<p><a href=\"#!/osrf/gazebo/commits/bccec5c\" rel=\"nofollow\" class=\"ap-connect-link\">bccec5c</a></p>", "type": "rendered"}, "created_on": "2015-11-05T06:40:29.389210+00:00", "user": {"display_name": "John Hsu", "uuid": "{0a186eae-abf0-4514-a951-23db5eccc286}", "links": {"self": {"href": "https://api.bitbucket.org/2.0/users/%7B0a186eae-abf0-4514-a951-23db5eccc286%7D"}, "html": {"href": "https://bitbucket.org/%7B0a186eae-abf0-4514-a951-23db5eccc286%7D/"}, "avatar": {"href": "https://avatar-management--avatars.us-west-2.prod.public.atl-paas.net/557058:f3968cd3-4910-4384-8349-482a6c7889ec/5445ce6e-6273-47f0-84eb-621c86ca11cb/128"}}, "nickname": "hsu", "type": "user", "account_id": "557058:f3968cd3-4910-4384-8349-482a6c7889ec"}, "inline": {}, "updated_on": "2015-11-05T06:40:29.393105+00:00", "type": "pullrequest_comment", "id": 11493137}, "pull_request": {"type": "pullrequest", "id": 1974, "links": {"self": {"href": "data/repositories/osrf/gazebo/pullrequests/1974.json"}, "html": {"href": "#!/osrf/gazebo/pull-requests/1974"}}, "title": "Elastic_modulus"}}, {"update": {"description": "* implement Poisson's Ratio and Elastic Modulus for ODE\r\n* add conditional specifying when to use Elastic Modulus (dContactEM).\r\n* setting up elastic modulus test\r\n", "title": "Elastic_modulus", "destination": {"commit": {"hash": "8f2b990230cd", "type": "commit", "links": {"self": {"href": "data/repositories/osrf/gazebo/commit/8f2b990230cd.json"}, "html": {"href": "#!/osrf/gazebo/commits/8f2b990230cd"}}}, "repository": {"links": {"self": {"href": "data/repositories/osrf/gazebo.json"}, "html": {"href": "#!/osrf/gazebo"}, "avatar": {"href": "data/bytebucket.org/ravatar/{51a0cd5d-8697-4eb1-8b08-e919ee881e1c}ts=1694483"}}, "type": "repository", "name": "gazebo", "full_name": "osrf/gazebo", "uuid": "{51a0cd5d-8697-4eb1-8b08-e919ee881e1c}"}, "branch": {"name": "default"}}, "reason": "", "source": {"commit": {"hash": "bccec5c166e4", "type": "commit", "links": {"self": {"href": "data/repositories/osrf/gazebo/commit/bccec5c166e4.json"}, "html": {"href": "#!/osrf/gazebo/commits/bccec5c166e4"}}}, "repository": {"links": {"self": {"href": "data/repositories/osrf/gazebo.json"}, "html": {"href": "#!/osrf/gazebo"}, "avatar": {"href": "data/bytebucket.org/ravatar/{51a0cd5d-8697-4eb1-8b08-e919ee881e1c}ts=1694483"}}, "type": "repository", "name": "gazebo", "full_name": "osrf/gazebo", "uuid": "{51a0cd5d-8697-4eb1-8b08-e919ee881e1c}"}, "branch": {"name": "elastic_modulus"}}, "state": "OPEN", "author": {"display_name": "John Hsu", "uuid": "{0a186eae-abf0-4514-a951-23db5eccc286}", "links": {"self": {"href": "https://api.bitbucket.org/2.0/users/%7B0a186eae-abf0-4514-a951-23db5eccc286%7D"}, "html": {"href": "https://bitbucket.org/%7B0a186eae-abf0-4514-a951-23db5eccc286%7D/"}, "avatar": {"href": "https://avatar-management--avatars.us-west-2.prod.public.atl-paas.net/557058:f3968cd3-4910-4384-8349-482a6c7889ec/5445ce6e-6273-47f0-84eb-621c86ca11cb/128"}}, "nickname": "hsu", "type": "user", "account_id": "557058:f3968cd3-4910-4384-8349-482a6c7889ec"}, "date": "2015-11-05T06:40:15.804825+00:00"}, "pull_request": {"type": "pullrequest", "id": 1974, "links": {"self": {"href": "data/repositories/osrf/gazebo/pullrequests/1974.json"}, "html": {"href": "#!/osrf/gazebo/pull-requests/1974"}}, "title": "Elastic_modulus"}}, {"update": {"description": "* implement Poisson's Ratio and Elastic Modulus for ODE\r\n* add conditional specifying when to use Elastic Modulus (dContactEM).\r\n* setting up elastic modulus test\r\n", "title": "Elastic_modulus", "destination": {"commit": {"hash": "8f2b990230cd", "type": "commit", "links": {"self": {"href": "data/repositories/osrf/gazebo/commit/8f2b990230cd.json"}, "html": {"href": "#!/osrf/gazebo/commits/8f2b990230cd"}}}, "repository": {"links": {"self": {"href": "data/repositories/osrf/gazebo.json"}, "html": {"href": "#!/osrf/gazebo"}, "avatar": {"href": "data/bytebucket.org/ravatar/{51a0cd5d-8697-4eb1-8b08-e919ee881e1c}ts=1694483"}}, "type": "repository", "name": "gazebo", "full_name": "osrf/gazebo", "uuid": "{51a0cd5d-8697-4eb1-8b08-e919ee881e1c}"}, "branch": {"name": "default"}}, "reason": "", "source": {"commit": {"hash": "68289fd97756", "type": "commit", "links": {"self": {"href": "data/repositories/osrf/gazebo/commit/68289fd97756.json"}, "html": {"href": "#!/osrf/gazebo/commits/68289fd97756"}}}, "repository": {"links": {"self": {"href": "data/repositories/osrf/gazebo.json"}, "html": {"href": "#!/osrf/gazebo"}, "avatar": {"href": "data/bytebucket.org/ravatar/{51a0cd5d-8697-4eb1-8b08-e919ee881e1c}ts=1694483"}}, "type": "repository", "name": "gazebo", "full_name": "osrf/gazebo", "uuid": "{51a0cd5d-8697-4eb1-8b08-e919ee881e1c}"}, "branch": {"name": "elastic_modulus"}}, "state": "OPEN", "author": {"display_name": "John Hsu", "uuid": "{0a186eae-abf0-4514-a951-23db5eccc286}", "links": {"self": {"href": "https://api.bitbucket.org/2.0/users/%7B0a186eae-abf0-4514-a951-23db5eccc286%7D"}, "html": {"href": "https://bitbucket.org/%7B0a186eae-abf0-4514-a951-23db5eccc286%7D/"}, "avatar": {"href": "https://avatar-management--avatars.us-west-2.prod.public.atl-paas.net/557058:f3968cd3-4910-4384-8349-482a6c7889ec/5445ce6e-6273-47f0-84eb-621c86ca11cb/128"}}, "nickname": "hsu", "type": "user", "account_id": "557058:f3968cd3-4910-4384-8349-482a6c7889ec"}, "date": "2015-11-05T06:38:15.412621+00:00"}, "pull_request": {"type": "pullrequest", "id": 1974, "links": {"self": {"href": "data/repositories/osrf/gazebo/pullrequests/1974.json"}, "html": {"href": "#!/osrf/gazebo/pull-requests/1974"}}, "title": "Elastic_modulus"}}, {"update": {"description": "* implement Poisson's Ratio and Elastic Modulus for ODE\r\n* add conditional specifying when to use Elastic Modulus (dContactEM).\r\n* setting up elastic modulus test\r\n", "title": "Elastic_modulus", "destination": {"commit": {"hash": "8f2b990230cd", "type": "commit", "links": {"self": {"href": "data/repositories/osrf/gazebo/commit/8f2b990230cd.json"}, "html": {"href": "#!/osrf/gazebo/commits/8f2b990230cd"}}}, "repository": {"links": {"self": {"href": "data/repositories/osrf/gazebo.json"}, "html": {"href": "#!/osrf/gazebo"}, "avatar": {"href": "data/bytebucket.org/ravatar/{51a0cd5d-8697-4eb1-8b08-e919ee881e1c}ts=1694483"}}, "type": "repository", "name": "gazebo", "full_name": "osrf/gazebo", "uuid": "{51a0cd5d-8697-4eb1-8b08-e919ee881e1c}"}, "branch": {"name": "default"}}, "reason": "", "source": {"commit": {"hash": "f2c95345e151", "type": "commit", "links": {"self": {"href": "data/repositories/osrf/gazebo/commit/f2c95345e151.json"}, "html": {"href": "#!/osrf/gazebo/commits/f2c95345e151"}}}, "repository": {"links": {"self": {"href": "data/repositories/osrf/gazebo.json"}, "html": {"href": "#!/osrf/gazebo"}, "avatar": {"href": "data/bytebucket.org/ravatar/{51a0cd5d-8697-4eb1-8b08-e919ee881e1c}ts=1694483"}}, "type": "repository", "name": "gazebo", "full_name": "osrf/gazebo", "uuid": "{51a0cd5d-8697-4eb1-8b08-e919ee881e1c}"}, "branch": {"name": "elastic_modulus"}}, "state": "OPEN", "author": {"display_name": "John Hsu", "uuid": "{0a186eae-abf0-4514-a951-23db5eccc286}", "links": {"self": {"href": "https://api.bitbucket.org/2.0/users/%7B0a186eae-abf0-4514-a951-23db5eccc286%7D"}, "html": {"href": "https://bitbucket.org/%7B0a186eae-abf0-4514-a951-23db5eccc286%7D/"}, "avatar": {"href": "https://avatar-management--avatars.us-west-2.prod.public.atl-paas.net/557058:f3968cd3-4910-4384-8349-482a6c7889ec/5445ce6e-6273-47f0-84eb-621c86ca11cb/128"}}, "nickname": "hsu", "type": "user", "account_id": "557058:f3968cd3-4910-4384-8349-482a6c7889ec"}, "date": "2015-11-05T06:36:40.936532+00:00"}, "pull_request": {"type": "pullrequest", "id": 1974, "links": {"self": {"href": "data/repositories/osrf/gazebo/pullrequests/1974.json"}, "html": {"href": "#!/osrf/gazebo/pull-requests/1974"}}, "title": "Elastic_modulus"}}, {"comment": {"links": {"self": {"href": "data/repositories/osrf/gazebo/pullrequests/1974/comments/11490737.json"}, "html": {"href": "#!/osrf/gazebo/pull-requests/1974/_/diff#comment-11490737"}}, "parent": {"id": 11403882, "links": {"self": {"href": "data/repositories/osrf/gazebo/pullrequests/1974/comments/11403882.json"}, "html": {"href": "#!/osrf/gazebo/pull-requests/1974/_/diff#comment-11403882"}}}, "deleted": false, "pullrequest": {"type": "pullrequest", "id": 1974, "links": {"self": {"href": "data/repositories/osrf/gazebo/pullrequests/1974.json"}, "html": {"href": "#!/osrf/gazebo/pull-requests/1974"}}, "title": "Elastic_modulus"}, "content": {"raw": "[failed test](http://build.osrfoundation.org/job/gazebo-any-devel-trusty-amd64-gpu-nvidia/608/testReport/(root)/PhysicsEngines_Issue1702Test/SpawnDeleteSpawnAgain_1/) passed locally, probably a spurious failure.", "markup": "markdown", "html": "<p><a data-is-external-link=\"true\" href=\"http://build.osrfoundation.org/job/gazebo-any-devel-trusty-amd64-gpu-nvidia/608/testReport/(root)/PhysicsEngines_Issue1702Test/SpawnDeleteSpawnAgain_1/\" rel=\"nofollow\">failed test</a> passed locally, probably a spurious failure.</p>", "type": "rendered"}, "created_on": "2015-11-05T03:46:03.234081+00:00", "user": {"display_name": "John Hsu", "uuid": "{0a186eae-abf0-4514-a951-23db5eccc286}", "links": {"self": {"href": "https://api.bitbucket.org/2.0/users/%7B0a186eae-abf0-4514-a951-23db5eccc286%7D"}, "html": {"href": "https://bitbucket.org/%7B0a186eae-abf0-4514-a951-23db5eccc286%7D/"}, "avatar": {"href": "https://avatar-management--avatars.us-west-2.prod.public.atl-paas.net/557058:f3968cd3-4910-4384-8349-482a6c7889ec/5445ce6e-6273-47f0-84eb-621c86ca11cb/128"}}, "nickname": "hsu", "type": "user", "account_id": "557058:f3968cd3-4910-4384-8349-482a6c7889ec"}, "updated_on": "2015-11-05T03:46:03.236595+00:00", "type": "pullrequest_comment", "id": 11490737}, "pull_request": {"type": "pullrequest", "id": 1974, "links": {"self": {"href": "data/repositories/osrf/gazebo/pullrequests/1974.json"}, "html": {"href": "#!/osrf/gazebo/pull-requests/1974"}}, "title": "Elastic_modulus"}}, {"comment": {"links": {"self": {"href": "data/repositories/osrf/gazebo/pullrequests/1974/comments/11483677.json"}, "html": {"href": "#!/osrf/gazebo/pull-requests/1974/_/diff#comment-11483677"}}, "deleted": false, "pullrequest": {"type": "pullrequest", "id": 1974, "links": {"self": {"href": "data/repositories/osrf/gazebo/pullrequests/1974.json"}, "html": {"href": "#!/osrf/gazebo/pull-requests/1974"}}, "title": "Elastic_modulus"}, "content": {"raw": "_modulus -> _ratio", "markup": "markdown", "html": "<p>_modulus -&gt; _ratio</p>", "type": "rendered"}, "created_on": "2015-11-04T21:38:24.098594+00:00", "user": {"display_name": "Louise Poubel", "uuid": "{5cfa2075-477b-4ded-bdb9-8d2479544ec4}", "links": {"self": {"href": "https://api.bitbucket.org/2.0/users/%7B5cfa2075-477b-4ded-bdb9-8d2479544ec4%7D"}, "html": {"href": "https://bitbucket.org/%7B5cfa2075-477b-4ded-bdb9-8d2479544ec4%7D/"}, "avatar": {"href": "https://avatar-management--avatars.us-west-2.prod.public.atl-paas.net/557058:6ff86fcb-b7ab-44a5-b8a6-f6d9cae8b6e8/7d903d90-c5ea-4182-b7ef-0d467e9e1c74/128"}}, "nickname": "chapulina", "type": "user", "account_id": "557058:6ff86fcb-b7ab-44a5-b8a6-f6d9cae8b6e8"}, "inline": {}, "updated_on": "2015-11-04T21:38:24.100967+00:00", "type": "pullrequest_comment", "id": 11483677}, "pull_request": {"type": "pullrequest", "id": 1974, "links": {"self": {"href": "data/repositories/osrf/gazebo/pullrequests/1974.json"}, "html": {"href": "#!/osrf/gazebo/pull-requests/1974"}}, "title": "Elastic_modulus"}}, {"comment": {"links": {"self": {"href": "data/repositories/osrf/gazebo/pullrequests/1974/comments/11483430.json"}, "html": {"href": "#!/osrf/gazebo/pull-requests/1974/_/diff#comment-11483430"}}, "deleted": false, "pullrequest": {"type": "pullrequest", "id": 1974, "links": {"self": {"href": "data/repositories/osrf/gazebo/pullrequests/1974.json"}, "html": {"href": "#!/osrf/gazebo/pull-requests/1974"}}, "title": "Elastic_modulus"}, "content": {"raw": "Update changelog?", "markup": "markdown", "html": "<p>Update changelog?</p>", "type": "rendered"}, "created_on": "2015-11-04T21:30:52.388234+00:00", "user": {"display_name": "Louise Poubel", "uuid": "{5cfa2075-477b-4ded-bdb9-8d2479544ec4}", "links": {"self": {"href": "https://api.bitbucket.org/2.0/users/%7B5cfa2075-477b-4ded-bdb9-8d2479544ec4%7D"}, "html": {"href": "https://bitbucket.org/%7B5cfa2075-477b-4ded-bdb9-8d2479544ec4%7D/"}, "avatar": {"href": "https://avatar-management--avatars.us-west-2.prod.public.atl-paas.net/557058:6ff86fcb-b7ab-44a5-b8a6-f6d9cae8b6e8/7d903d90-c5ea-4182-b7ef-0d467e9e1c74/128"}}, "nickname": "chapulina", "type": "user", "account_id": "557058:6ff86fcb-b7ab-44a5-b8a6-f6d9cae8b6e8"}, "inline": {}, "updated_on": "2015-11-04T21:30:52.390269+00:00", "type": "pullrequest_comment", "id": 11483430}, "pull_request": {"type": "pullrequest", "id": 1974, "links": {"self": {"href": "data/repositories/osrf/gazebo/pullrequests/1974.json"}, "html": {"href": "#!/osrf/gazebo/pull-requests/1974"}}, "title": "Elastic_modulus"}}, {"comment": {"links": {"self": {"href": "data/repositories/osrf/gazebo/pullrequests/1974/comments/11403882.json"}, "html": {"href": "#!/osrf/gazebo/pull-requests/1974/_/diff#comment-11403882"}}, "deleted": false, "pullrequest": {"type": "pullrequest", "id": 1974, "links": {"self": {"href": "data/repositories/osrf/gazebo/pullrequests/1974.json"}, "html": {"href": "#!/osrf/gazebo/pull-requests/1974"}}, "title": "Elastic_modulus"}, "content": {"raw": "[any devel](http://build.osrfoundation.org/job/gazebo-any-devel-trusty-amd64-gpu-nvidia/608/)", "markup": "markdown", "html": "<p><a data-is-external-link=\"true\" href=\"http://build.osrfoundation.org/job/gazebo-any-devel-trusty-amd64-gpu-nvidia/608/\" rel=\"nofollow\">any devel</a></p>", "type": "rendered"}, "created_on": "2015-11-03T05:00:29.734099+00:00", "user": {"display_name": "John Hsu", "uuid": "{0a186eae-abf0-4514-a951-23db5eccc286}", "links": {"self": {"href": "https://api.bitbucket.org/2.0/users/%7B0a186eae-abf0-4514-a951-23db5eccc286%7D"}, "html": {"href": "https://bitbucket.org/%7B0a186eae-abf0-4514-a951-23db5eccc286%7D/"}, "avatar": {"href": "https://avatar-management--avatars.us-west-2.prod.public.atl-paas.net/557058:f3968cd3-4910-4384-8349-482a6c7889ec/5445ce6e-6273-47f0-84eb-621c86ca11cb/128"}}, "nickname": "hsu", "type": "user", "account_id": "557058:f3968cd3-4910-4384-8349-482a6c7889ec"}, "updated_on": "2015-11-03T05:00:29.738599+00:00", "type": "pullrequest_comment", "id": 11403882}, "pull_request": {"type": "pullrequest", "id": 1974, "links": {"self": {"href": "data/repositories/osrf/gazebo/pullrequests/1974.json"}, "html": {"href": "#!/osrf/gazebo/pull-requests/1974"}}, "title": "Elastic_modulus"}}, {"update": {"description": "* implement Poisson's Ratio and Elastic Modulus for ODE\r\n* add conditional specifying when to use Elastic Modulus (dContactEM).\r\n* setting up elastic modulus test\r\n", "title": "Elastic_modulus", "destination": {"commit": {"hash": "f88bf8e699db", "type": "commit", "links": {"self": {"href": "data/repositories/osrf/gazebo/commit/f88bf8e699db.json"}, "html": {"href": "#!/osrf/gazebo/commits/f88bf8e699db"}}}, "repository": {"links": {"self": {"href": "data/repositories/osrf/gazebo.json"}, "html": {"href": "#!/osrf/gazebo"}, "avatar": {"href": "data/bytebucket.org/ravatar/{51a0cd5d-8697-4eb1-8b08-e919ee881e1c}ts=1694483"}}, "type": "repository", "name": "gazebo", "full_name": "osrf/gazebo", "uuid": "{51a0cd5d-8697-4eb1-8b08-e919ee881e1c}"}, "branch": {"name": "default"}}, "reason": "", "source": {"commit": {"hash": "b9718bd8eb7d", "type": "commit", "links": {"self": {"href": "data/repositories/osrf/gazebo/commit/b9718bd8eb7d.json"}, "html": {"href": "#!/osrf/gazebo/commits/b9718bd8eb7d"}}}, "repository": {"links": {"self": {"href": "data/repositories/osrf/gazebo.json"}, "html": {"href": "#!/osrf/gazebo"}, "avatar": {"href": "data/bytebucket.org/ravatar/{51a0cd5d-8697-4eb1-8b08-e919ee881e1c}ts=1694483"}}, "type": "repository", "name": "gazebo", "full_name": "osrf/gazebo", "uuid": "{51a0cd5d-8697-4eb1-8b08-e919ee881e1c}"}, "branch": {"name": "elastic_modulus"}}, "state": "OPEN", "author": {"display_name": "John Hsu", "uuid": "{0a186eae-abf0-4514-a951-23db5eccc286}", "links": {"self": {"href": "https://api.bitbucket.org/2.0/users/%7B0a186eae-abf0-4514-a951-23db5eccc286%7D"}, "html": {"href": "https://bitbucket.org/%7B0a186eae-abf0-4514-a951-23db5eccc286%7D/"}, "avatar": {"href": "https://avatar-management--avatars.us-west-2.prod.public.atl-paas.net/557058:f3968cd3-4910-4384-8349-482a6c7889ec/5445ce6e-6273-47f0-84eb-621c86ca11cb/128"}}, "nickname": "hsu", "type": "user", "account_id": "557058:f3968cd3-4910-4384-8349-482a6c7889ec"}, "date": "2015-11-03T04:59:10.328060+00:00"}, "pull_request": {"type": "pullrequest", "id": 1974, "links": {"self": {"href": "data/repositories/osrf/gazebo/pullrequests/1974.json"}, "html": {"href": "#!/osrf/gazebo/pull-requests/1974"}}, "title": "Elastic_modulus"}}, {"update": {"description": "* implement Poisson's Ratio and Elastic Modulus for ODE\r\n* add conditional specifying when to use Elastic Modulus (dContactEM).\r\n* setting up elastic modulus test\r\n", "title": "Elastic_modulus", "destination": {"commit": {"hash": "f88bf8e699db", "type": "commit", "links": {"self": {"href": "data/repositories/osrf/gazebo/commit/f88bf8e699db.json"}, "html": {"href": "#!/osrf/gazebo/commits/f88bf8e699db"}}}, "repository": {"links": {"self": {"href": "data/repositories/osrf/gazebo.json"}, "html": {"href": "#!/osrf/gazebo"}, "avatar": {"href": "data/bytebucket.org/ravatar/{51a0cd5d-8697-4eb1-8b08-e919ee881e1c}ts=1694483"}}, "type": "repository", "name": "gazebo", "full_name": "osrf/gazebo", "uuid": "{51a0cd5d-8697-4eb1-8b08-e919ee881e1c}"}, "branch": {"name": "default"}}, "reason": "", "source": {"commit": {"hash": "b9718bd8eb7d", "type": "commit", "links": {"self": {"href": "data/repositories/osrf/gazebo/commit/b9718bd8eb7d.json"}, "html": {"href": "#!/osrf/gazebo/commits/b9718bd8eb7d"}}}, "repository": {"links": {"self": {"href": "data/repositories/osrf/gazebo.json"}, "html": {"href": "#!/osrf/gazebo"}, "avatar": {"href": "data/bytebucket.org/ravatar/{51a0cd5d-8697-4eb1-8b08-e919ee881e1c}ts=1694483"}}, "type": "repository", "name": "gazebo", "full_name": "osrf/gazebo", "uuid": "{51a0cd5d-8697-4eb1-8b08-e919ee881e1c}"}, "branch": {"name": "elastic_modulus"}}, "state": "OPEN", "author": {"display_name": "John Hsu", "uuid": "{0a186eae-abf0-4514-a951-23db5eccc286}", "links": {"self": {"href": "https://api.bitbucket.org/2.0/users/%7B0a186eae-abf0-4514-a951-23db5eccc286%7D"}, "html": {"href": "https://bitbucket.org/%7B0a186eae-abf0-4514-a951-23db5eccc286%7D/"}, "avatar": {"href": "https://avatar-management--avatars.us-west-2.prod.public.atl-paas.net/557058:f3968cd3-4910-4384-8349-482a6c7889ec/5445ce6e-6273-47f0-84eb-621c86ca11cb/128"}}, "nickname": "hsu", "type": "user", "account_id": "557058:f3968cd3-4910-4384-8349-482a6c7889ec"}, "date": "2015-11-03T04:59:10.300455+00:00"}, "pull_request": {"type": "pullrequest", "id": 1974, "links": {"self": {"href": "data/repositories/osrf/gazebo/pullrequests/1974.json"}, "html": {"href": "#!/osrf/gazebo/pull-requests/1974"}}, "title": "Elastic_modulus"}}]}