{"pagelen": 100, "values": [{"links": {"self": {"href": "data/repositories/osrf/gazebo/pullrequests/3100/comments/99741758.json"}, "html": {"href": "#!/osrf/gazebo/pull-requests/3100/_/diff#comment-99741758"}}, "deleted": false, "pullrequest": {"type": "pullrequest", "id": 3100, "links": {"self": {"href": "data/repositories/osrf/gazebo/pullrequests/3100.json"}, "html": {"href": "#!/osrf/gazebo/pull-requests/3100"}}, "title": "Make the GPU laser warp artifact transparent"}, "content": {"raw": "~~We need to wait until pull request #3101 is merged to check CI.~~", "markup": "markdown", "html": "<p><del>We need to wait until <a href=\"#!/osrf/gazebo/pull-requests/3101/use-dart-67-behavior-for-setting\" rel=\"nofollow\" class=\"ap-connect-link\">pull request #3101</a> is merged to check CI.</del></p>", "type": "rendered"}, "created_on": "2019-04-24T00:18:18.875125+00:00", "user": {"display_name": "Carlos Ag\u00fcero", "uuid": "{da8a8e89-4bb0-421b-bd0e-dbbed3d4ed6a}", "links": {"self": {"href": "https://api.bitbucket.org/2.0/users/%7Bda8a8e89-4bb0-421b-bd0e-dbbed3d4ed6a%7D"}, "html": {"href": "https://bitbucket.org/%7Bda8a8e89-4bb0-421b-bd0e-dbbed3d4ed6a%7D/"}, "avatar": {"href": "data/secure.gravatar.com/avatar/692bf15758111acaddae4da15a47f9e5d=httpsavatar-management--avatars.us-west-2.prod.public.atl-paas.netinitialsCA-0.png"}}, "nickname": "caguero", "type": "user", "account_id": "557058:4ded1ddf-947e-4154-bbd1-3dba24f1bdbd"}, "updated_on": "2019-04-25T17:49:49.935952+00:00", "type": "pullrequest_comment", "id": 99741758}, {"links": {"self": {"href": "data/repositories/osrf/gazebo/pullrequests/3100/comments/99924120.json"}, "html": {"href": "#!/osrf/gazebo/pull-requests/3100/_/diff#comment-99924120"}}, "deleted": false, "pullrequest": {"type": "pullrequest", "id": 3100, "links": {"self": {"href": "data/repositories/osrf/gazebo/pullrequests/3100.json"}, "html": {"href": "#!/osrf/gazebo/pull-requests/3100"}}, "title": "Make the GPU laser warp artifact transparent"}, "content": {"raw": "So do you need a GPU laser sensor and a camera in a model in order to reproduce this issue?", "markup": "markdown", "html": "<p>So do you need a GPU laser sensor and a camera in a model in order to reproduce this issue?</p>", "type": "rendered"}, "created_on": "2019-04-25T05:53:42.318670+00:00", "user": {"display_name": "Steve Peters", "uuid": "{2ccfed09-18b8-4921-8d58-15ef01092802}", "links": {"self": {"href": "https://api.bitbucket.org/2.0/users/%7B2ccfed09-18b8-4921-8d58-15ef01092802%7D"}, "html": {"href": "https://bitbucket.org/%7B2ccfed09-18b8-4921-8d58-15ef01092802%7D/"}, "avatar": {"href": "data/secure.gravatar.com/avatar/1fb4816dad9e68337d3096f750951f6cd=httpsavatar-management--avatars.us-west-2.prod.public.atl-paas.netinitialsSP-1.png"}}, "nickname": "Steven Peters", "type": "user", "account_id": "557058:5de38267-b118-494c-aa76-4fab35448816"}, "updated_on": "2019-04-25T05:53:42.327113+00:00", "type": "pullrequest_comment", "id": 99924120}, {"links": {"self": {"href": "data/repositories/osrf/gazebo/pullrequests/3100/comments/100016334.json"}, "html": {"href": "#!/osrf/gazebo/pull-requests/3100/_/diff#comment-100016334"}}, "parent": {"id": 99924120, "links": {"self": {"href": "data/repositories/osrf/gazebo/pullrequests/3100/comments/99924120.json"}, "html": {"href": "#!/osrf/gazebo/pull-requests/3100/_/diff#comment-99924120"}}, "depth": 1}, "deleted": false, "pullrequest": {"type": "pullrequest", "id": 3100, "links": {"self": {"href": "data/repositories/osrf/gazebo/pullrequests/3100.json"}, "html": {"href": "#!/osrf/gazebo/pull-requests/3100"}}, "title": "Make the GPU laser warp artifact transparent"}, "content": {"raw": "Yes but I wasn\u2019t able to reproduce the issue with a stand alone example in Gazebo. I can see the issue in VRX.", "markup": "markdown", "html": "<p>Yes but I wasn\u2019t able to reproduce the issue with a stand alone example in Gazebo. I can see the issue in VRX.</p>", "type": "rendered"}, "created_on": "2019-04-25T15:10:09.046200+00:00", "user": {"display_name": "Carlos Ag\u00fcero", "uuid": "{da8a8e89-4bb0-421b-bd0e-dbbed3d4ed6a}", "links": {"self": {"href": "https://api.bitbucket.org/2.0/users/%7Bda8a8e89-4bb0-421b-bd0e-dbbed3d4ed6a%7D"}, "html": {"href": "https://bitbucket.org/%7Bda8a8e89-4bb0-421b-bd0e-dbbed3d4ed6a%7D/"}, "avatar": {"href": "data/secure.gravatar.com/avatar/692bf15758111acaddae4da15a47f9e5d=httpsavatar-management--avatars.us-west-2.prod.public.atl-paas.netinitialsCA-0.png"}}, "nickname": "caguero", "type": "user", "account_id": "557058:4ded1ddf-947e-4154-bbd1-3dba24f1bdbd"}, "updated_on": "2019-04-25T15:10:09.060340+00:00", "type": "pullrequest_comment", "id": 100016334}, {"links": {"self": {"href": "data/repositories/osrf/gazebo/pullrequests/3100/comments/100038913.json"}, "html": {"href": "#!/osrf/gazebo/pull-requests/3100/_/diff#comment-100038913"}}, "deleted": false, "pullrequest": {"type": "pullrequest", "id": 3100, "links": {"self": {"href": "data/repositories/osrf/gazebo/pullrequests/3100.json"}, "html": {"href": "#!/osrf/gazebo/pull-requests/3100"}}, "title": "Make the GPU laser warp artifact transparent"}, "content": {"raw": "restarted builds:\n\n[xenial-nvidia](https://build.osrfoundation.org/job/gazebo-ci-pr_any-xenial-amd64-gpu-nvidia/836)\n\n[homebrew](https://build.osrfoundation.org/job/gazebo-ci-pr_any-homebrew-amd64/1714/)", "markup": "markdown", "html": "<p>restarted builds:</p>\n<p><a data-is-external-link=\"true\" href=\"https://build.osrfoundation.org/job/gazebo-ci-pr_any-xenial-amd64-gpu-nvidia/836\" rel=\"nofollow\">xenial-nvidia</a></p>\n<p><a data-is-external-link=\"true\" href=\"https://build.osrfoundation.org/job/gazebo-ci-pr_any-homebrew-amd64/1714/\" rel=\"nofollow\">homebrew</a></p>", "type": "rendered"}, "created_on": "2019-04-25T17:55:02.794783+00:00", "user": {"display_name": "Ian Chen", "uuid": "{eaa6fca5-6deb-43f6-907f-971c144735dd}", "links": {"self": {"href": "https://api.bitbucket.org/2.0/users/%7Beaa6fca5-6deb-43f6-907f-971c144735dd%7D"}, "html": {"href": "https://bitbucket.org/%7Beaa6fca5-6deb-43f6-907f-971c144735dd%7D/"}, "avatar": {"href": "https://avatar-management--avatars.us-west-2.prod.public.atl-paas.net/557058:10b01d41-a2e9-4a41-a907-e6e2f03b6cd5/1e4adcdf-1946-4280-9aea-eb5f15a7f912/128"}}, "nickname": "Ian Chen", "type": "user", "account_id": "557058:10b01d41-a2e9-4a41-a907-e6e2f03b6cd5"}, "updated_on": "2019-04-25T21:00:59.042240+00:00", "type": "pullrequest_comment", "id": 100038913}, {"links": {"self": {"href": "data/repositories/osrf/gazebo/pullrequests/3100/comments/100068557.json"}, "html": {"href": "#!/osrf/gazebo/pull-requests/3100/_/diff#comment-100068557"}}, "deleted": false, "pullrequest": {"type": "pullrequest", "id": 3100, "links": {"self": {"href": "data/repositories/osrf/gazebo/pullrequests/3100.json"}, "html": {"href": "#!/osrf/gazebo/pull-requests/3100"}}, "title": "Make the GPU laser warp artifact transparent"}, "content": {"raw": "we'll need to add this to the changelog now or later", "markup": "markdown", "html": "<p>we'll need to add this to the changelog now or later</p>", "type": "rendered"}, "created_on": "2019-04-25T23:45:43.814366+00:00", "user": {"display_name": "Steve Peters", "uuid": "{2ccfed09-18b8-4921-8d58-15ef01092802}", "links": {"self": {"href": "https://api.bitbucket.org/2.0/users/%7B2ccfed09-18b8-4921-8d58-15ef01092802%7D"}, "html": {"href": "https://bitbucket.org/%7B2ccfed09-18b8-4921-8d58-15ef01092802%7D/"}, "avatar": {"href": "data/secure.gravatar.com/avatar/1fb4816dad9e68337d3096f750951f6cd=httpsavatar-management--avatars.us-west-2.prod.public.atl-paas.netinitialsSP-1.png"}}, "nickname": "Steven Peters", "type": "user", "account_id": "557058:5de38267-b118-494c-aa76-4fab35448816"}, "updated_on": "2019-04-25T23:45:43.822204+00:00", "type": "pullrequest_comment", "id": 100068557}, {"links": {"self": {"href": "data/repositories/osrf/gazebo/pullrequests/3100/comments/100069977.json"}, "html": {"href": "#!/osrf/gazebo/pull-requests/3100/_/diff#comment-100069977"}}, "parent": {"id": 100068557, "links": {"self": {"href": "data/repositories/osrf/gazebo/pullrequests/3100/comments/100068557.json"}, "html": {"href": "#!/osrf/gazebo/pull-requests/3100/_/diff#comment-100068557"}}, "depth": 1}, "deleted": false, "pullrequest": {"type": "pullrequest", "id": 3100, "links": {"self": {"href": "data/repositories/osrf/gazebo/pullrequests/3100.json"}, "html": {"href": "#!/osrf/gazebo/pull-requests/3100"}}, "title": "Make the GPU laser warp artifact transparent"}, "content": {"raw": "Added in [6c26352](#!/osrf/gazebo/commits/6c26352184c8c9a2e0fdf52d25793ad13fe4b90e?at=gazebo9).", "markup": "markdown", "html": "<p>Added in <a data-is-external-link=\"true\" href=\"#!/osrf/gazebo/commits/6c26352184c8c9a2e0fdf52d25793ad13fe4b90e?at=gazebo9\" rel=\"nofollow\">6c26352</a>.</p>", "type": "rendered"}, "created_on": "2019-04-26T00:18:25.194607+00:00", "user": {"display_name": "Carlos Ag\u00fcero", "uuid": "{da8a8e89-4bb0-421b-bd0e-dbbed3d4ed6a}", "links": {"self": {"href": "https://api.bitbucket.org/2.0/users/%7Bda8a8e89-4bb0-421b-bd0e-dbbed3d4ed6a%7D"}, "html": {"href": "https://bitbucket.org/%7Bda8a8e89-4bb0-421b-bd0e-dbbed3d4ed6a%7D/"}, "avatar": {"href": "data/secure.gravatar.com/avatar/692bf15758111acaddae4da15a47f9e5d=httpsavatar-management--avatars.us-west-2.prod.public.atl-paas.netinitialsCA-0.png"}}, "nickname": "caguero", "type": "user", "account_id": "557058:4ded1ddf-947e-4154-bbd1-3dba24f1bdbd"}, "updated_on": "2019-04-26T00:18:25.204763+00:00", "type": "pullrequest_comment", "id": 100069977}], "page": 1, "size": 6}