{"pagelen": 50, "values": [{"update": {"description": "Issue #402\r\n\r\nUndo / redo:\r\n\r\n* Inserting nested models from the palette\r\n\r\n* Copy/pasting nested models\r\n\r\n* Deleting nested models with the DEL key\r\n\r\n* Deleting nested models via context menu\r\n\r\nObs:\r\n\r\nModel added to `testdb` should be the same as that added in pull request #2207, targeted at gazebo7. Once that is merged forward to default, they will coincide.", "title": "Model Editor: Undo insert / delete nested models", "destination": {"commit": {"hash": "f4d66ce30b32", "type": "commit", "links": {"self": {"href": "data/repositories/osrf/gazebo/commit/f4d66ce30b32.json"}, "html": {"href": "#!/osrf/gazebo/commits/f4d66ce30b32"}}}, "repository": {"links": {"self": {"href": "data/repositories/osrf/gazebo.json"}, "html": {"href": "#!/osrf/gazebo"}, "avatar": {"href": "data/bytebucket.org/ravatar/{51a0cd5d-8697-4eb1-8b08-e919ee881e1c}ts=1694483"}}, "type": "repository", "name": "gazebo", "full_name": "osrf/gazebo", "uuid": "{51a0cd5d-8697-4eb1-8b08-e919ee881e1c}"}, "branch": {"name": "default"}}, "reason": "", "source": {"commit": {"hash": "b61a78535f8e", "type": "commit", "links": {"self": {"href": "data/repositories/osrf/gazebo/commit/b61a78535f8e.json"}, "html": {"href": "#!/osrf/gazebo/commits/b61a78535f8e"}}}, "repository": {"links": {"self": {"href": "data/repositories/osrf/gazebo.json"}, "html": {"href": "#!/osrf/gazebo"}, "avatar": {"href": "data/bytebucket.org/ravatar/{51a0cd5d-8697-4eb1-8b08-e919ee881e1c}ts=1694483"}}, "type": "repository", "name": "gazebo", "full_name": "osrf/gazebo", "uuid": "{51a0cd5d-8697-4eb1-8b08-e919ee881e1c}"}, "branch": {"name": "undo_ME_nestedModel_insertion_deletion"}}, "state": "MERGED", "author": {"display_name": "Louise Poubel", "uuid": "{5cfa2075-477b-4ded-bdb9-8d2479544ec4}", "links": {"self": {"href": "https://api.bitbucket.org/2.0/users/%7B5cfa2075-477b-4ded-bdb9-8d2479544ec4%7D"}, "html": {"href": "https://bitbucket.org/%7B5cfa2075-477b-4ded-bdb9-8d2479544ec4%7D/"}, "avatar": {"href": "https://avatar-management--avatars.us-west-2.prod.public.atl-paas.net/557058:6ff86fcb-b7ab-44a5-b8a6-f6d9cae8b6e8/7d903d90-c5ea-4182-b7ef-0d467e9e1c74/128"}}, "nickname": "chapulina", "type": "user", "account_id": "557058:6ff86fcb-b7ab-44a5-b8a6-f6d9cae8b6e8"}, "date": "2016-04-14T19:57:15.992209+00:00"}, "pull_request": {"type": "pullrequest", "id": 2229, "links": {"self": {"href": "data/repositories/osrf/gazebo/pullrequests/2229.json"}, "html": {"href": "#!/osrf/gazebo/pull-requests/2229"}}, "title": "Model Editor: Undo insert / delete nested models"}}, {"approval": {"date": "2016-04-14T19:46:09.104393+00:00", "pullrequest": {"type": "pullrequest", "id": 2229, "links": {"self": {"href": "data/repositories/osrf/gazebo/pullrequests/2229.json"}, "html": {"href": "#!/osrf/gazebo/pull-requests/2229"}}, "title": "Model Editor: Undo insert / delete nested models"}, "user": {"display_name": "Ian Chen", "uuid": "{eaa6fca5-6deb-43f6-907f-971c144735dd}", "links": {"self": {"href": "https://api.bitbucket.org/2.0/users/%7Beaa6fca5-6deb-43f6-907f-971c144735dd%7D"}, "html": {"href": "https://bitbucket.org/%7Beaa6fca5-6deb-43f6-907f-971c144735dd%7D/"}, "avatar": {"href": "https://avatar-management--avatars.us-west-2.prod.public.atl-paas.net/557058:10b01d41-a2e9-4a41-a907-e6e2f03b6cd5/1e4adcdf-1946-4280-9aea-eb5f15a7f912/128"}}, "nickname": "Ian Chen", "type": "user", "account_id": "557058:10b01d41-a2e9-4a41-a907-e6e2f03b6cd5"}}, "pull_request": {"type": "pullrequest", "id": 2229, "links": {"self": {"href": "data/repositories/osrf/gazebo/pullrequests/2229.json"}, "html": {"href": "#!/osrf/gazebo/pull-requests/2229"}}, "title": "Model Editor: Undo insert / delete nested models"}}, {"comment": {"links": {"self": {"href": "data/repositories/osrf/gazebo/pullrequests/2229/comments/17263552.json"}, "html": {"href": "#!/osrf/gazebo/pull-requests/2229/_/diff#comment-17263552"}}, "parent": {"id": 17255992, "links": {"self": {"href": "data/repositories/osrf/gazebo/pullrequests/2229/comments/17255992.json"}, "html": {"href": "#!/osrf/gazebo/pull-requests/2229/_/diff#comment-17255992"}}}, "deleted": false, "pullrequest": {"type": "pullrequest", "id": 2229, "links": {"self": {"href": "data/repositories/osrf/gazebo/pullrequests/2229.json"}, "html": {"href": "#!/osrf/gazebo/pull-requests/2229"}}, "title": "Model Editor: Undo insert / delete nested models"}, "content": {"raw": "Done b61a785", "markup": "markdown", "html": "<p>Done <a href=\"#!/osrf/gazebo/commits/b61a785\" rel=\"nofollow\" class=\"ap-connect-link\">b61a785</a></p>", "type": "rendered"}, "created_on": "2016-04-14T19:35:41.886375+00:00", "user": {"display_name": "Louise Poubel", "uuid": "{5cfa2075-477b-4ded-bdb9-8d2479544ec4}", "links": {"self": {"href": "https://api.bitbucket.org/2.0/users/%7B5cfa2075-477b-4ded-bdb9-8d2479544ec4%7D"}, "html": {"href": "https://bitbucket.org/%7B5cfa2075-477b-4ded-bdb9-8d2479544ec4%7D/"}, "avatar": {"href": "https://avatar-management--avatars.us-west-2.prod.public.atl-paas.net/557058:6ff86fcb-b7ab-44a5-b8a6-f6d9cae8b6e8/7d903d90-c5ea-4182-b7ef-0d467e9e1c74/128"}}, "nickname": "chapulina", "type": "user", "account_id": "557058:6ff86fcb-b7ab-44a5-b8a6-f6d9cae8b6e8"}, "inline": {}, "updated_on": "2016-04-14T19:35:41.888872+00:00", "type": "pullrequest_comment", "id": 17263552}, "pull_request": {"type": "pullrequest", "id": 2229, "links": {"self": {"href": "data/repositories/osrf/gazebo/pullrequests/2229.json"}, "html": {"href": "#!/osrf/gazebo/pull-requests/2229"}}, "title": "Model Editor: Undo insert / delete nested models"}}, {"update": {"description": "Issue #402\r\n\r\nUndo / redo:\r\n\r\n* Inserting nested models from the palette\r\n\r\n* Copy/pasting nested models\r\n\r\n* Deleting nested models with the DEL key\r\n\r\n* Deleting nested models via context menu\r\n\r\nObs:\r\n\r\nModel added to `testdb` should be the same as that added in pull request #2207, targeted at gazebo7. Once that is merged forward to default, they will coincide.", "title": "Model Editor: Undo insert / delete nested models", "destination": {"commit": {"hash": "a1b49e117729", "type": "commit", "links": {"self": {"href": "data/repositories/osrf/gazebo/commit/a1b49e117729.json"}, "html": {"href": "#!/osrf/gazebo/commits/a1b49e117729"}}}, "repository": {"links": {"self": {"href": "data/repositories/osrf/gazebo.json"}, "html": {"href": "#!/osrf/gazebo"}, "avatar": {"href": "data/bytebucket.org/ravatar/{51a0cd5d-8697-4eb1-8b08-e919ee881e1c}ts=1694483"}}, "type": "repository", "name": "gazebo", "full_name": "osrf/gazebo", "uuid": "{51a0cd5d-8697-4eb1-8b08-e919ee881e1c}"}, "branch": {"name": "default"}}, "reason": "", "source": {"commit": {"hash": "b61a78535f8e", "type": "commit", "links": {"self": {"href": "data/repositories/osrf/gazebo/commit/b61a78535f8e.json"}, "html": {"href": "#!/osrf/gazebo/commits/b61a78535f8e"}}}, "repository": {"links": {"self": {"href": "data/repositories/osrf/gazebo.json"}, "html": {"href": "#!/osrf/gazebo"}, "avatar": {"href": "data/bytebucket.org/ravatar/{51a0cd5d-8697-4eb1-8b08-e919ee881e1c}ts=1694483"}}, "type": "repository", "name": "gazebo", "full_name": "osrf/gazebo", "uuid": "{51a0cd5d-8697-4eb1-8b08-e919ee881e1c}"}, "branch": {"name": "undo_ME_nestedModel_insertion_deletion"}}, "state": "OPEN", "author": {"display_name": "Louise Poubel", "uuid": "{5cfa2075-477b-4ded-bdb9-8d2479544ec4}", "links": {"self": {"href": "https://api.bitbucket.org/2.0/users/%7B5cfa2075-477b-4ded-bdb9-8d2479544ec4%7D"}, "html": {"href": "https://bitbucket.org/%7B5cfa2075-477b-4ded-bdb9-8d2479544ec4%7D/"}, "avatar": {"href": "https://avatar-management--avatars.us-west-2.prod.public.atl-paas.net/557058:6ff86fcb-b7ab-44a5-b8a6-f6d9cae8b6e8/7d903d90-c5ea-4182-b7ef-0d467e9e1c74/128"}}, "nickname": "chapulina", "type": "user", "account_id": "557058:6ff86fcb-b7ab-44a5-b8a6-f6d9cae8b6e8"}, "date": "2016-04-14T18:02:04.881847+00:00"}, "pull_request": {"type": "pullrequest", "id": 2229, "links": {"self": {"href": "data/repositories/osrf/gazebo/pullrequests/2229.json"}, "html": {"href": "#!/osrf/gazebo/pull-requests/2229"}}, "title": "Model Editor: Undo insert / delete nested models"}}, {"comment": {"links": {"self": {"href": "data/repositories/osrf/gazebo/pullrequests/2229/comments/17255992.json"}, "html": {"href": "#!/osrf/gazebo/pull-requests/2229/_/diff#comment-17255992"}}, "parent": {"id": 17246843, "links": {"self": {"href": "data/repositories/osrf/gazebo/pullrequests/2229/comments/17246843.json"}, "html": {"href": "#!/osrf/gazebo/pull-requests/2229/_/diff#comment-17246843"}}}, "deleted": false, "pullrequest": {"type": "pullrequest", "id": 2229, "links": {"self": {"href": "data/repositories/osrf/gazebo/pullrequests/2229.json"}, "html": {"href": "#!/osrf/gazebo/pull-requests/2229"}}, "title": "Model Editor: Undo insert / delete nested models"}, "content": {"raw": "Good point, I'll try that.", "markup": "markdown", "html": "<p>Good point, I'll try that.</p>", "type": "rendered"}, "created_on": "2016-04-14T17:02:50.786095+00:00", "user": {"display_name": "Louise Poubel", "uuid": "{5cfa2075-477b-4ded-bdb9-8d2479544ec4}", "links": {"self": {"href": "https://api.bitbucket.org/2.0/users/%7B5cfa2075-477b-4ded-bdb9-8d2479544ec4%7D"}, "html": {"href": "https://bitbucket.org/%7B5cfa2075-477b-4ded-bdb9-8d2479544ec4%7D/"}, "avatar": {"href": "https://avatar-management--avatars.us-west-2.prod.public.atl-paas.net/557058:6ff86fcb-b7ab-44a5-b8a6-f6d9cae8b6e8/7d903d90-c5ea-4182-b7ef-0d467e9e1c74/128"}}, "nickname": "chapulina", "type": "user", "account_id": "557058:6ff86fcb-b7ab-44a5-b8a6-f6d9cae8b6e8"}, "inline": {}, "updated_on": "2016-04-14T17:02:50.789325+00:00", "type": "pullrequest_comment", "id": 17255992}, "pull_request": {"type": "pullrequest", "id": 2229, "links": {"self": {"href": "data/repositories/osrf/gazebo/pullrequests/2229.json"}, "html": {"href": "#!/osrf/gazebo/pull-requests/2229"}}, "title": "Model Editor: Undo insert / delete nested models"}}, {"comment": {"links": {"self": {"href": "data/repositories/osrf/gazebo/pullrequests/2229/comments/17246843.json"}, "html": {"href": "#!/osrf/gazebo/pull-requests/2229/_/diff#comment-17246843"}}, "deleted": false, "pullrequest": {"type": "pullrequest", "id": 2229, "links": {"self": {"href": "data/repositories/osrf/gazebo/pullrequests/2229.json"}, "html": {"href": "#!/osrf/gazebo/pull-requests/2229"}}, "title": "Model Editor: Undo insert / delete nested models"}, "content": {"raw": "oh I just noticed that running this test overwrites my `gui.ini` settings because of this line I think. Does the test need to update `gui.ini` or can it be done by only calling `gazebo::common::SystemPaths::Instance()->AddModelPathsUpdate`?\n", "markup": "markdown", "html": "<p>oh I just noticed that running this test overwrites my <code>gui.ini</code> settings because of this line I think. Does the test need to update <code>gui.ini</code> or can it be done by only calling <code>gazebo::common::SystemPaths::Instance()-&gt;AddModelPathsUpdate</code>?</p>", "type": "rendered"}, "created_on": "2016-04-14T14:38:41.928888+00:00", "user": {"display_name": "Ian Chen", "uuid": "{eaa6fca5-6deb-43f6-907f-971c144735dd}", "links": {"self": {"href": "https://api.bitbucket.org/2.0/users/%7Beaa6fca5-6deb-43f6-907f-971c144735dd%7D"}, "html": {"href": "https://bitbucket.org/%7Beaa6fca5-6deb-43f6-907f-971c144735dd%7D/"}, "avatar": {"href": "https://avatar-management--avatars.us-west-2.prod.public.atl-paas.net/557058:10b01d41-a2e9-4a41-a907-e6e2f03b6cd5/1e4adcdf-1946-4280-9aea-eb5f15a7f912/128"}}, "nickname": "Ian Chen", "type": "user", "account_id": "557058:10b01d41-a2e9-4a41-a907-e6e2f03b6cd5"}, "inline": {}, "updated_on": "2016-04-14T14:38:41.932456+00:00", "type": "pullrequest_comment", "id": 17246843}, "pull_request": {"type": "pullrequest", "id": 2229, "links": {"self": {"href": "data/repositories/osrf/gazebo/pullrequests/2229.json"}, "html": {"href": "#!/osrf/gazebo/pull-requests/2229"}}, "title": "Model Editor: Undo insert / delete nested models"}}, {"update": {"description": "Issue #402\r\n\r\nUndo / redo:\r\n\r\n* Inserting nested models from the palette\r\n\r\n* Copy/pasting nested models\r\n\r\n* Deleting nested models with the DEL key\r\n\r\n* Deleting nested models via context menu\r\n\r\nObs:\r\n\r\nModel added to `testdb` should be the same as that added in pull request #2207, targeted at gazebo7. Once that is merged forward to default, they will coincide.", "title": "Model Editor: Undo insert / delete nested models", "destination": {"commit": {"hash": "a1b49e117729", "type": "commit", "links": {"self": {"href": "data/repositories/osrf/gazebo/commit/a1b49e117729.json"}, "html": {"href": "#!/osrf/gazebo/commits/a1b49e117729"}}}, "repository": {"links": {"self": {"href": "data/repositories/osrf/gazebo.json"}, "html": {"href": "#!/osrf/gazebo"}, "avatar": {"href": "data/bytebucket.org/ravatar/{51a0cd5d-8697-4eb1-8b08-e919ee881e1c}ts=1694483"}}, "type": "repository", "name": "gazebo", "full_name": "osrf/gazebo", "uuid": "{51a0cd5d-8697-4eb1-8b08-e919ee881e1c}"}, "branch": {"name": "default"}}, "reason": "", "source": {"commit": {"hash": "3f8ee51a7c04", "type": "commit", "links": {"self": {"href": "data/repositories/osrf/gazebo/commit/3f8ee51a7c04.json"}, "html": {"href": "#!/osrf/gazebo/commits/3f8ee51a7c04"}}}, "repository": {"links": {"self": {"href": "data/repositories/osrf/gazebo.json"}, "html": {"href": "#!/osrf/gazebo"}, "avatar": {"href": "data/bytebucket.org/ravatar/{51a0cd5d-8697-4eb1-8b08-e919ee881e1c}ts=1694483"}}, "type": "repository", "name": "gazebo", "full_name": "osrf/gazebo", "uuid": "{51a0cd5d-8697-4eb1-8b08-e919ee881e1c}"}, "branch": {"name": "undo_ME_nestedModel_insertion_deletion"}}, "state": "OPEN", "author": {"display_name": "Ian Chen", "uuid": "{eaa6fca5-6deb-43f6-907f-971c144735dd}", "links": {"self": {"href": "https://api.bitbucket.org/2.0/users/%7Beaa6fca5-6deb-43f6-907f-971c144735dd%7D"}, "html": {"href": "https://bitbucket.org/%7Beaa6fca5-6deb-43f6-907f-971c144735dd%7D/"}, "avatar": {"href": "https://avatar-management--avatars.us-west-2.prod.public.atl-paas.net/557058:10b01d41-a2e9-4a41-a907-e6e2f03b6cd5/1e4adcdf-1946-4280-9aea-eb5f15a7f912/128"}}, "nickname": "Ian Chen", "type": "user", "account_id": "557058:10b01d41-a2e9-4a41-a907-e6e2f03b6cd5"}, "date": "2016-04-14T14:29:25.015095+00:00"}, "pull_request": {"type": "pullrequest", "id": 2229, "links": {"self": {"href": "data/repositories/osrf/gazebo/pullrequests/2229.json"}, "html": {"href": "#!/osrf/gazebo/pull-requests/2229"}}, "title": "Model Editor: Undo insert / delete nested models"}}, {"update": {"description": "Issue #402\r\n\r\nUndo / redo:\r\n\r\n* Inserting nested models from the palette\r\n\r\n* Copy/pasting nested models\r\n\r\n* Deleting nested models with the DEL key\r\n\r\n* Deleting nested models via context menu\r\n\r\nObs:\r\n\r\nModel added to `testdb` should be the same as that added in pull request #2207, targeted at gazebo7. Once that is merged forward to default, they will coincide.", "title": "Model Editor: Undo insert / delete nested models", "destination": {"commit": {"hash": "f7642917b79e", "type": "commit", "links": {"self": {"href": "data/repositories/osrf/gazebo/commit/f7642917b79e.json"}, "html": {"href": "#!/osrf/gazebo/commits/f7642917b79e"}}}, "repository": {"links": {"self": {"href": "data/repositories/osrf/gazebo.json"}, "html": {"href": "#!/osrf/gazebo"}, "avatar": {"href": "data/bytebucket.org/ravatar/{51a0cd5d-8697-4eb1-8b08-e919ee881e1c}ts=1694483"}}, "type": "repository", "name": "gazebo", "full_name": "osrf/gazebo", "uuid": "{51a0cd5d-8697-4eb1-8b08-e919ee881e1c}"}, "branch": {"name": "default"}}, "reason": "", "source": {"commit": {"hash": "e6d2f7943d96", "type": "commit", "links": {"self": {"href": "data/repositories/osrf/gazebo/commit/e6d2f7943d96.json"}, "html": {"href": "#!/osrf/gazebo/commits/e6d2f7943d96"}}}, "repository": {"links": {"self": {"href": "data/repositories/osrf/gazebo.json"}, "html": {"href": "#!/osrf/gazebo"}, "avatar": {"href": "data/bytebucket.org/ravatar/{51a0cd5d-8697-4eb1-8b08-e919ee881e1c}ts=1694483"}}, "type": "repository", "name": "gazebo", "full_name": "osrf/gazebo", "uuid": "{51a0cd5d-8697-4eb1-8b08-e919ee881e1c}"}, "branch": {"name": "undo_ME_nestedModel_insertion_deletion"}}, "state": "OPEN", "author": {"display_name": "Louise Poubel", "uuid": "{5cfa2075-477b-4ded-bdb9-8d2479544ec4}", "links": {"self": {"href": "https://api.bitbucket.org/2.0/users/%7B5cfa2075-477b-4ded-bdb9-8d2479544ec4%7D"}, "html": {"href": "https://bitbucket.org/%7B5cfa2075-477b-4ded-bdb9-8d2479544ec4%7D/"}, "avatar": {"href": "https://avatar-management--avatars.us-west-2.prod.public.atl-paas.net/557058:6ff86fcb-b7ab-44a5-b8a6-f6d9cae8b6e8/7d903d90-c5ea-4182-b7ef-0d467e9e1c74/128"}}, "nickname": "chapulina", "type": "user", "account_id": "557058:6ff86fcb-b7ab-44a5-b8a6-f6d9cae8b6e8"}, "date": "2016-04-11T17:52:14.064222+00:00"}, "pull_request": {"type": "pullrequest", "id": 2229, "links": {"self": {"href": "data/repositories/osrf/gazebo/pullrequests/2229.json"}, "html": {"href": "#!/osrf/gazebo/pull-requests/2229"}}, "title": "Model Editor: Undo insert / delete nested models"}}, {"update": {"description": "Issue #402\r\n\r\nUndo / redo:\r\n\r\n* Inserting nested models from the palette\r\n\r\n* Copy/pasting nested models\r\n\r\n* Deleting nested models with the DEL key\r\n\r\n* Deleting nested models via context menu\r\n\r\nObs:\r\n\r\nModel added to `testdb` should be the same as that added in pull request #2207, targeted at gazebo7. Once that is merged forward to default, they will coincide.", "title": "Model Editor: Undo insert / delete nested models", "destination": {"commit": {"hash": "5efdcf9bf853", "type": "commit", "links": {"self": {"href": "data/repositories/osrf/gazebo/commit/5efdcf9bf853.json"}, "html": {"href": "#!/osrf/gazebo/commits/5efdcf9bf853"}}}, "repository": {"links": {"self": {"href": "data/repositories/osrf/gazebo.json"}, "html": {"href": "#!/osrf/gazebo"}, "avatar": {"href": "data/bytebucket.org/ravatar/{51a0cd5d-8697-4eb1-8b08-e919ee881e1c}ts=1694483"}}, "type": "repository", "name": "gazebo", "full_name": "osrf/gazebo", "uuid": "{51a0cd5d-8697-4eb1-8b08-e919ee881e1c}"}, "branch": {"name": "default"}}, "reason": "", "source": {"commit": {"hash": "932433c1476d", "type": "commit", "links": {"self": {"href": "data/repositories/osrf/gazebo/commit/932433c1476d.json"}, "html": {"href": "#!/osrf/gazebo/commits/932433c1476d"}}}, "repository": {"links": {"self": {"href": "data/repositories/osrf/gazebo.json"}, "html": {"href": "#!/osrf/gazebo"}, "avatar": {"href": "data/bytebucket.org/ravatar/{51a0cd5d-8697-4eb1-8b08-e919ee881e1c}ts=1694483"}}, "type": "repository", "name": "gazebo", "full_name": "osrf/gazebo", "uuid": "{51a0cd5d-8697-4eb1-8b08-e919ee881e1c}"}, "branch": {"name": "undo_ME_nestedModel_insertion_deletion"}}, "state": "OPEN", "author": {"display_name": "Louise Poubel", "uuid": "{5cfa2075-477b-4ded-bdb9-8d2479544ec4}", "links": {"self": {"href": "https://api.bitbucket.org/2.0/users/%7B5cfa2075-477b-4ded-bdb9-8d2479544ec4%7D"}, "html": {"href": "https://bitbucket.org/%7B5cfa2075-477b-4ded-bdb9-8d2479544ec4%7D/"}, "avatar": {"href": "https://avatar-management--avatars.us-west-2.prod.public.atl-paas.net/557058:6ff86fcb-b7ab-44a5-b8a6-f6d9cae8b6e8/7d903d90-c5ea-4182-b7ef-0d467e9e1c74/128"}}, "nickname": "chapulina", "type": "user", "account_id": "557058:6ff86fcb-b7ab-44a5-b8a6-f6d9cae8b6e8"}, "date": "2016-04-08T16:31:12.560170+00:00"}, "pull_request": {"type": "pullrequest", "id": 2229, "links": {"self": {"href": "data/repositories/osrf/gazebo/pullrequests/2229.json"}, "html": {"href": "#!/osrf/gazebo/pull-requests/2229"}}, "title": "Model Editor: Undo insert / delete nested models"}}, {"update": {"description": "Issue #402\r\n\r\nUndo / redo:\r\n\r\n* Inserting nested models from the palette\r\n\r\n* Copy/pasting nested models\r\n\r\n* Deleting nested models with the DEL key\r\n\r\n* Deleting nested models via context menu\r\n\r\nObs:\r\n\r\nModel added to `testdb` should be the same as that added in pull request #2207, targeted at gazebo7. Once that is merged forward to default, they will coincide.", "title": "Model Editor: Undo insert / delete nested models", "destination": {"commit": {"hash": "5efdcf9bf853", "type": "commit", "links": {"self": {"href": "data/repositories/osrf/gazebo/commit/5efdcf9bf853.json"}, "html": {"href": "#!/osrf/gazebo/commits/5efdcf9bf853"}}}, "repository": {"links": {"self": {"href": "data/repositories/osrf/gazebo.json"}, "html": {"href": "#!/osrf/gazebo"}, "avatar": {"href": "data/bytebucket.org/ravatar/{51a0cd5d-8697-4eb1-8b08-e919ee881e1c}ts=1694483"}}, "type": "repository", "name": "gazebo", "full_name": "osrf/gazebo", "uuid": "{51a0cd5d-8697-4eb1-8b08-e919ee881e1c}"}, "branch": {"name": "default"}}, "reason": "", "source": {"commit": {"hash": "932433c1476d", "type": "commit", "links": {"self": {"href": "data/repositories/osrf/gazebo/commit/932433c1476d.json"}, "html": {"href": "#!/osrf/gazebo/commits/932433c1476d"}}}, "repository": {"links": {"self": {"href": "data/repositories/osrf/gazebo.json"}, "html": {"href": "#!/osrf/gazebo"}, "avatar": {"href": "data/bytebucket.org/ravatar/{51a0cd5d-8697-4eb1-8b08-e919ee881e1c}ts=1694483"}}, "type": "repository", "name": "gazebo", "full_name": "osrf/gazebo", "uuid": "{51a0cd5d-8697-4eb1-8b08-e919ee881e1c}"}, "branch": {"name": "undo_ME_nestedModel_insertion_deletion"}}, "state": "OPEN", "author": {"display_name": "Louise Poubel", "uuid": "{5cfa2075-477b-4ded-bdb9-8d2479544ec4}", "links": {"self": {"href": "https://api.bitbucket.org/2.0/users/%7B5cfa2075-477b-4ded-bdb9-8d2479544ec4%7D"}, "html": {"href": "https://bitbucket.org/%7B5cfa2075-477b-4ded-bdb9-8d2479544ec4%7D/"}, "avatar": {"href": "https://avatar-management--avatars.us-west-2.prod.public.atl-paas.net/557058:6ff86fcb-b7ab-44a5-b8a6-f6d9cae8b6e8/7d903d90-c5ea-4182-b7ef-0d467e9e1c74/128"}}, "nickname": "chapulina", "type": "user", "account_id": "557058:6ff86fcb-b7ab-44a5-b8a6-f6d9cae8b6e8"}, "date": "2016-04-08T16:31:10.031290+00:00"}, "pull_request": {"type": "pullrequest", "id": 2229, "links": {"self": {"href": "data/repositories/osrf/gazebo/pullrequests/2229.json"}, "html": {"href": "#!/osrf/gazebo/pull-requests/2229"}}, "title": "Model Editor: Undo insert / delete nested models"}}, {"approval": {"date": "2016-04-06T22:07:49.694077+00:00", "pullrequest": {"type": "pullrequest", "id": 2229, "links": {"self": {"href": "data/repositories/osrf/gazebo/pullrequests/2229.json"}, "html": {"href": "#!/osrf/gazebo/pull-requests/2229"}}, "title": "Model Editor: Undo insert / delete nested models"}, "user": {"display_name": "Nate Koenig", "uuid": "{c862cdd9-fcc8-4419-9fc7-e20db14b8fcb}", "links": {"self": {"href": "https://api.bitbucket.org/2.0/users/%7Bc862cdd9-fcc8-4419-9fc7-e20db14b8fcb%7D"}, "html": {"href": "https://bitbucket.org/%7Bc862cdd9-fcc8-4419-9fc7-e20db14b8fcb%7D/"}, "avatar": {"href": "https://avatar-management--avatars.us-west-2.prod.public.atl-paas.net/557058:095b1e12-74ed-4e20-b44f-2f0745b616e0/ca24bb11-4787-4b14-a20d-d91835e9bde2/128"}}, "nickname": "Nathan Koenig", "type": "user", "account_id": "557058:095b1e12-74ed-4e20-b44f-2f0745b616e0"}}, "pull_request": {"type": "pullrequest", "id": 2229, "links": {"self": {"href": "data/repositories/osrf/gazebo/pullrequests/2229.json"}, "html": {"href": "#!/osrf/gazebo/pull-requests/2229"}}, "title": "Model Editor: Undo insert / delete nested models"}}, {"update": {"description": "Issue #402\r\n\r\nUndo / redo:\r\n\r\n* Inserting nested models from the palette\r\n\r\n* Copy/pasting nested models\r\n\r\n* Deleting nested models with the DEL key\r\n\r\n* Deleting nested models via context menu\r\n\r\nObs:\r\n\r\nModel added to `testdb` should be the same as that added in pull request #2207, targeted at gazebo7. Once that is merged forward to default, they will coincide.", "title": "Model Editor: Undo insert / delete nested models", "destination": {"commit": {"hash": "07fcf3c9672c", "type": "commit", "links": {"self": {"href": "data/repositories/osrf/gazebo/commit/07fcf3c9672c.json"}, "html": {"href": "#!/osrf/gazebo/commits/07fcf3c9672c"}}}, "repository": {"links": {"self": {"href": "data/repositories/osrf/gazebo.json"}, "html": {"href": "#!/osrf/gazebo"}, "avatar": {"href": "data/bytebucket.org/ravatar/{51a0cd5d-8697-4eb1-8b08-e919ee881e1c}ts=1694483"}}, "type": "repository", "name": "gazebo", "full_name": "osrf/gazebo", "uuid": "{51a0cd5d-8697-4eb1-8b08-e919ee881e1c}"}, "branch": {"name": "default"}}, "reason": "", "source": {"commit": {"hash": "a4319f91ba86", "type": "commit", "links": {"self": {"href": "data/repositories/osrf/gazebo/commit/a4319f91ba86.json"}, "html": {"href": "#!/osrf/gazebo/commits/a4319f91ba86"}}}, "repository": {"links": {"self": {"href": "data/repositories/osrf/gazebo.json"}, "html": {"href": "#!/osrf/gazebo"}, "avatar": {"href": "data/bytebucket.org/ravatar/{51a0cd5d-8697-4eb1-8b08-e919ee881e1c}ts=1694483"}}, "type": "repository", "name": "gazebo", "full_name": "osrf/gazebo", "uuid": "{51a0cd5d-8697-4eb1-8b08-e919ee881e1c}"}, "branch": {"name": "undo_ME_nestedModel_insertion_deletion"}}, "state": "OPEN", "author": {"display_name": "Nate Koenig", "uuid": "{c862cdd9-fcc8-4419-9fc7-e20db14b8fcb}", "links": {"self": {"href": "https://api.bitbucket.org/2.0/users/%7Bc862cdd9-fcc8-4419-9fc7-e20db14b8fcb%7D"}, "html": {"href": "https://bitbucket.org/%7Bc862cdd9-fcc8-4419-9fc7-e20db14b8fcb%7D/"}, "avatar": {"href": "https://avatar-management--avatars.us-west-2.prod.public.atl-paas.net/557058:095b1e12-74ed-4e20-b44f-2f0745b616e0/ca24bb11-4787-4b14-a20d-d91835e9bde2/128"}}, "nickname": "Nathan Koenig", "type": "user", "account_id": "557058:095b1e12-74ed-4e20-b44f-2f0745b616e0"}, "date": "2016-04-06T19:03:36.643438+00:00"}, "pull_request": {"type": "pullrequest", "id": 2229, "links": {"self": {"href": "data/repositories/osrf/gazebo/pullrequests/2229.json"}, "html": {"href": "#!/osrf/gazebo/pull-requests/2229"}}, "title": "Model Editor: Undo insert / delete nested models"}}, {"update": {"description": "Issue #402\r\n\r\nUndo / redo:\r\n\r\n* Inserting nested models from the palette\r\n\r\n* Copy/pasting nested models\r\n\r\n* Deleting nested models with the DEL key\r\n\r\n* Deleting nested models via context menu\r\n\r\nObs:\r\n\r\nModel added to `testdb` should be the same as that added in pull request #2207, targeted at gazebo7. Once that is merged forward to default, they will coincide.", "title": "Model Editor: Undo insert / delete nested models", "destination": {"commit": {"hash": "07fcf3c9672c", "type": "commit", "links": {"self": {"href": "data/repositories/osrf/gazebo/commit/07fcf3c9672c.json"}, "html": {"href": "#!/osrf/gazebo/commits/07fcf3c9672c"}}}, "repository": {"links": {"self": {"href": "data/repositories/osrf/gazebo.json"}, "html": {"href": "#!/osrf/gazebo"}, "avatar": {"href": "data/bytebucket.org/ravatar/{51a0cd5d-8697-4eb1-8b08-e919ee881e1c}ts=1694483"}}, "type": "repository", "name": "gazebo", "full_name": "osrf/gazebo", "uuid": "{51a0cd5d-8697-4eb1-8b08-e919ee881e1c}"}, "branch": {"name": "default"}}, "reason": "", "source": {"commit": {"hash": "61fecb401bf5", "type": "commit", "links": {"self": {"href": "data/repositories/osrf/gazebo/commit/61fecb401bf5.json"}, "html": {"href": "#!/osrf/gazebo/commits/61fecb401bf5"}}}, "repository": {"links": {"self": {"href": "data/repositories/osrf/gazebo.json"}, "html": {"href": "#!/osrf/gazebo"}, "avatar": {"href": "data/bytebucket.org/ravatar/{51a0cd5d-8697-4eb1-8b08-e919ee881e1c}ts=1694483"}}, "type": "repository", "name": "gazebo", "full_name": "osrf/gazebo", "uuid": "{51a0cd5d-8697-4eb1-8b08-e919ee881e1c}"}, "branch": {"name": "undo_ME_nestedModel_insertion_deletion"}}, "state": "OPEN", "author": {"display_name": "Nate Koenig", "uuid": "{c862cdd9-fcc8-4419-9fc7-e20db14b8fcb}", "links": {"self": {"href": "https://api.bitbucket.org/2.0/users/%7Bc862cdd9-fcc8-4419-9fc7-e20db14b8fcb%7D"}, "html": {"href": "https://bitbucket.org/%7Bc862cdd9-fcc8-4419-9fc7-e20db14b8fcb%7D/"}, "avatar": {"href": "https://avatar-management--avatars.us-west-2.prod.public.atl-paas.net/557058:095b1e12-74ed-4e20-b44f-2f0745b616e0/ca24bb11-4787-4b14-a20d-d91835e9bde2/128"}}, "nickname": "Nathan Koenig", "type": "user", "account_id": "557058:095b1e12-74ed-4e20-b44f-2f0745b616e0"}, "date": "2016-04-06T18:51:54.349027+00:00"}, "pull_request": {"type": "pullrequest", "id": 2229, "links": {"self": {"href": "data/repositories/osrf/gazebo/pullrequests/2229.json"}, "html": {"href": "#!/osrf/gazebo/pull-requests/2229"}}, "title": "Model Editor: Undo insert / delete nested models"}}, {"update": {"description": "Issue #402\r\n\r\nUndo / redo:\r\n\r\n* Inserting nested models from the palette\r\n\r\n* Copy/pasting nested models\r\n\r\n* Deleting nested models with the DEL key\r\n\r\n* Deleting nested models via context menu\r\n\r\nObs:\r\n\r\nModel added to `testdb` should be the same as that added in pull request #2207, targeted at gazebo7. Once that is merged forward to default, they will coincide.", "title": "Model Editor: Undo insert / delete nested models", "destination": {"commit": {"hash": "07fcf3c9672c", "type": "commit", "links": {"self": {"href": "data/repositories/osrf/gazebo/commit/07fcf3c9672c.json"}, "html": {"href": "#!/osrf/gazebo/commits/07fcf3c9672c"}}}, "repository": {"links": {"self": {"href": "data/repositories/osrf/gazebo.json"}, "html": {"href": "#!/osrf/gazebo"}, "avatar": {"href": "data/bytebucket.org/ravatar/{51a0cd5d-8697-4eb1-8b08-e919ee881e1c}ts=1694483"}}, "type": "repository", "name": "gazebo", "full_name": "osrf/gazebo", "uuid": "{51a0cd5d-8697-4eb1-8b08-e919ee881e1c}"}, "branch": {"name": "default"}}, "reason": "", "source": {"commit": {"hash": "482017bfd352", "type": "commit", "links": {"self": {"href": "data/repositories/osrf/gazebo/commit/482017bfd352.json"}, "html": {"href": "#!/osrf/gazebo/commits/482017bfd352"}}}, "repository": {"links": {"self": {"href": "data/repositories/osrf/gazebo.json"}, "html": {"href": "#!/osrf/gazebo"}, "avatar": {"href": "data/bytebucket.org/ravatar/{51a0cd5d-8697-4eb1-8b08-e919ee881e1c}ts=1694483"}}, "type": "repository", "name": "gazebo", "full_name": "osrf/gazebo", "uuid": "{51a0cd5d-8697-4eb1-8b08-e919ee881e1c}"}, "branch": {"name": "undo_ME_nestedModel_insertion_deletion"}}, "state": "OPEN", "author": {"display_name": "Louise Poubel", "uuid": "{5cfa2075-477b-4ded-bdb9-8d2479544ec4}", "links": {"self": {"href": "https://api.bitbucket.org/2.0/users/%7B5cfa2075-477b-4ded-bdb9-8d2479544ec4%7D"}, "html": {"href": "https://bitbucket.org/%7B5cfa2075-477b-4ded-bdb9-8d2479544ec4%7D/"}, "avatar": {"href": "https://avatar-management--avatars.us-west-2.prod.public.atl-paas.net/557058:6ff86fcb-b7ab-44a5-b8a6-f6d9cae8b6e8/7d903d90-c5ea-4182-b7ef-0d467e9e1c74/128"}}, "nickname": "chapulina", "type": "user", "account_id": "557058:6ff86fcb-b7ab-44a5-b8a6-f6d9cae8b6e8"}, "date": "2016-04-05T21:39:59.129241+00:00"}, "pull_request": {"type": "pullrequest", "id": 2229, "links": {"self": {"href": "data/repositories/osrf/gazebo/pullrequests/2229.json"}, "html": {"href": "#!/osrf/gazebo/pull-requests/2229"}}, "title": "Model Editor: Undo insert / delete nested models"}}, {"update": {"description": "Issue #402\r\n\r\nUndo / redo:\r\n\r\n* Inserting nested models from the palette\r\n\r\n* Copy/pasting nested models\r\n\r\n* Deleting nested models with the DEL key\r\n\r\n* Deleting nested models via context menu\r\n\r\nObs:\r\n\r\nModel added to `testdb` should be the same as that added in pull request #2207, targeted at gazebo7. Once that is merged forward to default, they will coincide.", "title": "Model Editor: Undo insert / delete nested models", "destination": {"commit": {"hash": "07fcf3c9672c", "type": "commit", "links": {"self": {"href": "data/repositories/osrf/gazebo/commit/07fcf3c9672c.json"}, "html": {"href": "#!/osrf/gazebo/commits/07fcf3c9672c"}}}, "repository": {"links": {"self": {"href": "data/repositories/osrf/gazebo.json"}, "html": {"href": "#!/osrf/gazebo"}, "avatar": {"href": "data/bytebucket.org/ravatar/{51a0cd5d-8697-4eb1-8b08-e919ee881e1c}ts=1694483"}}, "type": "repository", "name": "gazebo", "full_name": "osrf/gazebo", "uuid": "{51a0cd5d-8697-4eb1-8b08-e919ee881e1c}"}, "branch": {"name": "default"}}, "reason": "", "source": {"commit": {"hash": "482017bfd352", "type": "commit", "links": {"self": {"href": "data/repositories/osrf/gazebo/commit/482017bfd352.json"}, "html": {"href": "#!/osrf/gazebo/commits/482017bfd352"}}}, "repository": {"links": {"self": {"href": "data/repositories/osrf/gazebo.json"}, "html": {"href": "#!/osrf/gazebo"}, "avatar": {"href": "data/bytebucket.org/ravatar/{51a0cd5d-8697-4eb1-8b08-e919ee881e1c}ts=1694483"}}, "type": "repository", "name": "gazebo", "full_name": "osrf/gazebo", "uuid": "{51a0cd5d-8697-4eb1-8b08-e919ee881e1c}"}, "branch": {"name": "undo_ME_nestedModel_insertion_deletion"}}, "state": "OPEN", "author": {"display_name": "Louise Poubel", "uuid": "{5cfa2075-477b-4ded-bdb9-8d2479544ec4}", "links": {"self": {"href": "https://api.bitbucket.org/2.0/users/%7B5cfa2075-477b-4ded-bdb9-8d2479544ec4%7D"}, "html": {"href": "https://bitbucket.org/%7B5cfa2075-477b-4ded-bdb9-8d2479544ec4%7D/"}, "avatar": {"href": "https://avatar-management--avatars.us-west-2.prod.public.atl-paas.net/557058:6ff86fcb-b7ab-44a5-b8a6-f6d9cae8b6e8/7d903d90-c5ea-4182-b7ef-0d467e9e1c74/128"}}, "nickname": "chapulina", "type": "user", "account_id": "557058:6ff86fcb-b7ab-44a5-b8a6-f6d9cae8b6e8"}, "date": "2016-04-05T21:39:57.037847+00:00"}, "pull_request": {"type": "pullrequest", "id": 2229, "links": {"self": {"href": "data/repositories/osrf/gazebo/pullrequests/2229.json"}, "html": {"href": "#!/osrf/gazebo/pull-requests/2229"}}, "title": "Model Editor: Undo insert / delete nested models"}}, {"comment": {"links": {"self": {"href": "data/repositories/osrf/gazebo/pullrequests/2229/comments/16745536.json"}, "html": {"href": "#!/osrf/gazebo/pull-requests/2229/_/diff#comment-16745536"}}, "parent": {"id": 16741621, "links": {"self": {"href": "data/repositories/osrf/gazebo/pullrequests/2229/comments/16741621.json"}, "html": {"href": "#!/osrf/gazebo/pull-requests/2229/_/diff#comment-16741621"}}}, "deleted": false, "pullrequest": {"type": "pullrequest", "id": 2229, "links": {"self": {"href": "data/repositories/osrf/gazebo/pullrequests/2229.json"}, "html": {"href": "#!/osrf/gazebo/pull-requests/2229"}}, "title": "Model Editor: Undo insert / delete nested models"}, "content": {"raw": "looks ok", "markup": "markdown", "html": "<p>looks ok</p>", "type": "rendered"}, "created_on": "2016-04-04T22:12:44.907147+00:00", "user": {"display_name": "Louise Poubel", "uuid": "{5cfa2075-477b-4ded-bdb9-8d2479544ec4}", "links": {"self": {"href": "https://api.bitbucket.org/2.0/users/%7B5cfa2075-477b-4ded-bdb9-8d2479544ec4%7D"}, "html": {"href": "https://bitbucket.org/%7B5cfa2075-477b-4ded-bdb9-8d2479544ec4%7D/"}, "avatar": {"href": "https://avatar-management--avatars.us-west-2.prod.public.atl-paas.net/557058:6ff86fcb-b7ab-44a5-b8a6-f6d9cae8b6e8/7d903d90-c5ea-4182-b7ef-0d467e9e1c74/128"}}, "nickname": "chapulina", "type": "user", "account_id": "557058:6ff86fcb-b7ab-44a5-b8a6-f6d9cae8b6e8"}, "updated_on": "2016-04-04T22:12:44.910109+00:00", "type": "pullrequest_comment", "id": 16745536}, "pull_request": {"type": "pullrequest", "id": 2229, "links": {"self": {"href": "data/repositories/osrf/gazebo/pullrequests/2229.json"}, "html": {"href": "#!/osrf/gazebo/pull-requests/2229"}}, "title": "Model Editor: Undo insert / delete nested models"}}, {"comment": {"links": {"self": {"href": "data/repositories/osrf/gazebo/pullrequests/2229/comments/16741621.json"}, "html": {"href": "#!/osrf/gazebo/pull-requests/2229/_/diff#comment-16741621"}}, "parent": {"id": 16615913, "links": {"self": {"href": "data/repositories/osrf/gazebo/pullrequests/2229/comments/16615913.json"}, "html": {"href": "#!/osrf/gazebo/pull-requests/2229/_/diff#comment-16615913"}}}, "deleted": false, "pullrequest": {"type": "pullrequest", "id": 2229, "links": {"self": {"href": "data/repositories/osrf/gazebo/pullrequests/2229.json"}, "html": {"href": "#!/osrf/gazebo/pull-requests/2229"}}, "title": "Model Editor: Undo insert / delete nested models"}, "content": {"raw": "I used `unique_ptr`s instead of raw pointers for the editors in 37de4bc. Now it passes on [homebrew](http://build.osrfoundation.org/job/gazebo-ci-pr_any-homebrew-amd64/306/testReport/). \n\nQueued one last [trusty gpu](http://build.osrfoundation.org/view/main/view/CI%20any%20jobs/job/gazebo-ci-pr_any-trusty-amd64-gpu-nvidia/) to make sure that's still ok.", "markup": "markdown", "html": "<p>I used <code>unique_ptr</code>s instead of raw pointers for the editors in <a href=\"#!/osrf/gazebo/commits/37de4bc\" rel=\"nofollow\" class=\"ap-connect-link\">37de4bc</a>. Now it passes on <a data-is-external-link=\"true\" href=\"http://build.osrfoundation.org/job/gazebo-ci-pr_any-homebrew-amd64/306/testReport/\" rel=\"nofollow\">homebrew</a>. </p>\n<p>Queued one last <a data-is-external-link=\"true\" href=\"http://build.osrfoundation.org/view/main/view/CI%20any%20jobs/job/gazebo-ci-pr_any-trusty-amd64-gpu-nvidia/\" rel=\"nofollow\">trusty gpu</a> to make sure that's still ok.</p>", "type": "rendered"}, "created_on": "2016-04-04T20:13:41.491899+00:00", "user": {"display_name": "Louise Poubel", "uuid": "{5cfa2075-477b-4ded-bdb9-8d2479544ec4}", "links": {"self": {"href": "https://api.bitbucket.org/2.0/users/%7B5cfa2075-477b-4ded-bdb9-8d2479544ec4%7D"}, "html": {"href": "https://bitbucket.org/%7B5cfa2075-477b-4ded-bdb9-8d2479544ec4%7D/"}, "avatar": {"href": "https://avatar-management--avatars.us-west-2.prod.public.atl-paas.net/557058:6ff86fcb-b7ab-44a5-b8a6-f6d9cae8b6e8/7d903d90-c5ea-4182-b7ef-0d467e9e1c74/128"}}, "nickname": "chapulina", "type": "user", "account_id": "557058:6ff86fcb-b7ab-44a5-b8a6-f6d9cae8b6e8"}, "updated_on": "2016-04-04T20:13:41.495199+00:00", "type": "pullrequest_comment", "id": 16741621}, "pull_request": {"type": "pullrequest", "id": 2229, "links": {"self": {"href": "data/repositories/osrf/gazebo/pullrequests/2229.json"}, "html": {"href": "#!/osrf/gazebo/pull-requests/2229"}}, "title": "Model Editor: Undo insert / delete nested models"}}, {"update": {"description": "Issue #402\r\n\r\nUndo / redo:\r\n\r\n* Inserting nested models from the palette\r\n\r\n* Copy/pasting nested models\r\n\r\n* Deleting nested models with the DEL key\r\n\r\n* Deleting nested models via context menu\r\n\r\nObs:\r\n\r\nModel added to `testdb` should be the same as that added in pull request #2207, targeted at gazebo7. Once that is merged forward to default, they will coincide.", "title": "Model Editor: Undo insert / delete nested models", "destination": {"commit": {"hash": "0cc955fdbe12", "type": "commit", "links": {"self": {"href": "data/repositories/osrf/gazebo/commit/0cc955fdbe12.json"}, "html": {"href": "#!/osrf/gazebo/commits/0cc955fdbe12"}}}, "repository": {"links": {"self": {"href": "data/repositories/osrf/gazebo.json"}, "html": {"href": "#!/osrf/gazebo"}, "avatar": {"href": "data/bytebucket.org/ravatar/{51a0cd5d-8697-4eb1-8b08-e919ee881e1c}ts=1694483"}}, "type": "repository", "name": "gazebo", "full_name": "osrf/gazebo", "uuid": "{51a0cd5d-8697-4eb1-8b08-e919ee881e1c}"}, "branch": {"name": "default"}}, "reason": "", "source": {"commit": {"hash": "37de4bcc3f01", "type": "commit", "links": {"self": {"href": "data/repositories/osrf/gazebo/commit/37de4bcc3f01.json"}, "html": {"href": "#!/osrf/gazebo/commits/37de4bcc3f01"}}}, "repository": {"links": {"self": {"href": "data/repositories/osrf/gazebo.json"}, "html": {"href": "#!/osrf/gazebo"}, "avatar": {"href": "data/bytebucket.org/ravatar/{51a0cd5d-8697-4eb1-8b08-e919ee881e1c}ts=1694483"}}, "type": "repository", "name": "gazebo", "full_name": "osrf/gazebo", "uuid": "{51a0cd5d-8697-4eb1-8b08-e919ee881e1c}"}, "branch": {"name": "undo_ME_nestedModel_insertion_deletion"}}, "state": "OPEN", "author": {"display_name": "Louise Poubel", "uuid": "{5cfa2075-477b-4ded-bdb9-8d2479544ec4}", "links": {"self": {"href": "https://api.bitbucket.org/2.0/users/%7B5cfa2075-477b-4ded-bdb9-8d2479544ec4%7D"}, "html": {"href": "https://bitbucket.org/%7B5cfa2075-477b-4ded-bdb9-8d2479544ec4%7D/"}, "avatar": {"href": "https://avatar-management--avatars.us-west-2.prod.public.atl-paas.net/557058:6ff86fcb-b7ab-44a5-b8a6-f6d9cae8b6e8/7d903d90-c5ea-4182-b7ef-0d467e9e1c74/128"}}, "nickname": "chapulina", "type": "user", "account_id": "557058:6ff86fcb-b7ab-44a5-b8a6-f6d9cae8b6e8"}, "date": "2016-04-04T18:00:02.521922+00:00"}, "pull_request": {"type": "pullrequest", "id": 2229, "links": {"self": {"href": "data/repositories/osrf/gazebo/pullrequests/2229.json"}, "html": {"href": "#!/osrf/gazebo/pull-requests/2229"}}, "title": "Model Editor: Undo insert / delete nested models"}}, {"update": {"description": "Issue #402\r\n\r\nUndo / redo:\r\n\r\n* Inserting nested models from the palette\r\n\r\n* Copy/pasting nested models\r\n\r\n* Deleting nested models with the DEL key\r\n\r\n* Deleting nested models via context menu\r\n\r\nObs:\r\n\r\nModel added to `testdb` should be the same as that added in pull request #2207, targeted at gazebo7. Once that is merged forward to default, they will coincide.", "title": "Model Editor: Undo insert / delete nested models", "destination": {"commit": {"hash": "32276ac316a9", "type": "commit", "links": {"self": {"href": "data/repositories/osrf/gazebo/commit/32276ac316a9.json"}, "html": {"href": "#!/osrf/gazebo/commits/32276ac316a9"}}}, "repository": {"links": {"self": {"href": "data/repositories/osrf/gazebo.json"}, "html": {"href": "#!/osrf/gazebo"}, "avatar": {"href": "data/bytebucket.org/ravatar/{51a0cd5d-8697-4eb1-8b08-e919ee881e1c}ts=1694483"}}, "type": "repository", "name": "gazebo", "full_name": "osrf/gazebo", "uuid": "{51a0cd5d-8697-4eb1-8b08-e919ee881e1c}"}, "branch": {"name": "default"}}, "reason": "", "source": {"commit": {"hash": "81cbb11cfa38", "type": "commit", "links": {"self": {"href": "data/repositories/osrf/gazebo/commit/81cbb11cfa38.json"}, "html": {"href": "#!/osrf/gazebo/commits/81cbb11cfa38"}}}, "repository": {"links": {"self": {"href": "data/repositories/osrf/gazebo.json"}, "html": {"href": "#!/osrf/gazebo"}, "avatar": {"href": "data/bytebucket.org/ravatar/{51a0cd5d-8697-4eb1-8b08-e919ee881e1c}ts=1694483"}}, "type": "repository", "name": "gazebo", "full_name": "osrf/gazebo", "uuid": "{51a0cd5d-8697-4eb1-8b08-e919ee881e1c}"}, "branch": {"name": "undo_ME_nestedModel_insertion_deletion"}}, "state": "OPEN", "author": {"display_name": "Nate Koenig", "uuid": "{c862cdd9-fcc8-4419-9fc7-e20db14b8fcb}", "links": {"self": {"href": "https://api.bitbucket.org/2.0/users/%7Bc862cdd9-fcc8-4419-9fc7-e20db14b8fcb%7D"}, "html": {"href": "https://bitbucket.org/%7Bc862cdd9-fcc8-4419-9fc7-e20db14b8fcb%7D/"}, "avatar": {"href": "https://avatar-management--avatars.us-west-2.prod.public.atl-paas.net/557058:095b1e12-74ed-4e20-b44f-2f0745b616e0/ca24bb11-4787-4b14-a20d-d91835e9bde2/128"}}, "nickname": "Nathan Koenig", "type": "user", "account_id": "557058:095b1e12-74ed-4e20-b44f-2f0745b616e0"}, "date": "2016-04-04T14:36:49.866963+00:00"}, "pull_request": {"type": "pullrequest", "id": 2229, "links": {"self": {"href": "data/repositories/osrf/gazebo/pullrequests/2229.json"}, "html": {"href": "#!/osrf/gazebo/pull-requests/2229"}}, "title": "Model Editor: Undo insert / delete nested models"}}, {"comment": {"links": {"self": {"href": "data/repositories/osrf/gazebo/pullrequests/2229/comments/16616302.json"}, "html": {"href": "#!/osrf/gazebo/pull-requests/2229/_/diff#comment-16616302"}}, "parent": {"id": 16615913, "links": {"self": {"href": "data/repositories/osrf/gazebo/pullrequests/2229/comments/16615913.json"}, "html": {"href": "#!/osrf/gazebo/pull-requests/2229/_/diff#comment-16615913"}}}, "deleted": false, "pullrequest": {"type": "pullrequest", "id": 2229, "links": {"self": {"href": "data/repositories/osrf/gazebo/pullrequests/2229.json"}, "html": {"href": "#!/osrf/gazebo/pull-requests/2229"}}, "title": "Model Editor: Undo insert / delete nested models"}, "content": {"raw": "Thanks for the backtrace. I didn't even realize the `JointMaker_TEST` and other Model Editor tests were also failing. I thought only the new test was. ", "markup": "markdown", "html": "<p>Thanks for the backtrace. I didn't even realize the <code>JointMaker_TEST</code> and other Model Editor tests were also failing. I thought only the new test was. </p>", "type": "rendered"}, "created_on": "2016-04-02T00:26:30.129610+00:00", "user": {"display_name": "Louise Poubel", "uuid": "{5cfa2075-477b-4ded-bdb9-8d2479544ec4}", "links": {"self": {"href": "https://api.bitbucket.org/2.0/users/%7B5cfa2075-477b-4ded-bdb9-8d2479544ec4%7D"}, "html": {"href": "https://bitbucket.org/%7B5cfa2075-477b-4ded-bdb9-8d2479544ec4%7D/"}, "avatar": {"href": "https://avatar-management--avatars.us-west-2.prod.public.atl-paas.net/557058:6ff86fcb-b7ab-44a5-b8a6-f6d9cae8b6e8/7d903d90-c5ea-4182-b7ef-0d467e9e1c74/128"}}, "nickname": "chapulina", "type": "user", "account_id": "557058:6ff86fcb-b7ab-44a5-b8a6-f6d9cae8b6e8"}, "updated_on": "2016-04-02T00:26:30.131800+00:00", "type": "pullrequest_comment", "id": 16616302}, "pull_request": {"type": "pullrequest", "id": 2229, "links": {"self": {"href": "data/repositories/osrf/gazebo/pullrequests/2229.json"}, "html": {"href": "#!/osrf/gazebo/pull-requests/2229"}}, "title": "Model Editor: Undo insert / delete nested models"}}, {"comment": {"links": {"self": {"href": "data/repositories/osrf/gazebo/pullrequests/2229/comments/16615913.json"}, "html": {"href": "#!/osrf/gazebo/pull-requests/2229/_/diff#comment-16615913"}}, "parent": {"id": 16611741, "links": {"self": {"href": "data/repositories/osrf/gazebo/pullrequests/2229/comments/16611741.json"}, "html": {"href": "#!/osrf/gazebo/pull-requests/2229/_/diff#comment-16611741"}}}, "deleted": false, "pullrequest": {"type": "pullrequest", "id": 2229, "links": {"self": {"href": "data/repositories/osrf/gazebo/pullrequests/2229.json"}, "html": {"href": "#!/osrf/gazebo/pull-requests/2229"}}, "title": "Model Editor: Undo insert / delete nested models"}, "content": {"raw": "they are failing in `~MainWindow`:\n\n* https://gist.github.com/scpeters/cf3af66c4865ea9a2da2b01087a5cd83", "markup": "markdown", "html": "<p>they are failing in <code>~MainWindow</code>:</p>\n<ul>\n<li><a href=\"https://gist.github.com/scpeters/cf3af66c4865ea9a2da2b01087a5cd83\" rel=\"nofollow\" class=\"ap-connect-link\">https://gist.github.com/scpeters/cf3af66c4865ea9a2da2b01087a5cd83</a></li>\n</ul>", "type": "rendered"}, "created_on": "2016-04-02T00:18:40.628276+00:00", "user": {"display_name": "Steve Peters", "uuid": "{2ccfed09-18b8-4921-8d58-15ef01092802}", "links": {"self": {"href": "https://api.bitbucket.org/2.0/users/%7B2ccfed09-18b8-4921-8d58-15ef01092802%7D"}, "html": {"href": "https://bitbucket.org/%7B2ccfed09-18b8-4921-8d58-15ef01092802%7D/"}, "avatar": {"href": "data/secure.gravatar.com/avatar/1fb4816dad9e68337d3096f750951f6cd=httpsavatar-management--avatars.us-west-2.prod.public.atl-paas.netinitialsSP-1.png"}}, "nickname": "Steven Peters", "type": "user", "account_id": "557058:5de38267-b118-494c-aa76-4fab35448816"}, "updated_on": "2016-04-02T00:18:40.632953+00:00", "type": "pullrequest_comment", "id": 16615913}, "pull_request": {"type": "pullrequest", "id": 2229, "links": {"self": {"href": "data/repositories/osrf/gazebo/pullrequests/2229.json"}, "html": {"href": "#!/osrf/gazebo/pull-requests/2229"}}, "title": "Model Editor: Undo insert / delete nested models"}}, {"update": {"description": "Issue #402\r\n\r\nUndo / redo:\r\n\r\n* Inserting nested models from the palette\r\n\r\n* Copy/pasting nested models\r\n\r\n* Deleting nested models with the DEL key\r\n\r\n* Deleting nested models via context menu\r\n\r\nObs:\r\n\r\nModel added to `testdb` should be the same as that added in pull request #2207, targeted at gazebo7. Once that is merged forward to default, they will coincide.", "title": "Model Editor: Undo insert / delete nested models", "destination": {"commit": {"hash": "24946320a3b5", "type": "commit", "links": {"self": {"href": "data/repositories/osrf/gazebo/commit/24946320a3b5.json"}, "html": {"href": "#!/osrf/gazebo/commits/24946320a3b5"}}}, "repository": {"links": {"self": {"href": "data/repositories/osrf/gazebo.json"}, "html": {"href": "#!/osrf/gazebo"}, "avatar": {"href": "data/bytebucket.org/ravatar/{51a0cd5d-8697-4eb1-8b08-e919ee881e1c}ts=1694483"}}, "type": "repository", "name": "gazebo", "full_name": "osrf/gazebo", "uuid": "{51a0cd5d-8697-4eb1-8b08-e919ee881e1c}"}, "branch": {"name": "default"}}, "reason": "", "source": {"commit": {"hash": "2c8ec25583f3", "type": "commit", "links": {"self": {"href": "data/repositories/osrf/gazebo/commit/2c8ec25583f3.json"}, "html": {"href": "#!/osrf/gazebo/commits/2c8ec25583f3"}}}, "repository": {"links": {"self": {"href": "data/repositories/osrf/gazebo.json"}, "html": {"href": "#!/osrf/gazebo"}, "avatar": {"href": "data/bytebucket.org/ravatar/{51a0cd5d-8697-4eb1-8b08-e919ee881e1c}ts=1694483"}}, "type": "repository", "name": "gazebo", "full_name": "osrf/gazebo", "uuid": "{51a0cd5d-8697-4eb1-8b08-e919ee881e1c}"}, "branch": {"name": "undo_ME_nestedModel_insertion_deletion"}}, "state": "OPEN", "author": {"display_name": "Steve Peters", "uuid": "{2ccfed09-18b8-4921-8d58-15ef01092802}", "links": {"self": {"href": "https://api.bitbucket.org/2.0/users/%7B2ccfed09-18b8-4921-8d58-15ef01092802%7D"}, "html": {"href": "https://bitbucket.org/%7B2ccfed09-18b8-4921-8d58-15ef01092802%7D/"}, "avatar": {"href": "data/secure.gravatar.com/avatar/1fb4816dad9e68337d3096f750951f6cd=httpsavatar-management--avatars.us-west-2.prod.public.atl-paas.netinitialsSP-1.png"}}, "nickname": "Steven Peters", "type": "user", "account_id": "557058:5de38267-b118-494c-aa76-4fab35448816"}, "date": "2016-04-01T22:12:43.853790+00:00"}, "pull_request": {"type": "pullrequest", "id": 2229, "links": {"self": {"href": "data/repositories/osrf/gazebo/pullrequests/2229.json"}, "html": {"href": "#!/osrf/gazebo/pull-requests/2229"}}, "title": "Model Editor: Undo insert / delete nested models"}}, {"comment": {"links": {"self": {"href": "data/repositories/osrf/gazebo/pullrequests/2229/comments/16611741.json"}, "html": {"href": "#!/osrf/gazebo/pull-requests/2229/_/diff#comment-16611741"}}, "parent": {"id": 16608266, "links": {"self": {"href": "data/repositories/osrf/gazebo/pullrequests/2229/comments/16608266.json"}, "html": {"href": "#!/osrf/gazebo/pull-requests/2229/_/diff#comment-16608266"}}}, "deleted": false, "pullrequest": {"type": "pullrequest", "id": 2229, "links": {"self": {"href": "data/repositories/osrf/gazebo/pullrequests/2229.json"}, "html": {"href": "#!/osrf/gazebo/pull-requests/2229"}}, "title": "Model Editor: Undo insert / delete nested models"}, "content": {"raw": "test fails on homebrew, will look into it", "markup": "markdown", "html": "<p>test fails on homebrew, will look into it</p>", "type": "rendered"}, "created_on": "2016-04-01T22:03:43.238068+00:00", "user": {"display_name": "Louise Poubel", "uuid": "{5cfa2075-477b-4ded-bdb9-8d2479544ec4}", "links": {"self": {"href": "https://api.bitbucket.org/2.0/users/%7B5cfa2075-477b-4ded-bdb9-8d2479544ec4%7D"}, "html": {"href": "https://bitbucket.org/%7B5cfa2075-477b-4ded-bdb9-8d2479544ec4%7D/"}, "avatar": {"href": "https://avatar-management--avatars.us-west-2.prod.public.atl-paas.net/557058:6ff86fcb-b7ab-44a5-b8a6-f6d9cae8b6e8/7d903d90-c5ea-4182-b7ef-0d467e9e1c74/128"}}, "nickname": "chapulina", "type": "user", "account_id": "557058:6ff86fcb-b7ab-44a5-b8a6-f6d9cae8b6e8"}, "updated_on": "2016-04-01T22:03:43.240058+00:00", "type": "pullrequest_comment", "id": 16611741}, "pull_request": {"type": "pullrequest", "id": 2229, "links": {"self": {"href": "data/repositories/osrf/gazebo/pullrequests/2229.json"}, "html": {"href": "#!/osrf/gazebo/pull-requests/2229"}}, "title": "Model Editor: Undo insert / delete nested models"}}, {"comment": {"links": {"self": {"href": "data/repositories/osrf/gazebo/pullrequests/2229/comments/16608266.json"}, "html": {"href": "#!/osrf/gazebo/pull-requests/2229/_/diff#comment-16608266"}}, "deleted": false, "pullrequest": {"type": "pullrequest", "id": 2229, "links": {"self": {"href": "data/repositories/osrf/gazebo/pullrequests/2229.json"}, "html": {"href": "#!/osrf/gazebo/pull-requests/2229"}}, "title": "Model Editor: Undo insert / delete nested models"}, "content": {"raw": "As the great status indicator says above on the right, [trusty no gpu](build.osrfoundation.org/job/gazebo-ci-pr_any-trusty-amd64-gpu-none/283/) is :large_blue_circle: \n\n[homebrew](http://build.osrfoundation.org/view/main/view/CI%20any%20jobs/job/gazebo-ci-pr_any-homebrew-amd64/297/) pending\n\n", "markup": "markdown", "html": "<p>As the great status indicator says above on the right, <a data-is-external-link=\"true\" href=\"/osrf/gazebo/src/cde54284e90b59a9af9fade096946c0cd4a91c44/build.osrfoundation.org/job/gazebo-ci-pr_any-trusty-amd64-gpu-none/283\" rel=\"nofollow\">trusty no gpu</a> is :large_blue_circle: </p>\n<p><a data-is-external-link=\"true\" href=\"http://build.osrfoundation.org/view/main/view/CI%20any%20jobs/job/gazebo-ci-pr_any-homebrew-amd64/297/\" rel=\"nofollow\">homebrew</a> pending</p>", "type": "rendered"}, "created_on": "2016-04-01T20:35:05.785328+00:00", "user": {"display_name": "Louise Poubel", "uuid": "{5cfa2075-477b-4ded-bdb9-8d2479544ec4}", "links": {"self": {"href": "https://api.bitbucket.org/2.0/users/%7B5cfa2075-477b-4ded-bdb9-8d2479544ec4%7D"}, "html": {"href": "https://bitbucket.org/%7B5cfa2075-477b-4ded-bdb9-8d2479544ec4%7D/"}, "avatar": {"href": "https://avatar-management--avatars.us-west-2.prod.public.atl-paas.net/557058:6ff86fcb-b7ab-44a5-b8a6-f6d9cae8b6e8/7d903d90-c5ea-4182-b7ef-0d467e9e1c74/128"}}, "nickname": "chapulina", "type": "user", "account_id": "557058:6ff86fcb-b7ab-44a5-b8a6-f6d9cae8b6e8"}, "updated_on": "2016-04-01T20:35:05.787304+00:00", "type": "pullrequest_comment", "id": 16608266}, "pull_request": {"type": "pullrequest", "id": 2229, "links": {"self": {"href": "data/repositories/osrf/gazebo/pullrequests/2229.json"}, "html": {"href": "#!/osrf/gazebo/pull-requests/2229"}}, "title": "Model Editor: Undo insert / delete nested models"}}, {"update": {"description": "Issue #402\r\n\r\nUndo / redo:\r\n\r\n* Inserting nested models from the palette\r\n\r\n* Copy/pasting nested models\r\n\r\n* Deleting nested models with the DEL key\r\n\r\n* Deleting nested models via context menu\r\n\r\nObs:\r\n\r\nModel added to `testdb` should be the same as that added in pull request #2207, targeted at gazebo7. Once that is merged forward to default, they will coincide.", "title": "Model Editor: Undo insert / delete nested models", "destination": {"commit": {"hash": "13a4b72180d1", "type": "commit", "links": {"self": {"href": "data/repositories/osrf/gazebo/commit/13a4b72180d1.json"}, "html": {"href": "#!/osrf/gazebo/commits/13a4b72180d1"}}}, "repository": {"links": {"self": {"href": "data/repositories/osrf/gazebo.json"}, "html": {"href": "#!/osrf/gazebo"}, "avatar": {"href": "data/bytebucket.org/ravatar/{51a0cd5d-8697-4eb1-8b08-e919ee881e1c}ts=1694483"}}, "type": "repository", "name": "gazebo", "full_name": "osrf/gazebo", "uuid": "{51a0cd5d-8697-4eb1-8b08-e919ee881e1c}"}, "branch": {"name": "default"}}, "reason": "", "source": {"commit": {"hash": "4a5b94070c9c", "type": "commit", "links": {"self": {"href": "data/repositories/osrf/gazebo/commit/4a5b94070c9c.json"}, "html": {"href": "#!/osrf/gazebo/commits/4a5b94070c9c"}}}, "repository": {"links": {"self": {"href": "data/repositories/osrf/gazebo.json"}, "html": {"href": "#!/osrf/gazebo"}, "avatar": {"href": "data/bytebucket.org/ravatar/{51a0cd5d-8697-4eb1-8b08-e919ee881e1c}ts=1694483"}}, "type": "repository", "name": "gazebo", "full_name": "osrf/gazebo", "uuid": "{51a0cd5d-8697-4eb1-8b08-e919ee881e1c}"}, "branch": {"name": "undo_ME_nestedModel_insertion_deletion"}}, "state": "OPEN", "author": {"display_name": "Louise Poubel", "uuid": "{5cfa2075-477b-4ded-bdb9-8d2479544ec4}", "links": {"self": {"href": "https://api.bitbucket.org/2.0/users/%7B5cfa2075-477b-4ded-bdb9-8d2479544ec4%7D"}, "html": {"href": "https://bitbucket.org/%7B5cfa2075-477b-4ded-bdb9-8d2479544ec4%7D/"}, "avatar": {"href": "https://avatar-management--avatars.us-west-2.prod.public.atl-paas.net/557058:6ff86fcb-b7ab-44a5-b8a6-f6d9cae8b6e8/7d903d90-c5ea-4182-b7ef-0d467e9e1c74/128"}}, "nickname": "chapulina", "type": "user", "account_id": "557058:6ff86fcb-b7ab-44a5-b8a6-f6d9cae8b6e8"}, "date": "2016-04-01T16:27:21.129726+00:00"}, "pull_request": {"type": "pullrequest", "id": 2229, "links": {"self": {"href": "data/repositories/osrf/gazebo/pullrequests/2229.json"}, "html": {"href": "#!/osrf/gazebo/pull-requests/2229"}}, "title": "Model Editor: Undo insert / delete nested models"}}, {"update": {"description": "Issue #402\r\n\r\nUndo / redo:\r\n\r\n* Inserting nested models from the palette\r\n\r\n* Copy/pasting nested models\r\n\r\n* Deleting nested models with the DEL key\r\n\r\n* Deleting nested models via context menu\r\n\r\nObs:\r\n\r\nModel added to `testdb` should be the same as that added in pull request #2207, targeted at gazebo7. Once that is merged forward to default, they will coincide.", "title": "Model Editor: Undo insert / delete nested models", "destination": {"commit": {"hash": "13a4b72180d1", "type": "commit", "links": {"self": {"href": "data/repositories/osrf/gazebo/commit/13a4b72180d1.json"}, "html": {"href": "#!/osrf/gazebo/commits/13a4b72180d1"}}}, "repository": {"links": {"self": {"href": "data/repositories/osrf/gazebo.json"}, "html": {"href": "#!/osrf/gazebo"}, "avatar": {"href": "data/bytebucket.org/ravatar/{51a0cd5d-8697-4eb1-8b08-e919ee881e1c}ts=1694483"}}, "type": "repository", "name": "gazebo", "full_name": "osrf/gazebo", "uuid": "{51a0cd5d-8697-4eb1-8b08-e919ee881e1c}"}, "branch": {"name": "default"}}, "reason": "", "source": {"commit": {"hash": "06c1873546b6", "type": "commit", "links": {"self": {"href": "data/repositories/osrf/gazebo/commit/06c1873546b6.json"}, "html": {"href": "#!/osrf/gazebo/commits/06c1873546b6"}}}, "repository": {"links": {"self": {"href": "data/repositories/osrf/gazebo.json"}, "html": {"href": "#!/osrf/gazebo"}, "avatar": {"href": "data/bytebucket.org/ravatar/{51a0cd5d-8697-4eb1-8b08-e919ee881e1c}ts=1694483"}}, "type": "repository", "name": "gazebo", "full_name": "osrf/gazebo", "uuid": "{51a0cd5d-8697-4eb1-8b08-e919ee881e1c}"}, "branch": {"name": "undo_ME_nestedModel_insertion_deletion"}}, "state": "OPEN", "author": {"display_name": "Louise Poubel", "uuid": "{5cfa2075-477b-4ded-bdb9-8d2479544ec4}", "links": {"self": {"href": "https://api.bitbucket.org/2.0/users/%7B5cfa2075-477b-4ded-bdb9-8d2479544ec4%7D"}, "html": {"href": "https://bitbucket.org/%7B5cfa2075-477b-4ded-bdb9-8d2479544ec4%7D/"}, "avatar": {"href": "https://avatar-management--avatars.us-west-2.prod.public.atl-paas.net/557058:6ff86fcb-b7ab-44a5-b8a6-f6d9cae8b6e8/7d903d90-c5ea-4182-b7ef-0d467e9e1c74/128"}}, "nickname": "chapulina", "type": "user", "account_id": "557058:6ff86fcb-b7ab-44a5-b8a6-f6d9cae8b6e8"}, "date": "2016-04-01T16:24:08.963468+00:00"}, "pull_request": {"type": "pullrequest", "id": 2229, "links": {"self": {"href": "data/repositories/osrf/gazebo/pullrequests/2229.json"}, "html": {"href": "#!/osrf/gazebo/pull-requests/2229"}}, "title": "Model Editor: Undo insert / delete nested models"}}, {"update": {"description": "Issue #402\r\n\r\nUndo / redo:\r\n\r\n* Inserting nested models from the palette\r\n\r\n* Copy/pasting nested models\r\n\r\n* Deleting nested models with the DEL key\r\n\r\n* Deleting nested models via context menu\r\n\r\nObs:\r\n\r\nModel added to `testdb` should be the same as that added in pull request #2207, targeted at gazebo7. Once that is merged forward to default, they will coincide.", "title": "Model Editor: Undo insert / delete nested models", "destination": {"commit": {"hash": "13a4b72180d1", "type": "commit", "links": {"self": {"href": "data/repositories/osrf/gazebo/commit/13a4b72180d1.json"}, "html": {"href": "#!/osrf/gazebo/commits/13a4b72180d1"}}}, "repository": {"links": {"self": {"href": "data/repositories/osrf/gazebo.json"}, "html": {"href": "#!/osrf/gazebo"}, "avatar": {"href": "data/bytebucket.org/ravatar/{51a0cd5d-8697-4eb1-8b08-e919ee881e1c}ts=1694483"}}, "type": "repository", "name": "gazebo", "full_name": "osrf/gazebo", "uuid": "{51a0cd5d-8697-4eb1-8b08-e919ee881e1c}"}, "branch": {"name": "default"}}, "reason": "", "source": {"commit": {"hash": "06c1873546b6", "type": "commit", "links": {"self": {"href": "data/repositories/osrf/gazebo/commit/06c1873546b6.json"}, "html": {"href": "#!/osrf/gazebo/commits/06c1873546b6"}}}, "repository": {"links": {"self": {"href": "data/repositories/osrf/gazebo.json"}, "html": {"href": "#!/osrf/gazebo"}, "avatar": {"href": "data/bytebucket.org/ravatar/{51a0cd5d-8697-4eb1-8b08-e919ee881e1c}ts=1694483"}}, "type": "repository", "name": "gazebo", "full_name": "osrf/gazebo", "uuid": "{51a0cd5d-8697-4eb1-8b08-e919ee881e1c}"}, "branch": {"name": "undo_ME_nestedModel_insertion_deletion"}}, "state": "OPEN", "author": {"display_name": "Louise Poubel", "uuid": "{5cfa2075-477b-4ded-bdb9-8d2479544ec4}", "links": {"self": {"href": "https://api.bitbucket.org/2.0/users/%7B5cfa2075-477b-4ded-bdb9-8d2479544ec4%7D"}, "html": {"href": "https://bitbucket.org/%7B5cfa2075-477b-4ded-bdb9-8d2479544ec4%7D/"}, "avatar": {"href": "https://avatar-management--avatars.us-west-2.prod.public.atl-paas.net/557058:6ff86fcb-b7ab-44a5-b8a6-f6d9cae8b6e8/7d903d90-c5ea-4182-b7ef-0d467e9e1c74/128"}}, "nickname": "chapulina", "type": "user", "account_id": "557058:6ff86fcb-b7ab-44a5-b8a6-f6d9cae8b6e8"}, "date": "2016-04-01T16:24:08.901362+00:00"}, "pull_request": {"type": "pullrequest", "id": 2229, "links": {"self": {"href": "data/repositories/osrf/gazebo/pullrequests/2229.json"}, "html": {"href": "#!/osrf/gazebo/pull-requests/2229"}}, "title": "Model Editor: Undo insert / delete nested models"}}]}