{"links": {"self": {"href": "data/repositories/osrf/gazebo/pullrequests/415/comments/174245.json"}, "code": {"href": "https://api.bitbucket.org/2.0/repositories/osrf/gazebo/diff/osrf/gazebo:50936409e756..20efe8528945?path=gazebo%2Fsensors%2FImuSensor.cc"}, "html": {"href": "#!/osrf/gazebo/pull-requests/415/_/diff#comment-174245"}}, "deleted": false, "pullrequest": {"type": "pullrequest", "id": 415, "links": {"self": {"href": "data/repositories/osrf/gazebo/pullrequests/415.json"}, "html": {"href": "#!/osrf/gazebo/pull-requests/415"}}, "title": "Updated imu sensor  to subscribe to timestamped link data"}, "content": {"raw": "Can you make sure that `this->parentName` is the scoped name of the parent?", "markup": "markdown", "html": "<p>Can you make sure that <code>this-&gt;parentName</code> is the scoped name of the parent?</p>", "type": "rendered"}, "created_on": "2013-03-28T04:08:01.742786+00:00", "user": {"display_name": "Nate Koenig", "uuid": "{c862cdd9-fcc8-4419-9fc7-e20db14b8fcb}", "links": {"self": {"href": "https://api.bitbucket.org/2.0/users/%7Bc862cdd9-fcc8-4419-9fc7-e20db14b8fcb%7D"}, "html": {"href": "https://bitbucket.org/%7Bc862cdd9-fcc8-4419-9fc7-e20db14b8fcb%7D/"}, "avatar": {"href": "https://avatar-management--avatars.us-west-2.prod.public.atl-paas.net/557058:095b1e12-74ed-4e20-b44f-2f0745b616e0/ca24bb11-4787-4b14-a20d-d91835e9bde2/128"}}, "nickname": "Nathan Koenig", "type": "user", "account_id": "557058:095b1e12-74ed-4e20-b44f-2f0745b616e0"}, "inline": {"to": 168, "from": null, "outdated": true, "path": "gazebo/sensors/ImuSensor.cc"}, "updated_on": "2013-03-28T04:08:01.751787+00:00", "type": "pullrequest_comment", "id": 174245}