{"pagelen": 50, "values": [{"update": {"description": "add ability to parse plugin parameters that contains pose elements.\r\n\r\nexpose Joint::SetThreadPitch for screw joints.", "title": "param pose parsing.  exposing thread pitch setting for screw constraint.", "destination": {"commit": {"hash": "d9e6100f82ee", "type": "commit", "links": {"self": {"href": "data/repositories/osrf/gazebo/commit/d9e6100f82ee.json"}, "html": {"href": "#!/osrf/gazebo/commits/d9e6100f82ee"}}}, "repository": {"links": {"self": {"href": "data/repositories/osrf/gazebo.json"}, "html": {"href": "#!/osrf/gazebo"}, "avatar": {"href": "data/bytebucket.org/ravatar/{51a0cd5d-8697-4eb1-8b08-e919ee881e1c}ts=1694483"}}, "type": "repository", "name": "gazebo", "full_name": "osrf/gazebo", "uuid": "{51a0cd5d-8697-4eb1-8b08-e919ee881e1c}"}, "branch": {"name": "dev"}}, "reason": "", "source": {"commit": {"hash": "ec27b32373e3", "type": "commit", "links": {"self": {"href": "data/repositories/osrf/gazebo/commit/ec27b32373e3.json"}, "html": {"href": "#!/osrf/gazebo/commits/ec27b32373e3"}}}, "repository": {"links": {"self": {"href": "data/repositories/osrf/gazebo.json"}, "html": {"href": "#!/osrf/gazebo"}, "avatar": {"href": "data/bytebucket.org/ravatar/{51a0cd5d-8697-4eb1-8b08-e919ee881e1c}ts=1694483"}}, "type": "repository", "name": "gazebo", "full_name": "osrf/gazebo", "uuid": "{51a0cd5d-8697-4eb1-8b08-e919ee881e1c}"}, "branch": {"name": "param_thread_picth_path"}}, "state": "MERGED", "author": {"display_name": "Nate Koenig", "uuid": "{c862cdd9-fcc8-4419-9fc7-e20db14b8fcb}", "links": {"self": {"href": "https://api.bitbucket.org/2.0/users/%7Bc862cdd9-fcc8-4419-9fc7-e20db14b8fcb%7D"}, "html": {"href": "https://bitbucket.org/%7Bc862cdd9-fcc8-4419-9fc7-e20db14b8fcb%7D/"}, "avatar": {"href": "https://avatar-management--avatars.us-west-2.prod.public.atl-paas.net/557058:095b1e12-74ed-4e20-b44f-2f0745b616e0/ca24bb11-4787-4b14-a20d-d91835e9bde2/128"}}, "nickname": "Nathan Koenig", "type": "user", "account_id": "557058:095b1e12-74ed-4e20-b44f-2f0745b616e0"}, "date": "2012-11-08T15:41:18.116754+00:00"}, "pull_request": {"type": "pullrequest", "id": 77, "links": {"self": {"href": "data/repositories/osrf/gazebo/pullrequests/77.json"}, "html": {"href": "#!/osrf/gazebo/pull-requests/77"}}, "title": "param pose parsing.  exposing thread pitch setting for screw constraint."}}, {"approval": {"date": "2012-11-08T15:40:47.866720+00:00", "pullrequest": {"type": "pullrequest", "id": 77, "links": {"self": {"href": "data/repositories/osrf/gazebo/pullrequests/77.json"}, "html": {"href": "#!/osrf/gazebo/pull-requests/77"}}, "title": "param pose parsing.  exposing thread pitch setting for screw constraint."}, "user": {"display_name": "Nate Koenig", "uuid": "{c862cdd9-fcc8-4419-9fc7-e20db14b8fcb}", "links": {"self": {"href": "https://api.bitbucket.org/2.0/users/%7Bc862cdd9-fcc8-4419-9fc7-e20db14b8fcb%7D"}, "html": {"href": "https://bitbucket.org/%7Bc862cdd9-fcc8-4419-9fc7-e20db14b8fcb%7D/"}, "avatar": {"href": "https://avatar-management--avatars.us-west-2.prod.public.atl-paas.net/557058:095b1e12-74ed-4e20-b44f-2f0745b616e0/ca24bb11-4787-4b14-a20d-d91835e9bde2/128"}}, "nickname": "Nathan Koenig", "type": "user", "account_id": "557058:095b1e12-74ed-4e20-b44f-2f0745b616e0"}}, "pull_request": {"type": "pullrequest", "id": 77, "links": {"self": {"href": "data/repositories/osrf/gazebo/pullrequests/77.json"}, "html": {"href": "#!/osrf/gazebo/pull-requests/77"}}, "title": "param pose parsing.  exposing thread pitch setting for screw constraint."}}, {"update": {"description": "add ability to parse plugin parameters that contains pose elements.\r\n\r\nexpose Joint::SetThreadPitch for screw joints.", "title": "param pose parsing.  exposing thread pitch setting for screw constraint.", "destination": {"commit": {"hash": "d9e6100f82ee", "type": "commit", "links": {"self": {"href": "data/repositories/osrf/gazebo/commit/d9e6100f82ee.json"}, "html": {"href": "#!/osrf/gazebo/commits/d9e6100f82ee"}}}, "repository": {"links": {"self": {"href": "data/repositories/osrf/gazebo.json"}, "html": {"href": "#!/osrf/gazebo"}, "avatar": {"href": "data/bytebucket.org/ravatar/{51a0cd5d-8697-4eb1-8b08-e919ee881e1c}ts=1694483"}}, "type": "repository", "name": "gazebo", "full_name": "osrf/gazebo", "uuid": "{51a0cd5d-8697-4eb1-8b08-e919ee881e1c}"}, "branch": {"name": "dev"}}, "reason": "", "source": {"commit": {"hash": "ec27b32373e3", "type": "commit", "links": {"self": {"href": "data/repositories/osrf/gazebo/commit/ec27b32373e3.json"}, "html": {"href": "#!/osrf/gazebo/commits/ec27b32373e3"}}}, "repository": {"links": {"self": {"href": "data/repositories/osrf/gazebo.json"}, "html": {"href": "#!/osrf/gazebo"}, "avatar": {"href": "data/bytebucket.org/ravatar/{51a0cd5d-8697-4eb1-8b08-e919ee881e1c}ts=1694483"}}, "type": "repository", "name": "gazebo", "full_name": "osrf/gazebo", "uuid": "{51a0cd5d-8697-4eb1-8b08-e919ee881e1c}"}, "branch": {"name": "param_thread_picth_path"}}, "state": "OPEN", "author": {"display_name": "Nate Koenig", "uuid": "{c862cdd9-fcc8-4419-9fc7-e20db14b8fcb}", "links": {"self": {"href": "https://api.bitbucket.org/2.0/users/%7Bc862cdd9-fcc8-4419-9fc7-e20db14b8fcb%7D"}, "html": {"href": "https://bitbucket.org/%7Bc862cdd9-fcc8-4419-9fc7-e20db14b8fcb%7D/"}, "avatar": {"href": "https://avatar-management--avatars.us-west-2.prod.public.atl-paas.net/557058:095b1e12-74ed-4e20-b44f-2f0745b616e0/ca24bb11-4787-4b14-a20d-d91835e9bde2/128"}}, "nickname": "Nathan Koenig", "type": "user", "account_id": "557058:095b1e12-74ed-4e20-b44f-2f0745b616e0"}, "date": "2012-11-08T15:40:13.827366+00:00"}, "pull_request": {"type": "pullrequest", "id": 77, "links": {"self": {"href": "data/repositories/osrf/gazebo/pullrequests/77.json"}, "html": {"href": "#!/osrf/gazebo/pull-requests/77"}}, "title": "param pose parsing.  exposing thread pitch setting for screw constraint."}}, {"comment": {"links": {"self": {"href": "data/repositories/osrf/gazebo/pullrequests/77/comments/37881.json"}, "html": {"href": "#!/osrf/gazebo/pull-requests/77/_/diff#comment-37881"}}, "parent": {"id": 37879, "links": {"self": {"href": "data/repositories/osrf/gazebo/pullrequests/77/comments/37879.json"}, "html": {"href": "#!/osrf/gazebo/pull-requests/77/_/diff#comment-37879"}}}, "deleted": false, "pullrequest": {"type": "pullrequest", "id": 77, "links": {"self": {"href": "data/repositories/osrf/gazebo/pullrequests/77.json"}, "html": {"href": "#!/osrf/gazebo/pull-requests/77"}}, "title": "param pose parsing.  exposing thread pitch setting for screw constraint."}, "content": {"raw": "yeah, maybe call to `Joint::UpdateParameters(_sdf)` might be better.", "markup": "markdown", "html": "<p>yeah, maybe call to <code>Joint::UpdateParameters(_sdf)</code> might be better.</p>", "type": "rendered"}, "created_on": "2012-11-08T02:21:08.669175+00:00", "user": {"display_name": "John Hsu", "uuid": "{0a186eae-abf0-4514-a951-23db5eccc286}", "links": {"self": {"href": "https://api.bitbucket.org/2.0/users/%7B0a186eae-abf0-4514-a951-23db5eccc286%7D"}, "html": {"href": "https://bitbucket.org/%7B0a186eae-abf0-4514-a951-23db5eccc286%7D/"}, "avatar": {"href": "https://avatar-management--avatars.us-west-2.prod.public.atl-paas.net/557058:f3968cd3-4910-4384-8349-482a6c7889ec/5445ce6e-6273-47f0-84eb-621c86ca11cb/128"}}, "nickname": "hsu", "type": "user", "account_id": "557058:f3968cd3-4910-4384-8349-482a6c7889ec"}, "inline": {}, "updated_on": "2012-11-08T02:21:08.675364+00:00", "type": "pullrequest_comment", "id": 37881}, "pull_request": {"type": "pullrequest", "id": 77, "links": {"self": {"href": "data/repositories/osrf/gazebo/pullrequests/77.json"}, "html": {"href": "#!/osrf/gazebo/pull-requests/77"}}, "title": "param pose parsing.  exposing thread pitch setting for screw constraint."}}, {"comment": {"links": {"self": {"href": "data/repositories/osrf/gazebo/pullrequests/77/comments/37880.json"}, "html": {"href": "#!/osrf/gazebo/pull-requests/77/_/diff#comment-37880"}}, "parent": {"id": 37876, "links": {"self": {"href": "data/repositories/osrf/gazebo/pullrequests/77/comments/37876.json"}, "html": {"href": "#!/osrf/gazebo/pull-requests/77/_/diff#comment-37876"}}}, "deleted": false, "pullrequest": {"type": "pullrequest", "id": 77, "links": {"self": {"href": "data/repositories/osrf/gazebo/pullrequests/77.json"}, "html": {"href": "#!/osrf/gazebo/pull-requests/77"}}, "title": "param pose parsing.  exposing thread pitch setting for screw constraint."}, "content": {"raw": "Cool. I should have just looked at more of the code.", "markup": "markdown", "html": "<p>Cool. I should have just looked at more of the code.</p>", "type": "rendered"}, "created_on": "2012-11-08T02:19:56.607875+00:00", "user": {"display_name": "Nate Koenig", "uuid": "{c862cdd9-fcc8-4419-9fc7-e20db14b8fcb}", "links": {"self": {"href": "https://api.bitbucket.org/2.0/users/%7Bc862cdd9-fcc8-4419-9fc7-e20db14b8fcb%7D"}, "html": {"href": "https://bitbucket.org/%7Bc862cdd9-fcc8-4419-9fc7-e20db14b8fcb%7D/"}, "avatar": {"href": "https://avatar-management--avatars.us-west-2.prod.public.atl-paas.net/557058:095b1e12-74ed-4e20-b44f-2f0745b616e0/ca24bb11-4787-4b14-a20d-d91835e9bde2/128"}}, "nickname": "Nathan Koenig", "type": "user", "account_id": "557058:095b1e12-74ed-4e20-b44f-2f0745b616e0"}, "inline": {}, "updated_on": "2012-11-08T02:19:56.613706+00:00", "type": "pullrequest_comment", "id": 37880}, "pull_request": {"type": "pullrequest", "id": 77, "links": {"self": {"href": "data/repositories/osrf/gazebo/pullrequests/77.json"}, "html": {"href": "#!/osrf/gazebo/pull-requests/77"}}, "title": "param pose parsing.  exposing thread pitch setting for screw constraint."}}, {"comment": {"links": {"self": {"href": "data/repositories/osrf/gazebo/pullrequests/77/comments/37879.json"}, "html": {"href": "#!/osrf/gazebo/pull-requests/77/_/diff#comment-37879"}}, "deleted": false, "pullrequest": {"type": "pullrequest", "id": 77, "links": {"self": {"href": "data/repositories/osrf/gazebo/pullrequests/77.json"}, "html": {"href": "#!/osrf/gazebo/pull-requests/77"}}, "title": "param pose parsing.  exposing thread pitch setting for screw constraint."}, "content": {"raw": "This is specific to one particular joint type. Is there a cleaner mechanism for this?", "markup": "markdown", "html": "<p>This is specific to one particular joint type. Is there a cleaner mechanism for this?</p>", "type": "rendered"}, "created_on": "2012-11-08T02:17:56.365862+00:00", "user": {"display_name": "Nate Koenig", "uuid": "{c862cdd9-fcc8-4419-9fc7-e20db14b8fcb}", "links": {"self": {"href": "https://api.bitbucket.org/2.0/users/%7Bc862cdd9-fcc8-4419-9fc7-e20db14b8fcb%7D"}, "html": {"href": "https://bitbucket.org/%7Bc862cdd9-fcc8-4419-9fc7-e20db14b8fcb%7D/"}, "avatar": {"href": "https://avatar-management--avatars.us-west-2.prod.public.atl-paas.net/557058:095b1e12-74ed-4e20-b44f-2f0745b616e0/ca24bb11-4787-4b14-a20d-d91835e9bde2/128"}}, "nickname": "Nathan Koenig", "type": "user", "account_id": "557058:095b1e12-74ed-4e20-b44f-2f0745b616e0"}, "inline": {}, "updated_on": "2012-11-08T02:17:56.376228+00:00", "type": "pullrequest_comment", "id": 37879}, "pull_request": {"type": "pullrequest", "id": 77, "links": {"self": {"href": "data/repositories/osrf/gazebo/pullrequests/77.json"}, "html": {"href": "#!/osrf/gazebo/pull-requests/77"}}, "title": "param pose parsing.  exposing thread pitch setting for screw constraint."}}, {"update": {"description": "add ability to parse plugin parameters that contains pose elements.\r\n\r\nexpose Joint::SetThreadPitch for screw joints.", "title": "param pose parsing.  exposing thread pitch setting for screw constraint.", "destination": {"commit": {"hash": "5dbed136ec69", "type": "commit", "links": {"self": {"href": "data/repositories/osrf/gazebo/commit/5dbed136ec69.json"}, "html": {"href": "#!/osrf/gazebo/commits/5dbed136ec69"}}}, "repository": {"links": {"self": {"href": "data/repositories/osrf/gazebo.json"}, "html": {"href": "#!/osrf/gazebo"}, "avatar": {"href": "data/bytebucket.org/ravatar/{51a0cd5d-8697-4eb1-8b08-e919ee881e1c}ts=1694483"}}, "type": "repository", "name": "gazebo", "full_name": "osrf/gazebo", "uuid": "{51a0cd5d-8697-4eb1-8b08-e919ee881e1c}"}, "branch": {"name": "dev"}}, "reason": "", "source": {"commit": {"hash": "6d902eb30b99", "type": "commit", "links": {"self": {"href": "data/repositories/osrf/gazebo/commit/6d902eb30b99.json"}, "html": {"href": "#!/osrf/gazebo/commits/6d902eb30b99"}}}, "repository": {"links": {"self": {"href": "data/repositories/osrf/gazebo.json"}, "html": {"href": "#!/osrf/gazebo"}, "avatar": {"href": "data/bytebucket.org/ravatar/{51a0cd5d-8697-4eb1-8b08-e919ee881e1c}ts=1694483"}}, "type": "repository", "name": "gazebo", "full_name": "osrf/gazebo", "uuid": "{51a0cd5d-8697-4eb1-8b08-e919ee881e1c}"}, "branch": {"name": "param_thread_picth_path"}}, "state": "OPEN", "author": {"display_name": "Nate Koenig", "uuid": "{c862cdd9-fcc8-4419-9fc7-e20db14b8fcb}", "links": {"self": {"href": "https://api.bitbucket.org/2.0/users/%7Bc862cdd9-fcc8-4419-9fc7-e20db14b8fcb%7D"}, "html": {"href": "https://bitbucket.org/%7Bc862cdd9-fcc8-4419-9fc7-e20db14b8fcb%7D/"}, "avatar": {"href": "https://avatar-management--avatars.us-west-2.prod.public.atl-paas.net/557058:095b1e12-74ed-4e20-b44f-2f0745b616e0/ca24bb11-4787-4b14-a20d-d91835e9bde2/128"}}, "nickname": "Nathan Koenig", "type": "user", "account_id": "557058:095b1e12-74ed-4e20-b44f-2f0745b616e0"}, "date": "2012-11-08T02:16:39.124694+00:00"}, "pull_request": {"type": "pullrequest", "id": 77, "links": {"self": {"href": "data/repositories/osrf/gazebo/pullrequests/77.json"}, "html": {"href": "#!/osrf/gazebo/pull-requests/77"}}, "title": "param pose parsing.  exposing thread pitch setting for screw constraint."}}, {"comment": {"links": {"self": {"href": "data/repositories/osrf/gazebo/pullrequests/77/comments/37876.json"}, "html": {"href": "#!/osrf/gazebo/pull-requests/77/_/diff#comment-37876"}}, "parent": {"id": 37873, "links": {"self": {"href": "data/repositories/osrf/gazebo/pullrequests/77/comments/37873.json"}, "html": {"href": "#!/osrf/gazebo/pull-requests/77/_/diff#comment-37873"}}}, "deleted": false, "pullrequest": {"type": "pullrequest", "id": 77, "links": {"self": {"href": "data/repositories/osrf/gazebo/pullrequests/77.json"}, "html": {"href": "#!/osrf/gazebo/pull-requests/77"}}, "title": "param pose parsing.  exposing thread pitch setting for screw constraint."}, "content": {"raw": "when calling `_sdf->GetValuePose(\"my_plugin_stuff\")` insdie `ModelPlugin::Load(_model, _sdf)`, it seems equivalent parsing exists for `Vector3`, `String`, etc.?", "markup": "markdown", "html": "<p>when calling <code>_sdf-&gt;GetValuePose(\"my_plugin_stuff\")</code> insdie <code>ModelPlugin::Load(_model, _sdf)</code>, it seems equivalent parsing exists for <code>Vector3</code>, <code>String</code>, etc.?</p>", "type": "rendered"}, "created_on": "2012-11-08T02:07:08.877297+00:00", "user": {"display_name": "John Hsu", "uuid": "{0a186eae-abf0-4514-a951-23db5eccc286}", "links": {"self": {"href": "https://api.bitbucket.org/2.0/users/%7B0a186eae-abf0-4514-a951-23db5eccc286%7D"}, "html": {"href": "https://bitbucket.org/%7B0a186eae-abf0-4514-a951-23db5eccc286%7D/"}, "avatar": {"href": "https://avatar-management--avatars.us-west-2.prod.public.atl-paas.net/557058:f3968cd3-4910-4384-8349-482a6c7889ec/5445ce6e-6273-47f0-84eb-621c86ca11cb/128"}}, "nickname": "hsu", "type": "user", "account_id": "557058:f3968cd3-4910-4384-8349-482a6c7889ec"}, "inline": {}, "updated_on": "2012-11-08T02:08:05.962737+00:00", "type": "pullrequest_comment", "id": 37876}, "pull_request": {"type": "pullrequest", "id": 77, "links": {"self": {"href": "data/repositories/osrf/gazebo/pullrequests/77.json"}, "html": {"href": "#!/osrf/gazebo/pull-requests/77"}}, "title": "param pose parsing.  exposing thread pitch setting for screw constraint."}}, {"comment": {"links": {"self": {"href": "data/repositories/osrf/gazebo/pullrequests/77/comments/37873.json"}, "html": {"href": "#!/osrf/gazebo/pull-requests/77/_/diff#comment-37873"}}, "deleted": false, "pullrequest": {"type": "pullrequest", "id": 77, "links": {"self": {"href": "data/repositories/osrf/gazebo/pullrequests/77.json"}, "html": {"href": "#!/osrf/gazebo/pull-requests/77"}}, "title": "param pose parsing.  exposing thread pitch setting for screw constraint."}, "content": {"raw": "This seem wrong. When is this code ever executed?", "markup": "markdown", "html": "<p>This seem wrong. When is this code ever executed?</p>", "type": "rendered"}, "created_on": "2012-11-08T02:04:01.917289+00:00", "user": {"display_name": "Nate Koenig", "uuid": "{c862cdd9-fcc8-4419-9fc7-e20db14b8fcb}", "links": {"self": {"href": "https://api.bitbucket.org/2.0/users/%7Bc862cdd9-fcc8-4419-9fc7-e20db14b8fcb%7D"}, "html": {"href": "https://bitbucket.org/%7Bc862cdd9-fcc8-4419-9fc7-e20db14b8fcb%7D/"}, "avatar": {"href": "https://avatar-management--avatars.us-west-2.prod.public.atl-paas.net/557058:095b1e12-74ed-4e20-b44f-2f0745b616e0/ca24bb11-4787-4b14-a20d-d91835e9bde2/128"}}, "nickname": "Nathan Koenig", "type": "user", "account_id": "557058:095b1e12-74ed-4e20-b44f-2f0745b616e0"}, "inline": {}, "updated_on": "2012-11-08T02:04:01.922584+00:00", "type": "pullrequest_comment", "id": 37873}, "pull_request": {"type": "pullrequest", "id": 77, "links": {"self": {"href": "data/repositories/osrf/gazebo/pullrequests/77.json"}, "html": {"href": "#!/osrf/gazebo/pull-requests/77"}}, "title": "param pose parsing.  exposing thread pitch setting for screw constraint."}}, {"update": {"description": "add ability to parse plugin parameters that contains pose elements.\r\n\r\nexpose Joint::SetThreadPitch for screw joints.", "title": "param pose parsing.  exposing thread pitch setting for screw constraint.", "destination": {"commit": {"hash": "274a249a6395", "type": "commit", "links": {"self": {"href": "data/repositories/osrf/gazebo/commit/274a249a6395.json"}, "html": {"href": "#!/osrf/gazebo/commits/274a249a6395"}}}, "repository": {"links": {"self": {"href": "data/repositories/osrf/gazebo.json"}, "html": {"href": "#!/osrf/gazebo"}, "avatar": {"href": "data/bytebucket.org/ravatar/{51a0cd5d-8697-4eb1-8b08-e919ee881e1c}ts=1694483"}}, "type": "repository", "name": "gazebo", "full_name": "osrf/gazebo", "uuid": "{51a0cd5d-8697-4eb1-8b08-e919ee881e1c}"}, "branch": {"name": "dev"}}, "reason": "", "source": {"commit": {"hash": "1e31bf561cfe", "type": "commit", "links": {"self": {"href": "data/repositories/osrf/gazebo/commit/1e31bf561cfe.json"}, "html": {"href": "#!/osrf/gazebo/commits/1e31bf561cfe"}}}, "repository": {"links": {"self": {"href": "data/repositories/osrf/gazebo.json"}, "html": {"href": "#!/osrf/gazebo"}, "avatar": {"href": "data/bytebucket.org/ravatar/{51a0cd5d-8697-4eb1-8b08-e919ee881e1c}ts=1694483"}}, "type": "repository", "name": "gazebo", "full_name": "osrf/gazebo", "uuid": "{51a0cd5d-8697-4eb1-8b08-e919ee881e1c}"}, "branch": {"name": "param_thread_picth_path"}}, "state": "OPEN", "author": {"display_name": "John Hsu", "uuid": "{0a186eae-abf0-4514-a951-23db5eccc286}", "links": {"self": {"href": "https://api.bitbucket.org/2.0/users/%7B0a186eae-abf0-4514-a951-23db5eccc286%7D"}, "html": {"href": "https://bitbucket.org/%7B0a186eae-abf0-4514-a951-23db5eccc286%7D/"}, "avatar": {"href": "https://avatar-management--avatars.us-west-2.prod.public.atl-paas.net/557058:f3968cd3-4910-4384-8349-482a6c7889ec/5445ce6e-6273-47f0-84eb-621c86ca11cb/128"}}, "nickname": "hsu", "type": "user", "account_id": "557058:f3968cd3-4910-4384-8349-482a6c7889ec"}, "date": "2012-11-03T17:36:28.668445+00:00"}, "pull_request": {"type": "pullrequest", "id": 77, "links": {"self": {"href": "data/repositories/osrf/gazebo/pullrequests/77.json"}, "html": {"href": "#!/osrf/gazebo/pull-requests/77"}}, "title": "param pose parsing.  exposing thread pitch setting for screw constraint."}}, {"update": {"description": "add ability to parse plugin parameters that contains pose elements.\r\n\r\nexpose Joint::SetThreadPitch for screw joints.", "title": "param pose parsing.  exposing thread pitch setting for screw constraint.", "destination": {"commit": {"hash": "274a249a6395", "type": "commit", "links": {"self": {"href": "data/repositories/osrf/gazebo/commit/274a249a6395.json"}, "html": {"href": "#!/osrf/gazebo/commits/274a249a6395"}}}, "repository": {"links": {"self": {"href": "data/repositories/osrf/gazebo.json"}, "html": {"href": "#!/osrf/gazebo"}, "avatar": {"href": "data/bytebucket.org/ravatar/{51a0cd5d-8697-4eb1-8b08-e919ee881e1c}ts=1694483"}}, "type": "repository", "name": "gazebo", "full_name": "osrf/gazebo", "uuid": "{51a0cd5d-8697-4eb1-8b08-e919ee881e1c}"}, "branch": {"name": "dev"}}, "reason": "", "source": {"commit": {"hash": "ace2bae21355", "type": "commit", "links": {"self": {"href": "data/repositories/osrf/gazebo/commit/ace2bae21355.json"}, "html": {"href": "#!/osrf/gazebo/commits/ace2bae21355"}}}, "repository": {"links": {"self": {"href": "data/repositories/osrf/gazebo.json"}, "html": {"href": "#!/osrf/gazebo"}, "avatar": {"href": "data/bytebucket.org/ravatar/{51a0cd5d-8697-4eb1-8b08-e919ee881e1c}ts=1694483"}}, "type": "repository", "name": "gazebo", "full_name": "osrf/gazebo", "uuid": "{51a0cd5d-8697-4eb1-8b08-e919ee881e1c}"}, "branch": {"name": "param_thread_picth_path"}}, "state": "OPEN", "author": {"display_name": "John Hsu", "uuid": "{0a186eae-abf0-4514-a951-23db5eccc286}", "links": {"self": {"href": "https://api.bitbucket.org/2.0/users/%7B0a186eae-abf0-4514-a951-23db5eccc286%7D"}, "html": {"href": "https://bitbucket.org/%7B0a186eae-abf0-4514-a951-23db5eccc286%7D/"}, "avatar": {"href": "https://avatar-management--avatars.us-west-2.prod.public.atl-paas.net/557058:f3968cd3-4910-4384-8349-482a6c7889ec/5445ce6e-6273-47f0-84eb-621c86ca11cb/128"}}, "nickname": "hsu", "type": "user", "account_id": "557058:f3968cd3-4910-4384-8349-482a6c7889ec"}, "date": "2012-11-03T17:32:51.338967+00:00"}, "pull_request": {"type": "pullrequest", "id": 77, "links": {"self": {"href": "data/repositories/osrf/gazebo/pullrequests/77.json"}, "html": {"href": "#!/osrf/gazebo/pull-requests/77"}}, "title": "param pose parsing.  exposing thread pitch setting for screw constraint."}}]}